Workbook

Sheet Personal
A1: DNI | B1: Código | C1: Nombre | D1: Foto | E1: Fecha de Ingreso | F1: Puesto Real | G1: CC Real | H1: Unidad Real | I1: Nombre Host | J1: Nueva Tajeta Micros
A2: 08869374 | B2: 0000F00015 | C2: PINEDA LOPEZ GLADYS DIANA | D2: SI | E2: 35080 | F2: Contralora Regional | G2: Contraloría | H2: Contraloría | I2: LIMCNTCG
A3: 10287285 | B3: 0000000025 | C3: TOULLIER ARTEAGA MIGUEL ANGEL | D3: SI | E3: 35255 | F3: Jefe de Gimnasio | G3: Gym & Spa | H3: División de Habitaciones (Operaciones) | I3: LIMDHGYM
A4: 10479259 | B4: 0000000031 | C4: MEDINA CASTILLO ALVARO GERARDO | D4: SI | E4: 35262 | F4: Sub Gerente de A&B | G4: Gerencia A&B | H4: Alimentos y Bebidas | I4: LIMAYBSGER
A5: 08738298 | B5: 0000F00011 | C5: CASTRO MORA NELLY YOLANDA | D5: SI | E5: 35277 | F5: Gerente de Compras Regional | G5: Compras | H5: Compras | I5: LIMCOMPGCR
A6: 09649733 | B6: 0000000037 | C6: OBARA AVI JUAN FERNANDO | D6: SI | E6: 35278 | F6: Gerente de Compras | G6: Compras | H6: Compras | I6: LIMCOMPGC | Y6: 8va Gen.
A7: 06111494 | B7: 0000000086 | C7: MOTA CASTRO JIM EDUARDO | D7: SI | E7: 35310 | F7: Auditor de Ingresos | G7: Auditoría de Ingresos | H7: Contraloría | I7: LIMCNTAI
A8: 09933993 | B8: 0000000116 | C8: SARMIENTO CONTRERAS RICARDO MARTIN | D8: SI | E8: 35317 | F8: Empleado de Lavanderia | G8: Lavandería | H8: División de Habitaciones (Operaciones) | I8: LIMDH
A9: 22090547 | B9: 0000000232 | C9: SALAS MENDOZA ROMULO OMAR | D9: SI | E9: 35327 | F9: Técnico Electricista | G9: Mantenimiento | H9: Mantenimiento | I9: LIMMANT
A10: 44673548 | B10: 0000001529 | C10: VILCHEZ QUISPE SHEILLA FIORELLA | D10: SI | E10: 44991 | F10: Team Leader de Banquetes | G10: Banquetes | H10: Alimentos y Bebidas | I10: LIMAYBBQ
A11: 09692690 | B11: 0000000269 | C11: VEGA ARRATEA JAVIER VICTOR | D11: SI | E11: 35338 | F11: Supervisor Jr. de Steward | G11: Steward | H11: Alimentos y Bebidas
A12: 08876264 | B12: 0000000260 | C12: SALAS PARRA MONICA | D12: SI | E12: 35339 | F12: Costurero | G12: Housekeeping | H12: División de Habitaciones (Operaciones) | I12: LIMDH
A13: 03822662 | B13: 0000000282 | C13: ACHA ZAPATA JOAQUIN ALEJANDRO | D13: SI | E13: 35345 | F13: Supervisor Senior de Control y Monitoreo | G13: Control y Monitoreo | H13: Control y Monitoreo | I13: LIMCMSCM
A14: 08906688 | B14: 0000000304 | C14: LLANCA ZUÑIGA JIMMY WIELER | D14: SI | E14: 35354 | F14: Técnico de Mantenimiento | G14: Mantenimiento | H14: Mantenimiento | I14: LIMMANT
A15: 09789487 | B15: 0000000323 | C15: HERNANDEZ HERNANDEZ EDILBRANDO | D15: SI | E15: 35370 | F15: Supervisor de Control y Monitoreo | G15: Control y Monitoreo | H15: Control y Monitoreo | I15: LIMCMSCM
A16: 09884050 | B16: 0000000345 | C16: MARTINEZ SOTELO LUIS ENRIQUE | D16: SI | E16: 35401 | F16: Supervisor Senior de Limpieza | G16: Limpieza | H16: División de Habitaciones (Operaciones) | I16: LIMDH
A17: 10793198 | B17: 0000001374 | C17: VIDAL LORENZZI FRANCO | D17: SI | E17: 43640 | F17: Recepcionista | G17: Recepción | H17: División de Habitaciones (Operaciones) | I17: LIMDHREC
A18: 10096345 | B18: 0000000445 | C18: CANO VEGA ALFREDO FRAY | D18: SI | E18: 35583 | F18: Supervisor Jr. De Limpieza | G18: Limpieza | H18: División de Habitaciones (Operaciones) | I18: LIMDH
A19: 08971022 | B19: 0000000508 | C19: VIGO MONTORO LUCIA | D19: SI | E19: 35846 | F19: Empleado de Housekeeping | G19: Housekeeping | H19: División de Habitaciones (Operaciones) | I19: LIMDH
A20: 72787160 | B20: 0000001628 | C20: VERGARA MORENO YADELIN ANAHI | D20: SI | E20: 45482 | F20: Ayudante de Cocina | G20: Cocina La Locanda | H20: Cocina
A21: 10806822 | B21: 0000000423 | C21: UGAZ OLIVARES PALOMA | D21: SI | E21: 37539 | F21: Supervisor Senior de A&B | G21: Lobby | H21: Alimentos y Bebidas
A22: 09398469 | B22: 0000000732 | C22: TELLO FARFAN JAVIER ALEJANDRO | D22: SI | E22: 37956 | F22: Empleado Puesto de Control | G22: Control y Monitoreo | H22: Control y Monitoreo | I22: LIMCMEPC
A23: 41108703 | B23: 0000000735 | C23: VELIZ CHUCO WILIAN | D23: SI | E23: 38054 | F23: Jardinero | G23: Mantenimiento | H23: Mantenimiento | I23: LIMMANT
A24: 25830800 | B24: 0000000736 | C24: PACHAS DELGADO CARMEN ROSA | D24: SI | E24: 38078 | F24: Ejecutiva de Ventas | G24: Ventas | H24: Ventas y Marketing | I24: LIMVMVEN
A25: 40856376 | B25: 0000000772 | C25: CARHUANCOTA CHAVEZ ANDRES ALBERTO | D25: SI | E25: 38596 | F25: Asistente Senior de Contabilidad | G25: Contabilidad | H25: Contraloría | I25: LIMCNTCONT3
A26: 08694596 | B26: 0000000783 | C26: QUISPE LOPEZ RICARDO | D26: SI | E26: 38749 | F26: Limpieza de Cocina | G26: Steward | H26: Alimentos y Bebidas
A27: 40235456 | B27: 0000000806 | C27: TRUJILLO GARAY MONICA ALEJANDRA | D27: SI | E27: 38899 | F27: Gerente de Congresos y Convenciones | G27: Ventas | H27: Ventas y Marketing | I27: LIMVMVEN
A28: 07448369 | B28: 0000000802 | C28: ZAMUDIO VICENTE ANTERO FERNANDO | D28: SI | E28: 38901 | F28: Empleado Puesto de Control | G28: Control y Monitoreo | H28: Control y Monitoreo | I28: LIMCMEPC
A29: 42354767 | B29: 0000000809 | C29: VALDERRAMA ALVAREZ PABLO CESAR | D29: SI | E29: 38915 | F29: Supervisor Senior de Lavanderia | G29: Lavandería | H29: División de Habitaciones (Operaciones) | I29: LIMDHSLV
A30: 09952724 | B30: 0000000834 | C30: MUCHA ROBLES ALEJANDRO CESAR | D30: SI | E30: 39128 | F30: Supervisor Senior de Control y Monitoreo | G30: Control y Monitoreo | H30: Control y Monitoreo | I30: LIMCMSCM
A31: 10093494 | B31: 0000000841 | C31: BERRU DIAZ ALEXANDER HUMBERTO | D31: SI | E31: 39206 | F31: Empleado de Lavanderia | G31: Lavandería | H31: División de Habitaciones (Operaciones) | I31: LIMDH
A32: 15356442 | B32: 0000000844 | C32: MENDIETA SOLANO WILLIAM JESUS | D32: SI | E32: 39206 | F32: Gerente de Control y Monitero | G32: Control y Monitoreo | H32: Control y Monitoreo | I32: LIMCMGCM
A33: 40263172 | B33: 0000000868 | C33: PECHING CHIONG KARINA JANET | D33: SI | E33: 39407 | F33: Gerenta de Reservas | G33: Reservas | H33: Ventas y Marketing | I33: LIMVMRES
A34: 10158051 | B34: 0000000874 | C34: FALCON PAZ JULIAN MIGUEL ANGEL | D34: SI | E34: 39448 | F34: Supervisor Senior de A&B | G34: Banquetes | H34: Alimentos y Bebidas | I34: LIMAYBBQ
A35: 43813442 | B35: 0000000952 | C35: PIPA ACEVEDO RICHARD | D35: SI | E35: 40330 | F35: Carpintero | G35: Mantenimiento | H35: Mantenimiento | I35: LIMMANTGER
A36: 09790217 | B36: 0000000982 | C36: OLIVEROS AGAMA ALEX MARIANO | D36: SI | E36: 40502 | F36: Chofer | G36: Gerencia General | H36: Gerencia General | I36: LIMGGCHO
A37: 40530952 | B37: 0000000993 | C37: CARPIO PONCE GARY ANDRES | D37: SI | E37: 40575 | F37: Bodeguero | G37: Bodegas | H37: Contraloría | I37: LIMCNTBD
A38: 40073853 | B38: 0000001005 | C38: BUENDIA LIMA NILTON HENRY | D38: SI | E38: 40640 | F38: Empleado Puesto de Control | G38: Control y Monitoreo | H38: Control y Monitoreo | I38: LIMCMEPC
A39: 41712577 | B39: 0000001044 | C39: MEJIA VELASQUEZ GONSALO | D39: SI | E39: 40833 | F39: Pintor | G39: Mantenimiento | H39: Mantenimiento | I39: LIMMANT
... A46: 45321314 | B46: 0000001382 | C46: TRUJILLO MILLA JOAN ELIZABETH | D46: SI | E46: 42313 | F46: Empleado de Limpieza | G46: Limpieza | H46: División de Habitaciones (Operaciones) | I46: LIMDH
A47: 40691981 | B47: 0000001222 | C47: LESMA SANTA MARIA CHRISTIAN RAFAEL | D47: SI | E47: 42380 | F47: Chef de Banquetes | G47: Cocina Producción | H47: Cocina
A48: 42368244 | B48: 0000001385 | C48: SIFUENTES DIAZ MARGOT YESENIA | D48: SI | E48: 42394 | F48: Supervisor Cocina La Locanda | G48: Cocina La Locanda | H48: Cocina
A49: 09844674 | C49: VARGAS CACHIQUE ORLANDO FLORENCIO | E49: 45971 | F49: Gerente de Mantenimiento | G49: Mantenimiento | H49: Mantenimiento | I49: LIMMANT
A50: 09928346 | B50: 0000001244 | C50: CUETO LOPEZ VICTOR HUGO | D50: SI | E50: 42552 | F50: Consejero Gastronómico | G50: Room Service | H50: Alimentos y Bebidas
A51: 46524399 | B51: 0000001278 | C51: PAJUELO ANGELES FRANCOIS ERNESTO | D51: SI | E51: 42737 | F51: Empleado de Limpieza | G51: Limpieza | H51: División de Habitaciones (Operaciones) | I51: LIMDH
A52: 41381117 | B52: 0000001283 | C52: NAVEROS CHIRINOS JULIO ALBERTO | D52: SI | E52: 42772 | F52: Supervisor Cocina La Locanda | G52: Cocina La Locanda | H52: Cocina
A53: 41712679 | B53: 0000F00041 | C53: RIOS IGREDA DE HOLLERER CLAUDIA MAGALI | D53: SI | E53: 42835 | F53: Gerenta de Operaciones | G53: Operaciones | H53: División de Habitaciones (Operaciones) | I53: LIMDHOPER
A54: 43828971 | B54: 0000001297 | C54: SICHA PEREZ IRIS GIOVANNA | D54: SI | E54: 42843 | F54: Supervisor Jr. De Housekeeping | G54: Housekeeping | H54: División de Habitaciones (Operaciones) | I54: LIMDH
A55: 71221009 | B55: 0000001292 | C55: CHAUCA CHAQQUERE JORDAN EDUARDO | D55: SI | E55: 42859 | F55: Empleado de Limpieza | G55: Limpieza | H55: División de Habitaciones (Operaciones) | I55: LIMDH
A56: 07622746 | B56: 0000001303 | C56: JAIME ESTABRIDIS FELIX ROBERTO | D56: SI | E56: 42940 | F56: Preparador Fisico | G56: Gym & Spa | H56: División de Habitaciones (Operaciones) | I56: LIMDHGYM
A57: 70067325 | B57: 0000001311 | C57: DIAZ PALACIOS CELESTE MERCEDES | D57: SI | E57: 42985 | F57: Consejero Gastronómico | G57: Le Café | H57: Alimentos y Bebidas
A58: 43513749 | B58: 0000001316 | C58: GONZALES GUERRA DANTE | D58: SI | E58: 43009 | F58: Empleado de Limpieza | G58: Limpieza | H58: División de Habitaciones (Operaciones) | I58: LIMDH
A59: 10086968 | B59: 0000001317 | C59: OCHOA RAYME EDITH BETTY | D59: SI | E59: 43010 | F59: Empleado de Housekeeping | G59: Housekeeping | H59: División de Habitaciones (Operaciones) | I59: LIMDH
A60: 46411356 | B60: 0000001406 | C60: CORDOVA ESTRADA JESUS MARTIN | D60: SI | E60: 43080 | F60: Bodeguero | G60: Bodegas | H60: Contraloría | I60: LIMCNTBD
A61: 40677617 | B61: 0000001326 | C61: POLO CASAFRANCA MARCO | D61: SI | E61: 43102 | F61: Empleado de Housekeeping | G61: Housekeeping | H61: División de Habitaciones (Operaciones) | I61: LIMDH
A62: 60652016 | B62: 0000001408 | C62: GARAY SALAZAR ELLIANE ANNEL | D62: SI | E62: 43118 | F62: Supervisor Cocina Fria | G62: Cocina Fría | H62: Cocina
A63: 70005695 | B63: 0000001335 | C63: CARBAJAL BRAVO ROMMEL MARTIN | D63: SI | E63: 43185 | F63: Gerente de Turno | G63: Recepción | H63: División de Habitaciones (Operaciones) | I63: LIMDHREC
A64: 44118819 | B64: 0000001420 | C64: HINOSTROZA CRUZ JOSE LUIS | D64: SI | E64: 43215 | F64: Empleado de Housekeeping | G64: Housekeeping | H64: División de Habitaciones (Operaciones) | I64: LIMDH
A65: 43329158 | B65: 0000001417 | C65: CARDENAS ALCAZABA PAOLA RAQUEL | D65: SI | E65: 43215 | F65: Supervisor Jr. De Housekeeping | G65: Housekeeping | H65: División de Habitaciones (Operaciones) | I65: LIMDHHK01
A66: 44910871 | B66: 0000001428 | C66: CARRILLO SILVA ENRIQUE RAFAEL | D66: SI | E66: 43297 | F66: Botones | G66: Recepción | H66: División de Habitaciones (Operaciones) | I66: LIMDHREC
A67: 48136066 | B67: 0000001429 | C67: LIZARZABURU COLAN CLAUDIA IRINNA | D67: SI | E67: 43297 | F67: Empleado de Lavanderia | G67: Lavandería | H67: División de Habitaciones (Operaciones) | I67: LIMDH
A68: 48198139 | B68: 0000001351 | C68: FERNANDEZ ALBERCA JORDANS JORGE LUIS | D68: SI | E68: 43320 | F68: Gerente de Turno | G68: Recepción | H68: División de Habitaciones (Operaciones) | I68: LIMDHREC
A69: 46421369 | B69: 0000001207 | C69: LOZADA PAREDES LIZBETH | D69: SI | E69: 43321 | F69: Ejecutiva de Eventos | G69: Ventas | H69: Ventas y Marketing | I69: LIMVMVEN
A70: 75624465 | B70: 0000001434 | C70: CARDENAS CARDENAS JESUS JUNIOR | D70: SI | E70: 43339 | F70: Recepcionista | G70: Recepción | H70: División de Habitaciones (Operaciones) | I70: LIMDHREC
A71: 10710564 | B71: 0000000875 | C71: COBOS GRANDA GLADYS EDITH | D71: SI | E71: 43367 | F71: Gerente de Capacitación y Desarrollo | G71: Personas y Cultura | H71: Personas y Cultura | I71: LIMPCGCD
A72: 60005193 | B72: 0000001441 | C72: ORIHUELA CARHUALLANQUI ROSMERY | D72: SI | E72: 43367 | F72: Supervisor de A&B | G72: La Fondue | H72: Alimentos y Bebidas
A73: 75623367 | B73: 0000001439 | C73: GOMEZ COBEÑA PERCY BOLIVAR | D73: SI | E73: 43367 | F73: Capitán de Banquetes | G73: Banquetes | H73: Alimentos y Bebidas | I73: LIMAYBBQ
A74: 71544844 | B74: 0000001448 | C74: CHAVEZ LING SUSANA BETSABE | D74: SI | E74: 43425 | F74: Supervisor Pasteleria / Panadería | G74: Pastelería | H74: Cocina
A75: 46333532 | B75: 0000001365 | C75: CANCHO VELIT MARCO ANTONIO | D75: SI | E75: 43517 | F75: Técnico de Mantenimiento | G75: Mantenimiento | H75: Mantenimiento | I75: LIMMANT
A76: 70022345 | B76: 0000001457 | C76: MENDOZA LLANTAY VICTOR ANGEL | D76: SI | E76: 43557 | F76: Empleado de Lavanderia | G76: Lavandería | H76: División de Habitaciones (Operaciones) | I76: LIMDH
A77: 73539255 | B77: 0000001458 | C77: QUISPE CANCHARI JOSE ALBERTO | D77: SI | E77: 43557 | F77: Empleado de Lavanderia | G77: Lavandería | H77: División de Habitaciones (Operaciones) | I77: LIMDH
A78: 46960867 | B78: 0000001462 | C78: HUAPAYA PEREZ LUIS ANGEL | D78: SI | E78: 43584 | F78: Supervisor de A&B | G78: Room Service | H78: Alimentos y Bebidas
A79: 75173008 | B79: 0000001577 | C79: RAFAELO LORENZO ANA ROSA | D79: SI | E79: 45356 | F79: Asistente de Coordinación | G79: Ventas | H79: Ventas y Marketing | I79: LIMVMAC
A80: 75965593 | B80: 0000001461 | C80: CCORAHUA PEÑA VICTOR HUGO | D80: SI | E80: 43584 | F80: Limpieza de Cocina | G80: Steward | H80: Alimentos y Bebidas
A81: 001007594 | B81: 0000F00031 | C81: VILLACIS PAREDES MARIA DE LOS ANGELES | D81: NA | E81: 43600 | F81: Directora Regional de Revenue | G81: Revenue | H81: Ventas y Marketing | I81: LIMVMREV
A82: 09457769 | B82: 0000000438 | C82: ORELLANA GODOY MELCHORA OLINDA | D82: SI | E82: 35566 | F82: Contador | G82: Contabilidad | H82: Contraloría | I82: LIMCNTCONT1
A83: 44260173 | B83: 0000001151 | C83: LUNA MARIÑO FANNY ISABEL | D83: SI | E83: 43851 | F83: Jefe de Recepción | G83: Recepción | H83: División de Habitaciones (Operaciones) | I83: LIMDHREC
A84: 25728850 | B84: 0000001491 | C84: GAMBONI KOIFMAN DE TENORIO SANCHO DAVI C | D84: SI | E84: 44445 | F84: Asistente de Gerencia General | G84: Gerencia General | H84: Gerencia General | I84: LIMGGAGG
A85: 000042032 | B85: 0000F00013 | C85: SPIELVOGEL XXXX FRANK | D85: NA | E85: 44467 | F85: Gerente General | G85: Gerencia General | H85: Gerencia General | I85: LIMGG
A86: 47156230 | B86: 0000001236 | C86: BAUTISTA CARDENAS MIGUEL ALEJANDRO | D86: SI | E86: 44531 | F86: Sub Chef | G86: Cocina La Locanda | H86: Cocina
A87: 44817223 | B87: 0000001496 | C87: GAMARRA MARCELO TONY EISNTEIN | D87: SI | E87: 44606 | F87: Técnico Electricista | G87: Mantenimiento | H87: Mantenimiento | I87: LIMMANT
A88: 02856974 | B88: 0000001501 | C88: YAMUNAQUE CASTILLO HECTOR ARTURO | D88: SI | E88: 44697 | F88: Gerente de Sistemas | G88: Tecnologias de Información | H88: Tecnologias de Información | I88: LIMTIGT
A89: 46376235 | B89: 0000001505 | C89: PASAPERA ROMAN MANUEL ADRIAN | D89: SI | E89: 44711 | F89: Técnico Sanitario | G89: Mantenimiento | H89: Mantenimiento | I89: LIMMANT
A90: 45809468 | B90: 0000001510 | C90: CHAVEZ CRUZ MARITZA DINA | D90: SI | E90: 44816 | F90: Ejecutiva de Ventas | G90: Ventas | H90: Ventas y Marketing | I90: LIMVMVEN
A91: 76698020 | B91: 0000001512 | C91: SAMAME MERA YOSEMAR | D91: SI | E91: 44816 | F91: Ayudante de Cocina | G91: Cocina La Locanda | H91: Cocina
A92: 44588268 | B92: 0000001511 | C92: HINOSTROZA TOCCAS MIGUEL ANGEL | D92: SI | E92: 44816 | F92: Supervisor Cocina Producción | G92: Cocina Producción | H92: Cocina
A93: 74404325 | B93: 0000001513 | C93: RODRIGUEZ ROJAS JEAN PIERRE | D93: SI | E93: 44819 | F93: Cocinero 1 | G93: Cocina Le Café | H93: Cocina
A94: 44247838 | B94: 0000001516 | C94: ROQUE SILVA TANIA MARYORI | D94: SI | E94: 44830 | F94: Agente de Reservas | G94: Reservas | H94: Ventas y Marketing | I94: LIMVMRES
A95: 42356973 | B95: 0000001520 | C95: ROMERO ORTIZ ALEX ARGENIS | D95: SI | E95: 44883 | F95: Pastelero 1 | G95: Pastelería | H95: Cocina
A96: 44543975 | B96: 0000001522 | C96: GUIDOTTI BOSSIO OSCAR OSMAR | D96: SI | E96: 44893 | F96: Gerente de Turno | G96: Recepción | H96: División de Habitaciones (Operaciones) | I96: LIMDHREC
A97: 46885186 | B97: 0000001527 | C97: MECHATO VILCAPOMA MARCIA LUISA | D97: SI | E97: 44963 | F97: Ejecutiva de Eventos | G97: Ventas | H97: Ventas y Marketing | I97: LIMVMVEN
A98: 74915395 | B98: 0000P00661 | C98: ORELLANA CHIPANA MARTIN SANTIAGO | D98: SI | E98: 45397 | F98: Practicante de Contabilidad | G98: Contabilidad | H98: Contraloría | I98: LIMCNTCONT6
A99: 76211885 | B99: 0000001539 | C99: HERRERA SOLIS CLAUDIA DANIELA FELICITA | D99: SI | E99: 45069 | F99: Restaurant Manager | G99: La Locanda | H99: Alimentos y Bebidas | I99: LIMAYBLL
A100: 72266940 | B100: 0000001540 | C100: VARGAS VILCA ANA GABRIELA | D100: SI | E100: 45078 | F100: Empleado de Housekeeping | G100: Housekeeping | H100: División de Habitaciones (Operaciones) | I100: LIMDH
A101: 74649557 | B101: 0000001542 | C101: RODRIGUEZ ESPINOZA CYANE MILAGROS | D101: SI | E101: 45078 | F101: Consejero Gastronómico | G101: Piso Ejecutivo | H101: Alimentos y Bebidas
A102: 43860201 | B102: 0000001546 | C102: ALCANTARA RONDO SERGIO MANUEL | D102: SI | E102: 45110 | F102: Recepcionista | G102: Recepción | H102: División de Habitaciones (Operaciones) | I102: LIMDHREC
A103: 40728257 | B103: 0000001548 | C103: QUINTANA TALLEDO ANGELA VIRGINIA | D103: SI | E103: 45110 | F103: Ejecutiva de Eventos | G103: Ventas | H103: Ventas y Marketing | I103: LIMVMVEN
A104: 45933007 | B104: 0000001551 | C104: ABAD PALOMINO BRYAN DEIVY | D104: SI | E104: 45131 | F104: Consejero Gastronómico | G104: Room Service | H104: Alimentos y Bebidas
A105: 74602111 | B105: 0000001552 | C105: ZARATE CHACON LUZ ANGELINA | D105: SI | E105: 45139 | F105: Panadero 1 | G105: Pastelería | H105: Cocina
A106: 40611017 | B106: 0000001553 | C106: DAVILA GUERRERO DIANA MARIELLA | D106: SI | E106: 45139 | F106: Ejecutiva de Ventas Senior | G106: Ventas | H106: Ventas y Marketing | I106: LIMVMVEN
...

Sheet InventarioSwiss
G2: Inventario Equipos TI
AO4: 6 | AP4: 7 | AQ4: 8
B5: Item | C5: Fecha | D5: Pedido | E5: Orden de Compra | F5: GR - Movistar | G5: Equipo | H5: Tipo | I5: Marca | J5: Modelo | K5: S/N | L5: P/N | M5: Operador | N5: Linea | O5: IMEI1 | P5: IMEI2 | Q5: Cuenta Gmail | R5: Clave Gmail | S5: Mac Address | T5: Mac Address - Wifi | U5: IP | V5: Nombre Host | W5: Nuevo Nombre Host | X5: Procesador | Y5: Generación Procesador | Z5: Chip Video | AA5: Ram | AB5: Ram Actual | AC5: Almacenamiento | AD5: Pantalla | AE5: Sistema Operativo | AF5: Antivirus | AG5: Office | AH5: Fech. Ini Garantía | AI5: Fech. Fin Garantía | AJ5: Propiedad | AK5: Estado | AL5: DNI | AM5: Código | AN5: Usuario | AO5: Cargo | AP5: Centro de Costo | AQ5: Unidad | AR5: Observación
B6: 1 | G6: Laptop | H6: Usuario | I6: HP | J6: Notebook HP -15 | K6: CND8322H3N | L6: 3PX38LA | S6: 50-91-E3-FC-3F-ED | T6: D0-C5-D3-21-1D-29 | U6: 10.72.10.168 | V6: LIMIT01 | X6: Intel Core i7 | Y6: 8va Gen. | Z6: NVIDEA | AA6: 32 GB DDR4 | AC6: 480 GB SSD | AD6: 15" | AE6: Windows 11 Pro | AF6: Pendiente | AG6: MS Office 2007 HB | AH6: 44927 | AJ6: HOTELERA COSTA DEL PACIFICO | AK6: Operativo | AL6: 43488382 | AM6: =VLOOKUP(AL6,Personal!$A$2:$I$300,2,FALSE) -> 0000001736 | AN6: =VLOOKUP(AL6,Personal!$A$2:$I$300,3,FALSE) -> SALINAS TORRES NOE | AO6: =VLOOKUP(AL6,Personal!$A$2:$I$300,6,FALSE) -> Analista de Sistemas | AP6: =VLOOKUP(AL6,Personal!$A$2:$I$300,7,FALSE) -> Tecnologias de Información | AQ6: =VLOOKUP(AL6,Personal!$A$2:$I$300,8,FALSE) -> Tecnologias de Información
B7: 2 | G7: Monitor | H7: Usuario | I7: Samsung | J7: S27E370D | K7: 0NWEHTHH600028Y | AD7: 27" | AJ7: HOTELERA COSTA DEL PACIFICO | AK7: Operativo | AL7: 43488382 | AM7: =VLOOKUP(AL7,Personal!$A$2:$I$300,2,FALSE) -> 0000001736 | AN7: =VLOOKUP(AL7,Personal!$A$2:$I$300,3,FALSE) -> SALINAS TORRES NOE | AO7: =VLOOKUP(AL7,Personal!$A$2:$I$300,6,FALSE) -> Analista de Sistemas | AP7: =VLOOKUP(AL7,Personal!$A$2:$I$300,7,FALSE) -> Tecnologias de Información | AQ7: =VLOOKUP(AL7,Personal!$A$2:$I$300,8,FALSE) -> Tecnologias de Información
B8: 3 | G8: Parlantes | H8: Usuario | I8: Samsung | J8: HW-J250 | K8: 0BE814MJ200528E | AJ8: HOTELERA COSTA DEL PACIFICO | AK8: Operativo | AL8: 43488382 | AM8: =VLOOKUP(AL8,Personal!$A$2:$I$300,2,FALSE) -> 0000001736 | AN8: =VLOOKUP(AL8,Personal!$A$2:$I$300,3,FALSE) -> SALINAS TORRES NOE | AO8: =VLOOKUP(AL8,Personal!$A$2:$I$300,6,FALSE) -> Analista de Sistemas | AP8: =VLOOKUP(AL8,Personal!$A$2:$I$300,7,FALSE) -> Tecnologias de Información | AQ8: =VLOOKUP(AL8,Personal!$A$2:$I$300,8,FALSE) -> Tecnologias de Información
B9: 4 | G9: Celular | H9: Usuario | I9: ZTE | J9: ZTE Blade A55 | K9: LZ0A55PEDC8002023 | M9: Movistar | N9: 965647947 | O9: 860590070432272 | T9: 54-1F-8D-A0-17-C3 | X9: Movil | AA9: 4GB | AC9: 128 GB | AD9: 6.75" | AE9: Android | AJ9: HOTELERA COSTA DEL PACIFICO | AK9: Operativo | AL9: 10158051 | AM9: =VLOOKUP(AL9,Personal!$A$2:$I$300,2,FALSE) -> 0000000874 | AN9: =VLOOKUP(AL9,Personal!$A$2:$I$300,3,FALSE) -> FALCON PAZ JULIAN MIGUEL ANGEL | AO9: =VLOOKUP(AL9,Personal!$A$2:$I$300,6,FALSE) -> Supervisor Senior de A&B | AP9: =VLOOKUP(AL9,Personal!$A$2:$I$300,7,FALSE) -> Banquetes | AQ9: =VLOOKUP(AL9,Personal!$A$2:$I$300,8,FALSE) -> Alimentos y Bebidas
B10: 5 | G10: Laptop | H10: Usuario | I10: Toshiba | J10: PORTEGE-R930-SP3256KL | K10: YD039184H | L10: PT331P-0KW0GT | S10: B8-6B-23-AD-0C-20 | T10: B4-B6-76-FB-46-4F | X10: Intel Core i5 | Y10: 3era Gen. | Z10: Intel Integrado | AA10: 8 GB DDR3 | AC10: 500 GB HDD | AD10: 14" | AE10: Windows 11 Pro | AF10: Pendiente | AJ10: HOTELERA COSTA DEL PACIFICO | AK10: Custodia - Operativo | AL10: Sistemas | AM10: =VLOOKUP(AL10,Personal!$A$2:$I$300,2,FALSE) -> 0 | AN10: =VLOOKUP(AL10,Personal!$A$2:$I$300,3,FALSE) -> Tecnologias de Información | AO10: =VLOOKUP(AL10,Personal!$A$2:$I$300,6,FALSE) -> Tecnologias de Información | AP10: =VLOOKUP(AL10,Personal!$A$2:$I$300,7,FALSE) -> Tecnologias de Información | AQ10: =VLOOKUP(AL10,Personal!$A$2:$I$300,8,FALSE) -> Tecnologias de Información | AR10: Falta cover que tapa la memoria ram.
B11: 6 | G11: PC | H11: Usuario | I11: Lenovo | J11: Thinkcentre Neo 50S | K11: YLT1642S | L11: 12XG0015LS | U11: 10.72.10.177 | W11: LIMCNTSC | X11: Intel Core i7 | Y11: 14va Gen. | Z11: Intel Integrado | AA11: 16 GB DDR5 | AC11: 480 GB SSD | AE11: Windows 11 Pro | AF11: Si | AG11: MS Office 365 HB | AJ11: HOTELERA COSTA DEL PACIFICO | AK11: Operativo | AL11: 10590738 | AM11: =VLOOKUP(AL11,Personal!$A$2:$I$300,2,FALSE) -> 0 | AN11: =VLOOKUP(AL11,Personal!$A$2:$I$300,3,FALSE) -> ALVARADO CHAVARRY JIMMY GERARDO | AO11: =VLOOKUP(AL11,Personal!$A$2:$I$300,6,FALSE) -> Sub Contralor | AP11: =VLOOKUP(AL11,Personal!$A$2:$I$300,7,FALSE) -> Contabilidad | AQ11: =VLOOKUP(AL11,Personal!$A$2:$I$300,8,FALSE) -> Contraloría
B12: 7 | G12: PC | H12: Usuario | I12: Lenovo | J12: Thinkcentre Neo 50S | K12: YLT16443 | L12: 12XG0015LS | S12: D0-F4-05-3E-74-C1 | T12: E4-1F-D5-E8-9F-CC | U12: 10.72.10.146 | W12: LIMFD02 | X12: Intel Core i7 | Y12: 14va Gen. | Z12: Intel Integrado | AA12: 32 GB DDR5 | AC12: 1000 GB SSD | AE12: Windows 11 Pro | AF12: Si | AG12: MS Office 2007 HB | AJ12: HOTELERA COSTA DEL PACIFICO | AK12: Operativo | AL12: Front Desk 2 | AM12: =VLOOKUP(AL12,Personal!$A$2:$I$300,2,FALSE) -> Front Desk | AN12: =VLOOKUP(AL12,Personal!$A$2:$I$300,3,FALSE) -> Front Desk 2 | AO12: =VLOOKUP(AL12,Personal!$A$2:$I$300,6,FALSE) -> Recepcionista | AP12: =VLOOKUP(AL12,Personal!$A$2:$I$300,7,FALSE) -> Recepción | AQ12: =VLOOKUP(AL12,Personal!$A$2:$I$300,8,FALSE) -> División de Habitaciones (Operaciones) | AR12: Para Front Desk
B13: 8 | G13: PC | H13: Usuario | I13: Dell | J13: Optiplex 3020 | K13: 355VN22 | L13: 0WMJ54 | U13: 10.72.10.162 | W13: LIMVMVEN14 | X13: Intel Core i5 | Y13: 5ta Gen. | Z13: Intel Integrado | AA13: 12 GB DDR3 | AC13: 480 GB SSD | AE13: Windows 11 Pro | AF13: Si | AG13: MS Office 2007 HB | AH13: 41926 | AJ13: HOTELERA COSTA DEL PACIFICO | AK13: Operativo | AL13: 74129212 | AM13: =VLOOKUP(AL13,Personal!$A$2:$I$300,2,FALSE) -> 0000P00764 | AN13: =VLOOKUP(AL13,Personal!$A$2:$I$300,3,FALSE) -> VIDAL TAPIA ARIANA FERNANDA VALERIA | AO13: =VLOOKUP(AL13,Personal!$A$2:$I$300,6,FALSE) -> Practicante de Ventas y Marketing | AP13: =VLOOKUP(AL13,Personal!$A$2:$I$300,7,FALSE) -> Ventas | AQ13: =VLOOKUP(AL13,Personal!$A$2:$I$300,8,FALSE) -> Ventas y Marketing | AR13: Equipo con etiqueta de Finanzas
B14: 9 | G14: PC | H14: Usuario | I14: Dell | J14: Optiplex 3020 | K14: D08SN22 | L14: 0WMJ54 | U14: 10.72.10.173 | W14: LIMVMAC | X14: Intel Core i5 | Y14: 5ta Gen. | Z14: Intel Integrado | AA14: 8 GB DDR3 | AC14: 480 GB SSD | AE14: Windows 11 Pro | AF14: Si | AG14: MS Office 2007 HB | AH14: 41923 | AJ14: HOTELERA COSTA DEL PACIFICO | AK14: Operativo | AL14: 75173008 | AM14: =VLOOKUP(AL14,Personal!$A$2:$I$300,2,FALSE) -> 0000001577 | AN14: =VLOOKUP(AL14,Personal!$A$2:$I$300,3,FALSE) -> RAFAELO LORENZO ANA ROSA | AO14: =VLOOKUP(AL14,Personal!$A$2:$I$300,6,FALSE) -> Asistente de Coordinación | AP14: =VLOOKUP(AL14,Personal!$A$2:$I$300,7,FALSE) -> Ventas | AQ14: =VLOOKUP(AL14,Personal!$A$2:$I$300,8,FALSE) -> Ventas y Marketing
B15: 10 | G15: PC | H15: Usuario | I15: Dell | J15: Optiplex 3020 | K15: CZZFN22 | L15: 0WMJ54 | U15: 10.72.10.129 | W15: LIMCNTCONT8 | X15: Intel Core i5 | Y15: 5ta Gen. | Z15: Intel Integrado | AA15: 16 GB DDR3 | AC15: 480 GB SSD | AE15: Windows 11 Pro | AF15: Si | AH15: 41923 | AJ15: HOTELERA COSTA DEL PACIFICO | AK15: Operativo | AL15: 76644092 | AM15: =VLOOKUP(AL15,Personal!$A$2:$I$300,2,FALSE) -> 0000P00758 | AN15: =VLOOKUP(AL15,Personal!$A$2:$I$300,3,FALSE) -> MILLA GOMEZ ANJALI ABIGAIL | AO15: =VLOOKUP(AL15,Personal!$A$2:$I$300,6,FALSE) -> Practicante de Contabilidad | AP15: =VLOOKUP(AL15,Personal!$A$2:$I$300,7,FALSE) -> Contabilidad | AQ15: =VLOOKUP(AL15,Personal!$A$2:$I$300,8,FALSE) -> Contraloría
B16: 11 | G16: PC | H16: Servidor | I16: Dell | J16: Optiplex 3020 | K16: D0DHN22 | L16: 0WMJ54 | S16: B0-83-FE-5E-0A-B9 | U16: 10.72.8.115 | W16: LIMH1SVRCONAC | X16: Intel Core i5 | Y16: 5ta Gen. | Z16: Intel Integrado | AA16: 12 GB DDR3 | AC16: 480 GB SSD | AE16: Windows 11 Pro | AF16: Si | AG16: MS Office 2007 HB | AH16: 41923 | AJ16: HOTELERA COSTA DEL PACIFICO | AK16: Operativo | AL16: Sistemas | AM16: =VLOOKUP(AL16,Personal!$A$2:$I$300,2,FALSE) -> 0 | AN16: =VLOOKUP(AL16,Personal!$A$2:$I$300,3,FALSE) -> Tecnologias de Información | AO16: =VLOOKUP(AL16,Personal!$A$2:$I$300,6,FALSE) -> Tecnologias de Información | AP16: =VLOOKUP(AL16,Personal!$A$2:$I$300,7,FALSE) -> Tecnologias de Información | AQ16: =VLOOKUP(AL16,Personal!$A$2:$I$300,8,FALSE) -> Tecnologias de Información | AR16: Integrador Contastec con Opera Cloud - FACT. ELECT
B17: 12 | G17: PC | H17: Usuario | I17: Dell | J17: Optiplex 3020 | K17: CZNGN22 | L17: 0WMJ54 | AH17: 41923 | AJ17: HOTELERA COSTA DEL PACIFICO | AK17: Custodia - Por Revisar | AL17: Sistemas | AM17: =VLOOKUP(AL17,Personal!$A$2:$I$300,2,FALSE) -> 0 | AN17: =VLOOKUP(AL17,Personal!$A$2:$I$300,3,FALSE) -> Tecnologias de Información | AO17: =VLOOKUP(AL17,Personal!$A$2:$I$300,6,FALSE) -> Tecnologias de Información | AP17: =VLOOKUP(AL17,Personal!$A$2:$I$300,7,FALSE) -> Tecnologias de Información | AQ17: =VLOOKUP(AL17,Personal!$A$2:$I$300,8,FALSE) -> Tecnologias de Información
B18: 13 | G18: PC | H18: Usuario | I18: Dell | J18: Optiplex 3020 | K18: D1BGN22 | L18: 0WMJ54 | X18: Intel Core i5 | Y18: 5ta Gen. | Z18: Intel Integrado | AF18: Pendiente | AH18: 41925 | AJ18: HOTELERA COSTA DEL PACIFICO | AK18: Custodia - Por Revisar | AL18: Sistemas | AM18: =VLOOKUP(AL18,Personal!$A$2:$I$300,2,FALSE) -> 0 | AN18: =VLOOKUP(AL18,Personal!$A$2:$I$300,3,FALSE) -> Tecnologias de Información | AO18: =VLOOKUP(AL18,Personal!$A$2:$I$300,6,FALSE) -> Tecnologias de Información | AP18: =VLOOKUP(AL18,Personal!$A$2:$I$300,7,FALSE) -> Tecnologias de Información | AQ18: =VLOOKUP(AL18,Personal!$A$2:$I$300,8,FALSE) -> Tecnologias de Información
B19: 14 | G19: PC | H19: Usuario | I19: Dell | J19: Optiplex 3020 | K19: D1BSN22 | L19: 0WMJ54 | S19: B0-83-FE-55-28-CD | U19: 10.72.10.109 | W19: LIMCMSCM01 | X19: Intel Core i5 | Y19: 5ta Gen. | Z19: Intel Integrado | AA19: 16 GB DDR3 | AC19: 480 GB SSD | AE19: Windows 11 Pro | AF19: Si | AH19: 41923 | AJ19: HOTELERA COSTA DEL PACIFICO | AK19: Operativo | AL19: CyM | AM19: =VLOOKUP(AL19,Personal!$A$2:$I$300,2,FALSE) -> 0 | AN19: =VLOOKUP(AL19,Personal!$A$2:$I$300,3,FALSE) -> Control y Monitoreo | AO19: =VLOOKUP(AL19,Personal!$A$2:$I$300,6,FALSE) -> Empleado Puesto de Control | AP19: =VLOOKUP(AL19,Personal!$A$2:$I$300,7,FALSE) -> Control y Monitoreo | AQ19: =VLOOKUP(AL19,Personal!$A$2:$I$300,8,FALSE) -> Control y Monitoreo
B20: 15 | G20: PC | H20: Usuario | I20: Dell | J20: Optiplex 3020 | K20: D00RN22 | L20: 0WMJ54 | S20: B0-83-FE-5E-E5-BC | U20: 10.72.10.103 | W20: LIMAYBSGER | X20: Intel Core i5 | Y20: 5ta Gen. | Z20: Intel Integrado | AA20: 16 GB DDR3 | AC20: 480 GB SSD | AE20: Windows 11 Pro | AF20: Si | AG20: MS Office 365 HB | AH20: 41923 | AJ20: HOTELERA COSTA DEL PACIFICO | AK20: Operativo | AL20: 10479259 | AM20: =VLOOKUP(AL20,Personal!$A$2:$I$300,2,FALSE) -> 0000000031 | AN20: =VLOOKUP(AL20,Personal!$A$2:$I$300,3,FALSE) -> MEDINA CASTILLO ALVARO GERARDO | AO20: =VLOOKUP(AL20,Personal!$A$2:$I$300,6,FALSE) -> Sub Gerente de A&B | AP20: =VLOOKUP(AL20,Personal!$A$2:$I$300,7,FALSE) -> Gerencia A&B | AQ20: =VLOOKUP(AL20,Personal!$A$2:$I$300,8,FALSE) -> Alimentos y Bebidas
B21: 16 | G21: PC | H21: Usuario | I21: Dell | J21: Optiplex 3020 | K21: D04SN22 | L21: 0WMJ54 | U21: 10.72.10.120 | W21: LIMSMGCC | X21: Intel Core i5 | Y21: 5ta Gen. | Z21: Intel Integrado | AA21: 16 GB DDR3 | AC21: 480 GB SSD | AE21: Windows 11 Pro | AF21: Si | AG21: MS Office 2007 HB | AH21: 41923 | AJ21: HOTELERA COSTA DEL PACIFICO | AK21: Operativo | AL21: 40235456 | AM21: =VLOOKUP(AL21,Personal!$A$2:$I$300,2,FALSE) -> 0000000806 | AN21: =VLOOKUP(AL21,Personal!$A$2:$I$300,3,FALSE) -> TRUJILLO GARAY MONICA ALEJANDRA | AO21: =VLOOKUP(AL21,Personal!$A$2:$I$300,6,FALSE) -> Gerente de Congresos y Convenciones | AP21: =VLOOKUP(AL21,Personal!$A$2:$I$300,7,FALSE) -> Ventas | AQ21: =VLOOKUP(AL21,Personal!$A$2:$I$300,8,FALSE) -> Ventas y Marketing
B22: 17 | G22: PC | H22: Usuario | I22: Dell | J22: Optiplex 3020 | K22: GK1TN22 | L22: 0WMJ54 | X22: Intel Core i5 | Y22: 5ta Gen. | Z22: Intel Integrado | AA22: 16 GB DDR3 | AE22: Windows 11 Pro | AF22: Pendiente | AH22: 41925 | AJ22: HOTELERA COSTA DEL PACIFICO | AK22: Custodia - Operativo | AL22: Sistemas | AM22: =VLOOKUP(AL22,Personal!$A$2:$I$300,2,FALSE) -> 0 | AN22: =VLOOKUP(AL22,Personal!$A$2:$I$300,3,FALSE) -> Tecnologias de Información | AO22: =VLOOKUP(AL22,Personal!$A$2:$I$300,6,FALSE) -> Tecnologias de Información | AP22: =VLOOKUP(AL22,Personal!$A$2:$I$300,7,FALSE) -> Tecnologias de Información | AQ22: =VLOOKUP(AL22,Personal!$A$2:$I$300,8,FALSE) -> Tecnologias de Información | AR22: Para asignar Ventas
B23: 18 | G23: Tablet | H23: Usuario | I23: Lenovo | J23: A7600-F | K23: HJH0ATGD | T23: 60-D9-A0-20-3A7F | X23: Movil | AA23: 1GB | AC23: 16 GB | AD23: 10" | AE23: Android | AF23: N/A | AJ23: HOTELERA COSTA DEL PACIFICO | AK23: Custodia - Obsoleto | AL23: Sistemas | AM23: =VLOOKUP(AL23,Personal!$A$2:$I$300,2,FALSE) -> 0 | AN23: =VLOOKUP(AL23,Personal!$A$2:$I$300,3,FALSE) -> Tecnologias de Información | AO23: =VLOOKUP(AL23,Personal!$A$2:$I$300,6,FALSE) -> Tecnologias de Información | AP23: =VLOOKUP(AL23,Personal!$A$2:$I$300,7,FALSE) -> Tecnologias de Información | AQ23: =VLOOKUP(AL23,Personal!$A$2:$I$300,8,FALSE) -> Tecnologias de Información | AR23: SIN CARGADOR
B24: 19 | G24: PC | H24: Usuario | I24: Gigabyte | J24: GB-BSi3H-6100 | K24: 1601631981 | X24: Intel Core i3 | Y24: 6ta Gen. | Z24: Intel Integrado | AA24: 8 GB DDR3 | AC24: 480 GB SSD | AE24: Windows 11 Pro | AF24: Pendiente | AJ24: HOTELERA COSTA DEL PACIFICO | AK24: Custodia - Operativo | AL24: Sistemas | AM24: =VLOOKUP(AL24,Personal!$A$2:$I$300,2,FALSE) -> 0 | AN24: =VLOOKUP(AL24,Personal!$A$2:$I$300,3,FALSE) -> Tecnologias de Información | AO24: =VLOOKUP(AL24,Personal!$A$2:$I$300,6,FALSE) -> Tecnologias de Información | AP24: =VLOOKUP(AL24,Personal!$A$2:$I$300,7,FALSE) -> Tecnologias de Información | AQ24: =VLOOKUP(AL24,Personal!$A$2:$I$300,8,FALSE) -> Tecnologias de Información | AR24: SE USARA PARA CLONACION DE IMÁGENES WINDOWS
B25: 20 | G25: PC | H25: Usuario | I25: Gigabyte | J25: GB-BSi3H-6100 | K25: 1601631938 | X25: Intel Core i3 | Y25: 6ta Gen. | Z25: Intel Integrado | AJ25: HOTELERA COSTA DEL PACIFICO | AK25: Custodia - Por Revisar | AL25: Sistemas | AM25: =VLOOKUP(AL25,Personal!$A$2:$I$300,2,FALSE) -> 0 | AN25: =VLOOKUP(AL25,Personal!$A$2:$I$300,3,FALSE) -> Tecnologias de Información | AO25: =VLOOKUP(AL25,Personal!$A$2:$I$300,6,FALSE) -> Tecnologias de Información | AP25: =VLOOKUP(AL25,Personal!$A$2:$I$300,7,FALSE) -> Tecnologias de Información | AQ25: =VLOOKUP(AL25,Personal!$A$2:$I$300,8,FALSE) -> Tecnologias de Información
B26: 21 | G26: PC | H26: Usuario | I26: Lenovo | J26: Thinkcentre Neo 50S | K26: YLT16FYF | L26: 12XG0015LS | S26: D0-F4-05-3F-CC-11 | T26: 9C-67-D6-78-99-A2 | X26: Intel Core i7 | Y26: 14va Gen. | Z26: Intel Integrado | AA26: 32 GB DDR3 | AC26: 1000 GB SSD | AE26: Windows 11 Pro | AF26: Pendiente | AJ26: HOTELERA COSTA DEL PACIFICO | AK26: Custodia - Operativo | AL26: Sistemas | AM26: =VLOOKUP(AL26,Personal!$A$2:$I$300,2,FALSE) -> 0 | AN26: =VLOOKUP(AL26,Personal!$A$2:$I$300,3,FALSE) -> Tecnologias de Información | AO26: =VLOOKUP(AL26,Personal!$A$2:$I$300,6,FALSE) -> Tecnologias de Información | AP26: =VLOOKUP(AL26,Personal!$A$2:$I$300,7,FALSE) -> Tecnologias de Información | AQ26: =VLOOKUP(AL26,Personal!$A$2:$I$300,8,FALSE) -> Tecnologias de Información | AR26: Para Contabilidad
B27: 22 | G27: PC | H27: Usuario | I27: Toshiba | J27: PORTEGE-R930-SP3256KL | K27: YD039215H | L27: PT331P-0KW0GT | X27: Intel Core i5 | Y27: 3era Gen. | Z27: Intel Integrado | AF27: N/A | AJ27: HOTELERA COSTA DEL PACIFICO | AK27: Custodia - Inoperativo | AL27: Sistemas | AM27: =VLOOKUP(AL27,Personal!$A$2:$I$300,2,FALSE) -> 0 | AN27: =VLOOKUP(AL27,Personal!$A$2:$I$300,3,FALSE) -> Tecnologias de Información | AO27: =VLOOKUP(AL27,Personal!$A$2:$I$300,6,FALSE) -> Tecnologias de Información | AP27: =VLOOKUP(AL27,Personal!$A$2:$I$300,7,FALSE) -> Tecnologias de Información | AQ27: =VLOOKUP(AL27,Personal!$A$2:$I$300,8,FALSE) -> Tecnologias de Información
B28: 23 | G28: PC | H28: Usuario | I28: Lenovo | J28: Thinkcentre Neo 50S | K28: YLT1643J | L28: 12XG0015LS | S28: D0-F4-05-3E-74-BB | U28: 10.72.10.34 | W28: LIMFD01 | X28: Intel Core i7 | Y28: 14va Gen. | Z28: Intel Integrado | AA28: 32 GB DDR5 | AC28: 1000 GB SSD | AE28: Windows 11 Pro | AF28: Si | AG28: MS Office 2007 HB | AJ28: HOTELERA COSTA DEL PACIFICO | AK28: Operativo | AL28: Front Desk 1 | AM28: =VLOOKUP(AL28,Personal!$A$2:$I$300,2,FALSE) -> Front Desk | AN28: =VLOOKUP(AL28,Personal!$A$2:$I$300,3,FALSE) -> Front Desk 1 | AO28: =VLOOKUP(AL28,Personal!$A$2:$I$300,6,FALSE) -> Recepcionista | AP28: =VLOOKUP(AL28,Personal!$A$2:$I$300,7,FALSE) -> Recepción | AQ28: =VLOOKUP(AL28,Personal!$A$2:$I$300,8,FALSE) -> División de Habitaciones (Operaciones) | AR28: Para Front Desk
B29: 24 | G29: Monitor | H29: Usuario | I29: Dell | J29: E2014HC | K29: CN012MWY6418046P3JJU | AD29: 20" | AJ29: HOTELERA COSTA DEL PACIFICO | AK29: Operativo | AL29: 09692690 | AM29: =VLOOKUP(AL29,Personal!$A$2:$I$300,2,FALSE) -> 0000000269 | AN29: =VLOOKUP(AL29,Personal!$A$2:$I$300,3,FALSE) -> VEGA ARRATEA JAVIER VICTOR | AO29: =VLOOKUP(AL29,Personal!$A$2:$I$300,6,FALSE) -> Supervisor Jr. de Steward | AP29: =VLOOKUP(AL29,Personal!$A$2:$I$300,7,FALSE) -> Steward | AQ29: =VLOOKUP(AL29,Personal!$A$2:$I$300,8,FALSE) -> Alimentos y Bebidas
B30: 25 | G30: Monitor | H30: Usuario | I30: Dell | J30: E2014HC | K30: CN012MWY6418046P3P7U | AD30: 20" | AJ30: HOTELERA COSTA DEL PACIFICO | AK30: Custodia - Operativo | AL30: Sistemas | AM30: =VLOOKUP(AL30,Personal!$A$2:$I$300,2,FALSE) -> 0 | AN30: =VLOOKUP(AL30,Personal!$A$2:$I$300,3,FALSE) -> Tecnologias de Información | AO30: =VLOOKUP(AL30,Personal!$A$2:$I$300,6,FALSE) -> Tecnologias de Información | AP30: =VLOOKUP(AL30,Personal!$A$2:$I$300,7,FALSE) -> Tecnologias de Información | AQ30: =VLOOKUP(AL30,Personal!$A$2:$I$300,8,FALSE) -> Tecnologias de Información
B31: 26 | G31: Monitor | H31: Usuario | I31: Samsung | J31: DB22D-P | K31: 03AMHCJJ100119B | AD31: 22" | AJ31: HOTELERA COSTA DEL PACIFICO | AK31: Custodia - Operativo | AL31: Sistemas | AM31: =VLOOKUP(AL31,Personal!$A$2:$I$300,2,FALSE) -> 0 | AN31: =VLOOKUP(AL31,Personal!$A$2:$I$300,3,FALSE) -> Tecnologias de Información | AO31: =VLOOKUP(AL31,Personal!$A$2:$I$300,6,FALSE) -> Tecnologias de Información | AP31: =VLOOKUP(AL31,Personal!$A$2:$I$300,7,FALSE) -> Tecnologias de Información | AQ31: =VLOOKUP(AL31,Personal!$A$2:$I$300,8,FALSE) -> Tecnologias de Información
B32: 27 | G32: PC | H32: Usuario | I32: HP | K32: MXL4321BG8 | X32: Intel Core i5 | Y32: 4ta Gen. | Z32: Intel Integrado | AA32: 16 GB DDR3 | AC32: 480 GB SSD | AE32: Windows 11 Pro | AF32: Si | AJ32: HOTELERA COSTA DEL PACIFICO | AK32: Custodia - Operativo | AL32: Sistemas | AM32: =VLOOKUP(AL32,Personal!$A$2:$I$300,2,FALSE) -> 0 | AN32: =VLOOKUP(AL32,Personal!$A$2:$I$300,3,FALSE) -> Tecnologias de Información | AO32: =VLOOKUP(AL32,Personal!$A$2:$I$300,6,FALSE) -> Tecnologias de Información | AP32: =VLOOKUP(AL32,Personal!$A$2:$I$300,7,FALSE) -> Tecnologias de Información | AQ32: =VLOOKUP(AL32,Personal!$A$2:$I$300,8,FALSE) -> Tecnologias de Información
B33: 28 | G33: Impresora | H33: Usuario | I33: Sharp | J33: MX-3070V | K33: 3500930400 | S33: A4:D7:3C:6F:E2:D0 | U33: 10.72.8.200 | V33: EPSON6FE2D0 | AJ33: Prov. DATACONT | AK33: Operativo | AM33: =VLOOKUP(AL33,Personal!$A$2:$I$300,2,FALSE) -> #N/A | AN33: =VLOOKUP(AL33,Personal!$A$2:$I$300,3,FALSE) -> #N/A | AO33: =VLOOKUP(AL33,Personal!$A$2:$I$300,6,FALSE) -> #N/A | AP33: =VLOOKUP(AL33,Personal!$A$2:$I$300,7,FALSE) -> #N/A | AQ33: =VLOOKUP(AL33,Personal!$A$2:$I$300,8,FALSE) -> #N/A | AR33: 1er Sotano - RRHH - Sistemas
B34: 29 | G34: Impresora | H34: Usuario | I34: Epson | J34: WF-C5790 Series | K34: X3B7003661 | S34: 9C:AE:D3:AD:20:FE | U34: 10.72.8.132 | V34: EPSONAD20FE | AJ34: Prov. DATACONT | AK34: Operativo | AM34: =VLOOKUP(AL34,Personal!$A$2:$I$300,2,FALSE) -> #N/A | AN34: =VLOOKUP(AL34,Personal!$A$2:$I$300,3,FALSE) -> #N/A | AO34: =VLOOKUP(AL34,Personal!$A$2:$I$300,6,FALSE) -> #N/A | AP34: =VLOOKUP(AL34,Personal!$A$2:$I$300,7,FALSE) -> #N/A | AQ34: =VLOOKUP(AL34,Personal!$A$2:$I$300,8,FALSE) -> #N/A | AR34: 1er Sotano - Steward - Limpieza
B35: 30 | G35: Impresora | H35: Usuario | I35: Epson | J35: WF-C5890 Series | K35: XBJZ017266 | S35: A4:D7:3C:6F:E1:2A | U35: 10.72.8.229 | V35: EPSON6FE12A | AJ35: Prov. DATACONT | AK35: Operativo | AM35: =VLOOKUP(AL35,Personal!$A$2:$I$300,2,FALSE) -> #N/A | AN35: =VLOOKUP(AL35,Personal!$A$2:$I$300,3,FALSE) -> #N/A | AO35: =VLOOKUP(AL35,Personal!$A$2:$I$300,6,FALSE) -> #N/A | AP35: =VLOOKUP(AL35,Personal!$A$2:$I$300,7,FALSE) -> #N/A | AQ35: =VLOOKUP(AL35,Personal!$A$2:$I$300,8,FALSE) -> #N/A | AR35: 1er Sotano - Housekeeping
B36: 31 | G36: Impresora | H36: Usuario | I36: Epson | J36: WF-C5890 Series | K36: XBJZ021772 | S36: A4:D7:3C:70:EE:9C | U36: 10.72.8.151 | AJ36: Prov. DATACONT | AK36: Operativo | AM36: =VLOOKUP(AL36,Personal!$A$2:$I$300,2,FALSE) -> #N/A | AN36: =VLOOKUP(AL36,Personal!$A$2:$I$300,3,FALSE) -> #N/A | AO36: =VLOOKUP(AL36,Personal!$A$2:$I$300,6,FALSE) -> #N/A | AP36: =VLOOKUP(AL36,Personal!$A$2:$I$300,7,FALSE) -> #N/A | AQ36: =VLOOKUP(AL36,Personal!$A$2:$I$300,8,FALSE) -> #N/A | AR36: 3er Piso - Gerencia General
B37: 32 | G37: Impresora | H37: Usuario | I37: Epson | J37: WF-C5890 Series | K37: XBJZ027512 | S37: A4:D7:3C:72:F2:76 | U37: 10.72.8.210 | V37: EPSON72F276 | AJ37: Prov. DATACONT | AK37: Operativo | AM37: =VLOOKUP(AL37,Personal!$A$2:$I$300,2,FALSE) -> #N/A | AN37: =VLOOKUP(AL37,Personal!$A$2:$I$300,3,FALSE) -> #N/A | AO37: =VLOOKUP(AL37,Personal!$A$2:$I$300,6,FALSE) -> #N/A | AP37: =VLOOKUP(AL37,Personal!$A$2:$I$300,7,FALSE) -> #N/A | AQ37: =VLOOKUP(AL37,Personal!$A$2:$I$300,8,FALSE) -> #N/A | AR37: 3er Piso - Ventas
B38: 33 | G38: Impresora | H38: Usuario | I38: Epson | J38: WF-C5790 Series | K38: X3B7003659 | S38: 9C:AE:D3:AD:21:00 | U38: 10.72.8.197 | V38: EPSONAD2100 | AJ38: Prov. DATACONT | AK38: Operativo | AM38: =VLOOKUP(AL38,Personal!$A$2:$I$300,2,FALSE) -> #N/A | AN38: =VLOOKUP(AL38,Personal!$A$2:$I$300,3,FALSE) -> #N/A | AO38: =VLOOKUP(AL38,Personal!$A$2:$I$300,6,FALSE) -> #N/A | AP38: =VLOOKUP(AL38,Personal!$A$2:$I$300,7,FALSE) -> #N/A | AQ38: =VLOOKUP(AL38,Personal!$A$2:$I$300,8,FALSE) -> #N/A | AR38: 3er Piso - Reservas
B39: 34 | G39: Impresora | H39: Usuario | I39: Epson | J39: WF-C5790 Series | K39: X3B7003703 | S39: 9C:AE:D3:AD:20:F0 | U39: 10.9.10.153 | V39: EPSONAD20F0 | AJ39: Prov. DATACONT | AK39: Operativo | AM39: =VLOOKUP(AL39,Personal!$A$2:$I$300,2,FALSE) -> #N/A | AN39: =VLOOKUP(AL39,Personal!$A$2:$I$300,3,FALSE) -> #N/A | AO39: =VLOOKUP(AL39,Personal!$A$2:$I$300,6,FALSE) -> #N/A | AP39: =VLOOKUP(AL39,Personal!$A$2:$I$300,7,FALSE) -> #N/A | AQ39: =VLOOKUP(AL39,Personal!$A$2:$I$300,8,FALSE) -> #N/A | AR39: 1er Piso Gym
B40: 35 | G40: Impresora | H40: Usuario | I40: Epson | J40: WF-C5790 Series | K40: X3B7002433 | S40: 9C:AE:D3:AC:4D:78 | U40: 10.72.8.191 | V40: EPSONAC4D78 | AJ40: Prov. DATACONT | AK40: Operativo | AM40: =VLOOKUP(AL40,Personal!$A$2:$I$300,2,FALSE) -> #N/A | AN40: =VLOOKUP(AL40,Personal!$A$2:$I$300,3,FALSE) -> #N/A | AO40: =VLOOKUP(AL40,Personal!$A$2:$I$300,6,FALSE) -> #N/A | AP40: =VLOOKUP(AL40,Personal!$A$2:$I$300,7,FALSE) -> #N/A | AQ40: =VLOOKUP(AL40,Personal!$A$2:$I$300,8,FALSE) -> #N/A | AR40: 2do Piso - Oficina Banquetes
B41: 36 | G41: Impresora | H41: Usuario | I41: Sharp | J41: MX-M3070 | K41: 15064216 | U41: 10.72.8.203 | V41: EPSON27359D | AJ41: Prov. DATACONT | AK41: Operativo | AM41: =VLOOKUP(AL41,Personal!$A$2:$I$300,2,FALSE) -> #N/A | AN41: =VLOOKUP(AL41,Personal!$A$2:$I$300,3,FALSE) -> #N/A | AO41: =VLOOKUP(AL41,Personal!$A$2:$I$300,6,FALSE) -> #N/A | AP41: =VLOOKUP(AL41,Personal!$A$2:$I$300,7,FALSE) -> #N/A | AQ41: =VLOOKUP(AL41,Personal!$A$2:$I$300,8,FALSE) -> #N/A | AR41: 2do Piso - Seguridad
B42: 37 | G42: Impresora | H42: Usuario | I42: Canon | J42: iR1730i | K42: QFX06245 | U42: 10.72.8.215 | V42: imageRUNNER1730i | AJ42: Prov. DATACONT | AK42: Operativo | AM42: =VLOOKUP(AL42,Personal!$A$2:$I$300,2,FALSE) -> #N/A | AN42: =VLOOKUP(AL42,Personal!$A$2:$I$300,3,FALSE) -> #N/A | AO42: =VLOOKUP(AL42,Personal!$A$2:$I$300,6,FALSE) -> #N/A | AP42: =VLOOKUP(AL42,Personal!$A$2:$I$300,7,FALSE) -> #N/A | AQ42: =VLOOKUP(AL42,Personal!$A$2:$I$300,8,FALSE) -> #N/A | AR42: 2do Piso - Oficina Auditor de Ingresos
B43: 38 | G43: Impresora | H43: Usuario | I43: Epson | J43: WF-C5790 Series | K43: X3B7003711 | S43: 9C:AE:D3:AD:21:2C | U43: 10.72.8.205 | V43: EPSONAD212C | AJ43: Prov. DATACONT | AK43: Operativo | AM43: =VLOOKUP(AL43,Personal!$A$2:$I$300,2,FALSE) -> #N/A | AN43: =VLOOKUP(AL43,Personal!$A$2:$I$300,3,FALSE) -> #N/A | AO43: =VLOOKUP(AL43,Personal!$A$2:$I$300,6,FALSE) -> #N/A | AP43: =VLOOKUP(AL43,Personal!$A$2:$I$300,7,FALSE) -> #N/A | AQ43: =VLOOKUP(AL43,Personal!$A$2:$I$300,8,FALSE) -> #N/A | AR43: 1er Piso - Recepción - Back Office
B44: 39 | G44: Impresora | H44: Usuario | I44: Canon | J44: iR1643i II | K44: 35E33608 | U44: 10.72.8.211 | V44: imageRUNNER1730i | AJ44: Prov. DATACONT | AK44: Operativo | AM44: =VLOOKUP(AL44,Personal!$A$2:$I$300,2,FALSE) -> #N/A | AN44: =VLOOKUP(AL44,Personal!$A$2:$I$300,3,FALSE) -> #N/A | AO44: =VLOOKUP(AL44,Personal!$A$2:$I$300,6,FALSE) -> #N/A | AP44: =VLOOKUP(AL44,Personal!$A$2:$I$300,7,FALSE) -> #N/A | AQ44: =VLOOKUP(AL44,Personal!$A$2:$I$300,8,FALSE) -> #N/A | AR44: 1er Piso - Front Desk - Recepción
B45: 40 | G45: Impresora | H45: Usuario | I45: Canon | J45: iR1643i II | K45: 35E33607 | U45: 10.72.8.153 | V45: imageRUNNER1730i | AJ45: Prov. DATACONT | AK45: Operativo | AM45: =VLOOKUP(AL45,Personal!$A$2:$I$300,2,FALSE) -> #N/A | AN45: =VLOOKUP(AL45,Personal!$A$2:$I$300,3,FALSE) -> #N/A | AO45: =VLOOKUP(AL45,Personal!$A$2:$I$300,6,FALSE) -> #N/A | AP45: =VLOOKUP(AL45,Personal!$A$2:$I$300,7,FALSE) -> #N/A | AQ45: =VLOOKUP(AL45,Personal!$A$2:$I$300,8,FALSE) -> #N/A | AR45: 1er Piso - Front Desk - Recepción
B46: 41 | G46: Impresora | H46: Usuario | I46: Epson | J46: WF-C5890 Series | K46: XBJZ017603 | S46: A4:D7:3C:6F:E3:B7 | U46: 10.72.8.196 | V46: EPSON6FE3B7 | AJ46: Prov. DATACONT | AK46: Operativo | AM46: =VLOOKUP(AL46,Personal!$A$2:$I$300,2,FALSE) -> #N/A | AN46: =VLOOKUP(AL46,Personal!$A$2:$I$300,3,FALSE) -> #N/A | AO46: =VLOOKUP(AL46,Personal!$A$2:$I$300,6,FALSE) -> #N/A | AP46: =VLOOKUP(AL46,Personal!$A$2:$I$300,7,FALSE) -> #N/A | AQ46: =VLOOKUP(AL46,Personal!$A$2:$I$300,8,FALSE) -> #N/A | AR46: 1er Piso - Conserge
B47: 42 | G47: Impresora | H47: Usuario | I47: Epson | J47: WF-C5790 Series | K47: X3B7003671 | S47: 9C:AE:DE:AD:21:38 | U47: 10.72.8.208 | AJ47: Prov. DATACONT | AK47: Operativo | AM47: =VLOOKUP(AL47,Personal!$A$2:$I$300,2,FALSE) -> #N/A | AN47: =VLOOKUP(AL47,Personal!$A$2:$I$300,3,FALSE) -> #N/A | AO47: =VLOOKUP(AL47,Personal!$A$2:$I$300,6,FALSE) -> #N/A | AP47: =VLOOKUP(AL47,Personal!$A$2:$I$300,7,FALSE) -> #N/A | AQ47: =VLOOKUP(AL47,Personal!$A$2:$I$300,8,FALSE) -> #N/A | AR47: 1er Piso - Caja Lobby Bar
B48: 43 | G48: Impresora | H48: Usuario | I48: Epson | J48: WF-C5890 Series | K48: XBJZ021745 | S48: A4:D7:3C:70:EF:10 | U48: 10.72.8.219 | V48: EPSON70EF10 | AJ48: Prov. DATACONT | AK48: Operativo | AM48: =VLOOKUP(AL48,Personal!$A$2:$I$300,2,FALSE) -> #N/A | AN48: =VLOOKUP(AL48,Personal!$A$2:$I$300,3,FALSE) -> #N/A | AO48: =VLOOKUP(AL48,Personal!$A$2:$I$300,6,FALSE) -> #N/A | AP48: =VLOOKUP(AL48,Personal!$A$2:$I$300,7,FALSE) -> #N/A | AQ48: =VLOOKUP(AL48,Personal!$A$2:$I$300,8,FALSE) -> #N/A | AR48: 1er Piso - Oficina Chef
B49: 44 | G49: Impresora | H49: Usuario | I49: Epson | J49: WF-C5790 Series | K49: X3B7003660 | S49: 9C:AE:D3:AD:20:FF | U49: 10.72.8.204 | V49: EPSONAD20FF | AJ49: Prov. DATACONT | AK49: Operativo | AM49: =VLOOKUP(AL49,Personal!$A$2:$I$300,2,FALSE) -> #N/A | AN49: =VLOOKUP(AL49,Personal!$A$2:$I$300,3,FALSE) -> #N/A | AO49: =VLOOKUP(AL49,Personal!$A$2:$I$300,6,FALSE) -> #N/A | AP49: =VLOOKUP(AL49,Personal!$A$2:$I$300,7,FALSE) -> #N/A | AQ49: =VLOOKUP(AL49,Personal!$A$2:$I$300,8,FALSE) -> #N/A | AR49: 1er Piso - Room Service
B50: 45 | G50: Impresora | H50: Usuario | I50: Epson | J50: WF-C5790 Series | K50: X3B7003876 | S50: 9C:AE:D3:AD:09:2F | U50: 10.72.8.220 | V50: EPSONAD092F | AJ50: Prov. DATACONT | AK50: Operativo | AM50: =VLOOKUP(AL50,Personal!$A$2:$I$300,2,FALSE) -> #N/A | AN50: =VLOOKUP(AL50,Personal!$A$2:$I$300,3,FALSE) -> #N/A | AO50: =VLOOKUP(AL50,Personal!$A$2:$I$300,6,FALSE) -> #N/A | AP50: =VLOOKUP(AL50,Personal!$A$2:$I$300,7,FALSE) -> #N/A | AQ50: =VLOOKUP(AL50,Personal!$A$2:$I$300,8,FALSE) -> #N/A | AR50: 1er Piso - Oficina AyB
B51: 46 | G51: Impresora | H51: Usuario | I51: Epson | J51: WF-C5790 Series | K51: X3B7003739 | S51: 9C:AE:D3:AD:21:72 | U51: 10.72.10.43 | V51: EPSONAD2172 | AJ51: Prov. DATACONT | AK51: Operativo | AM51: =VLOOKUP(AL51,Personal!$A$2:$I$300,2,FALSE) -> #N/A | AN51: =VLOOKUP(AL51,Personal!$A$2:$I$300,3,FALSE) -> #N/A | AO51: =VLOOKUP(AL51,Personal!$A$2:$I$300,6,FALSE) -> #N/A | AP51: =VLOOKUP(AL51,Personal!$A$2:$I$300,7,FALSE) -> #N/A | AQ51: =VLOOKUP(AL51,Personal!$A$2:$I$300,8,FALSE) -> #N/A | AR51: 1er Piso Compras
B52: 47 | G52: Impresora | H52: Usuario | I52: Epson | J52: WF-C5890 Series | K52: XBJZ017602 | S52: 9C:AE:D3:AD:21:3F | U52: 10.72.8.206 | V52: EPSONAD213F | AJ52: Prov. DATACONT | AK52: Operativo | AM52: =VLOOKUP(AL52,Personal!$A$2:$I$300,2,FALSE) -> #N/A | AN52: =VLOOKUP(AL52,Personal!$A$2:$I$300,3,FALSE) -> #N/A | AO52: =VLOOKUP(AL52,Personal!$A$2:$I$300,6,FALSE) -> #N/A | AP52: =VLOOKUP(AL52,Personal!$A$2:$I$300,7,FALSE) -> #N/A | AQ52: =VLOOKUP(AL52,Personal!$A$2:$I$300,8,FALSE) -> #N/A | AR52: 1er Piso - Bodega
B53: 48 | G53: Impresora | H53: Usuario | I53: Sharp | J53: MX-M3070 | K53: 9502370Y00 | U53: 10.72.8.207 | V53: imageRUNNER1730i | AJ53: Prov. DATACONT | AK53: Operativo | AM53: =VLOOKUP(AL53,Personal!$A$2:$I$300,2,FALSE) -> #N/A | AN53: =VLOOKUP(AL53,Personal!$A$2:$I$300,3,FALSE) -> #N/A | AO53: =VLOOKUP(AL53,Personal!$A$2:$I$300,6,FALSE) -> #N/A | AP53: =VLOOKUP(AL53,Personal!$A$2:$I$300,7,FALSE) -> #N/A | AQ53: =VLOOKUP(AL53,Personal!$A$2:$I$300,8,FALSE) -> #N/A | AR53: 3er Piso - Contabilidad
B54: 49 | G54: PC | H54: Usuario | I54: Dell | J54: Optiplex 3020 | K54: GK2QN22 | L54: 0WMJ54 | S54: B0-83-FE-5E-93-F0 | U54: 10.72.10.84 | W54: LIMFBSW | X54: Intel Core i5 | Y54: 4ta Gen. | Z54: Intel Integrado | AA54: 16 GB DDR3 | AC54: 480 GB SSD | AE54: Windows 11 Pro | AF54: Si | AG54: MS Office 2007 HB | AJ54: HOTELERA COSTA DEL PACIFICO | AK54: Operativo | AL54: 09692690 | AM54: =VLOOKUP(AL54,Personal!$A$2:$I$300,2,FALSE) -> 0000000269 | AN54: =VLOOKUP(AL54,Personal!$A$2:$I$300,3,FALSE) -> VEGA ARRATEA JAVIER VICTOR | AO54: =VLOOKUP(AL54,Personal!$A$2:$I$300,6,FALSE) -> Supervisor Jr. de Steward | AP54: =VLOOKUP(AL54,Personal!$A$2:$I$300,7,FALSE) -> Steward | AQ54: =VLOOKUP(AL54,Personal!$A$2:$I$300,8,FALSE) -> Alimentos y Bebidas
B55: 50 | G55: PC | H55: Usuario | I55: Dell | J55: Optiplex 3020 | K55: GJQGN22 | L55: 0WMJ54 | S55: B0-83-FE-5E-9D-9F | U55: 10.72.10.152 | V55: LIMMANT02 | W55: LIMMANT02 | X55: Intel Core i5 | Y55: 4ta Gen. | Z55: Intel Integrado | AA55: 12 GB DDR3 | AC55: 480 GB SSD | AE55: Windows 11 Pro | AG55: MS Office 365 HB | AJ55: HOTELERA COSTA DEL PACIFICO | AK55: Operativo | AL55: 46815301 | AM55: =VLOOKUP(AL55,Personal!$A$2:$I$300,2,FALSE) -> 0000001791 | AN55: =VLOOKUP(AL55,Personal!$A$2:$I$300,3,FALSE) -> MAMANI SEVILLANO ANGIE | AO55: =VLOOKUP(AL55,Personal!$A$2:$I$300,6,FALSE) -> Asistente de Mantenimiento | AP55: =VLOOKUP(AL55,Personal!$A$2:$I$300,7,FALSE) -> Mantenimiento | AQ55: =VLOOKUP(AL55,Personal!$A$2:$I$300,8,FALSE) -> Mantenimiento
B56: 51 | G56: PC | H56: Usuario | I56: HP | J56: Prodesk 600 G1 | K56: MXL4321BFN | L56: E1Z55LT#ABM | S56: 40-A8-F0-60-C2-FB | V56: LIMH1W11IT01 | X56: Intel Core i5 | Y56: 4ta Gen. | Z56: Intel Integrado | AA56: 32 GB DDR3 | AC56: 480 GB SSD + 500 GB HDD | AE56: Windows 11 Pro | AG56: MS Office 2007 HB | AJ56: HOTELERA COSTA DEL PACIFICO | AK56: Operativo | AL56: 02856974 | AM56: =VLOOKUP(AL56,Personal!$A$2:$I$300,2,FALSE) -> 0000001501 | AN56: =VLOOKUP(AL56,Personal!$A$2:$I$300,3,FALSE) -> YAMUNAQUE CASTILLO HECTOR ARTURO | AO56: =VLOOKUP(AL56,Personal!$A$2:$I$300,6,FALSE) -> Gerente de Sistemas | AP56: =VLOOKUP(AL56,Personal!$A$2:$I$300,7,FALSE) -> Tecnologias de Información | AQ56: =VLOOKUP(AL56,Personal!$A$2:$I$300,8,FALSE) -> Tecnologias de Información
B57: 52 | G57: Monitor | H57: Usuario | I57: Dell | J57: E2014HC | AD57: 20" | AJ57: HOTELERA COSTA DEL PACIFICO | AM57: =VLOOKUP(AL57,Personal!$A$2:$I$300,2,FALSE) -> #N/A | AN57: =VLOOKUP(AL57,Personal!$A$2:$I$300,3,FALSE) -> #N/A | AO57: =VLOOKUP(AL57,Personal!$A$2:$I$300,6,FALSE) -> #N/A | AP57: =VLOOKUP(AL57,Personal!$A$2:$I$300,7,FALSE) -> #N/A | AQ57: =VLOOKUP(AL57,Personal!$A$2:$I$300,8,FALSE) -> #N/A
B58: 53 | G58: PC | H58: Usuario | I58: Dell | J58: Optiplex 3020 | K58: GK6DN22 | L58: 0WMJ54 | S58: B0-83-FE-5E-9D-79 | U58: 10.72.10.93 | W58: LIMFB02 | X58: Intel Core i5 | Y58: 4ta Gen. | Z58: Intel Integrado | AA58: 16 GB DDR3 | AC58: 480 GB SSD | AE58: Windows 11 Pro | AF58: Si | AG58: MS Office 2007 HB | AJ58: HOTELERA COSTA DEL PACIFICO | AK58: Operativo | AL58: 75521197 | AM58: =VLOOKUP(AL58,Personal!$A$2:$I$300,2,FALSE) -> 0000001580 | AN58: =VLOOKUP(AL58,Personal!$A$2:$I$300,3,FALSE) -> RAMOS MAGAN HANNA GRACE | AO58: =VLOOKUP(AL58,Personal!$A$2:$I$300,6,FALSE) -> Asistente Administrativa Jr. | AP58: =VLOOKUP(AL58,Personal!$A$2:$I$300,7,FALSE) -> Gerencia A&B | AQ58: =VLOOKUP(AL58,Personal!$A$2:$I$300,8,FALSE) -> Alimentos y Bebidas
B59: 54 | G59: PC | H59: Usuario | I59: Dell | J59: Optiplex 3020 | K59: D0GQN22 | L59: 0WMJ54 | S59: B0-83-FE-5F-01-54 | U59: 10.72.10.111 | W59: LIMSMVEN1 | X59: Intel Core i5 | Y59: 4ta Gen. | Z59: Intel Integrado | AA59: 16 GB DDR3 | AC59: 480 GB SSD | AE59: Windows 11 Pro | AF59: Si | AG59: MS Office 2007 HB | AJ59: HOTELERA COSTA DEL PACIFICO | AK59: Operativo | AL59: 46405695 | AM59: =VLOOKUP(AL59,Personal!$A$2:$I$300,2,FALSE) -> 0000001780 | AN59: =VLOOKUP(AL59,Personal!$A$2:$I$300,3,FALSE) -> CHUYES MENDOZA CLAUDIA ELIZABETH | AO59: =VLOOKUP(AL59,Personal!$A$2:$I$300,6,FALSE) -> Ejecutiva de Eventos | AP59: =VLOOKUP(AL59,Personal!$A$2:$I$300,7,FALSE) -> Ventas | AQ59: =VLOOKUP(AL59,Personal!$A$2:$I$300,8,FALSE) -> Ventas y Marketing
B60: 55 | G60: Monitor | H60: Usuario | I60: Dell | J60: E2014HC | AJ60: HOTELERA COSTA DEL PACIFICO | AK60: Operativo | AL60: 41093999 | AM60: =VLOOKUP(AL60,Personal!$A$2:$I$300,2,FALSE) -> 0000001737 | AN60: =VLOOKUP(AL60,Personal!$A$2:$I$300,3,FALSE) -> MUÑOZ CUBA ROSA ALICIA | AO60: =VLOOKUP(AL60,Personal!$A$2:$I$300,6,FALSE) -> Ejecutiva de Eventos | AP60: =VLOOKUP(AL60,Personal!$A$2:$I$300,7,FALSE) -> Ventas | AQ60: =VLOOKUP(AL60,Personal!$A$2:$I$300,8,FALSE) -> Ventas y Marketing
B61: 56 | G61: PC | H61: Usuario | I61: Dell | J61: Optiplex 3020 | K61: GJWQN22 | L61: 0WMJ54 | S61: B0-83-FE-5F-8D-D3 | U61: 10.72.10.130 | W61: LIMMANT01 | X61: Intel Core i5 | Y61: 4ta Gen. | Z61: Intel Integrado | AA61: 12 GB DDR3 | AC61: 480 GB SSD | AE61: Windows 11 Pro | AF61: Si | AG61: MS Office 365 HB | AJ61: HOTELERA COSTA DEL PACIFICO | AK61: Operativo | AL61: 75438114 | AM61: =VLOOKUP(AL61,Personal!$A$2:$I$300,2,FALSE) -> 0000P00761 | AN61: =VLOOKUP(AL61,Personal!$A$2:$I$300,3,FALSE) -> NOLASCO CUNYARACHE GABRIELA FLOR | AO61: =VLOOKUP(AL61,Personal!$A$2:$I$300,6,FALSE) -> Practicante de Mantenimiento | AP61: =VLOOKUP(AL61,Personal!$A$2:$I$300,7,FALSE) -> Mantenimiento | AQ61: =VLOOKUP(AL61,Personal!$A$2:$I$300,8,FALSE) -> Mantenimiento
B62: 57 | G62: PC | H62: Usuario | I62: Dell | J62: Optiplex 3020 | K62: D03QN22 | L62: 0WMJ54 | S62: B0-83-FE-54-C6-74 | U62: 10.72.10.138 | V62: LIMH1SMPC019 | W62: LIMVMGRES | X62: Intel Core i5 | Y62: 4ta Gen. | Z62: Intel Integrado | AA62: 16 GB DDR3 | AC62: 480 GB SSD | AE62: Windows 11 Pro | AF62: Si | AG62: MS Office 2007 HB | AJ62: HOTELERA COSTA DEL PACIFICO | AK62: Operativo | AL62: 40263172 | AM62: =VLOOKUP(AL62,Personal!$A$2:$I$300,2,FALSE) -> 0000000868 | AN62: =VLOOKUP(AL62,Personal!$A$2:$I$300,3,FALSE) -> PECHING CHIONG KARINA JANET | AO62: =VLOOKUP(AL62,Personal!$A$2:$I$300,6,FALSE) -> Gerenta de Reservas | AP62: =VLOOKUP(AL62,Personal!$A$2:$I$300,7,FALSE) -> Reservas | AQ62: =VLOOKUP(AL62,Personal!$A$2:$I$300,8,FALSE) -> Ventas y Marketing
B63: 58 | G63: PC | H63: Usuario | I63: Dell | J63: Optiplex 3020 | K63: CZPRN22 | L63: 0WMJ54 | S63: B0-83-FE-5F-8F-0E | U63: 10.72.10.41 | V63: LIMH1W11P071 | X63: Intel Core i5 | Y63: 4ta Gen. | Z63: Intel Integrado | AA63: 16 GB DDR3 | AC63: 480 GB SSD | AE63: Windows 11 Pro | AF63: Si | AG63: MS Office 2007 HB | AJ63: HOTELERA COSTA DEL PACIFICO | AK63: Operativo | AL63: 41531474 | AM63: =VLOOKUP(AL63,Personal!$A$2:$I$300,2,FALSE) -> 0000F00050 | AN63: =VLOOKUP(AL63,Personal!$A$2:$I$300,3,FALSE) -> JARA RISCO GINO | AO63: =VLOOKUP(AL63,Personal!$A$2:$I$300,6,FALSE) -> Director de Alimentos y Bebidas | AP63: =VLOOKUP(AL63,Personal!$A$2:$I$300,7,FALSE) -> Gerencia A&B | AQ63: =VLOOKUP(AL63,Personal!$A$2:$I$300,8,FALSE) -> Alimentos y Bebidas
B64: 59 | G64: Monitor | H64: Usuario | I64: Dell | J64: E2014HC | K64: CN012MWY6418046P1V7U | AD64: 20" | AJ64: HOTELERA COSTA DEL PACIFICO | AK64: Operativo | AL64: 40235456 | AM64: =VLOOKUP(AL64,Personal!$A$2:$I$300,2,FALSE) -> 0000000806 | AN64: =VLOOKUP(AL64,Personal!$A$2:$I$300,3,FALSE) -> TRUJILLO GARAY MONICA ALEJANDRA | AO64: =VLOOKUP(AL64,Personal!$A$2:$I$300,6,FALSE) -> Gerente de Congresos y Convenciones | AP64: =VLOOKUP(AL64,Personal!$A$2:$I$300,7,FALSE) -> Ventas | AQ64: =VLOOKUP(AL64,Personal!$A$2:$I$300,8,FALSE) -> Ventas y Marketing
B65: 60 | G65: Monitor | H65: Usuario | I65: Dell | J65: E2014HC | K65: CN012MWY6418046P3NAU | AD65: 20" | AJ65: HOTELERA COSTA DEL PACIFICO | AK65: Custodia - Operativo | AL65: Sistemas | AM65: =VLOOKUP(AL65,Personal!$A$2:$I$300,2,FALSE) -> 0 | AN65: =VLOOKUP(AL65,Personal!$A$2:$I$300,3,FALSE) -> Tecnologias de Información | AO65: =VLOOKUP(AL65,Personal!$A$2:$I$300,6,FALSE) -> Tecnologias de Información | AP65: =VLOOKUP(AL65,Personal!$A$2:$I$300,7,FALSE) -> Tecnologias de Información | AQ65: =VLOOKUP(AL65,Personal!$A$2:$I$300,8,FALSE) -> Tecnologias de Información | AR65: Linea horizontal inferior.
B66: 61 | G66: PC | H66: Usuario | I66: Dell | J66: Optiplex 3020 | K66: D0HFN22 | L66: 0WMJ54 | S66: B0-83-FE-5E-FE-C2 | U66: 10.72.10.53 | V66: LIMH1ACPC003 | W66: LIMCNTCONT5 | X66: Intel Core i5 | Y66: 4ta Gen. | Z66: Intel Integrado | AA66: 16 GB DDR3 | AC66: 480 GB SSD | AE66: Windows 11 Pro | AG66: MS Office 365 HB | AJ66: HOTELERA COSTA DEL PACIFICO | AK66: Operativo | AL66: 46690955 | AM66: =VLOOKUP(AL66,Personal!$A$2:$I$300,2,FALSE) -> 0000001713 | AN66: =VLOOKUP(AL66,Personal!$A$2:$I$300,3,FALSE) -> TISNADO MEGO LEIDER ALFONZO | AO66: =VLOOKUP(AL66,Personal!$A$2:$I$300,6,FALSE) -> Encargado de Costos | AP66: =VLOOKUP(AL66,Personal!$A$2:$I$300,7,FALSE) -> Contabilidad | AQ66: =VLOOKUP(AL66,Personal!$A$2:$I$300,8,FALSE) -> Contraloría
B67: 62 | G67: PC | H67: Usuario | I67: Dell | J67: Optiplex 3020 | K67: CZYQN22 | L67: 0WMJ54 | S67: B0-83-FE-55-21-A3 | U67: 10.72.10.157 | V67: LIMH1FBPC06 | W67: LIMCOC04 | X67: Intel Core i5 | Y67: 4ta Gen. | Z67: Intel Integrado | AA67: 16 GB DDR3 | AC67: 480 GB SSD | AE67: Windows 11 Pro | AF67: Si | AG67: MS Office 2007 HB | AJ67: HOTELERA COSTA DEL PACIFICO | AK67: Operativo | AL67: 47156230 | AM67: =VLOOKUP(AL67,Personal!$A$2:$I$300,2,FALSE) -> 0000001236 | AN67: =VLOOKUP(AL67,Personal!$A$2:$I$300,3,FALSE) -> BAUTISTA CARDENAS MIGUEL ALEJANDRO | AO67: =VLOOKUP(AL67,Personal!$A$2:$I$300,6,FALSE) -> Sub Chef | AP67: =VLOOKUP(AL67,Personal!$A$2:$I$300,7,FALSE) -> Cocina La Locanda | AQ67: =VLOOKUP(AL67,Personal!$A$2:$I$300,8,FALSE) -> Cocina
B68: 63 | G68: PC | H68: Usuario | I68: Dell | J68: Optiplex 3020 | K68: D01GN22 | L68: 0WMJ54 | S68: B0-83-FE-5F-45-54 | U68: 10.72.10.138 | W68: LIMCOC05 | X68: Intel Core i5 | Y68: 4ta Gen. | Z68: Intel Integrado | AA68: 16 GB DDR3 | AC68: 480 GB SSD | AE68: Windows 11 Pro | AG68: MS Office 365 HB | AJ68: HOTELERA COSTA DEL PACIFICO | AK68: Operativo | AL68: 74767236 | AM68: =VLOOKUP(AL68,Personal!$A$2:$I$300,2,FALSE) -> 0000001760 | AN68: =VLOOKUP(AL68,Personal!$A$2:$I$300,3,FALSE) -> CONDORI MORENO ELIZABETH CINTHIA | AO68: =VLOOKUP(AL68,Personal!$A$2:$I$300,6,FALSE) -> Asistente de Calidad | AP68: =VLOOKUP(AL68,Personal!$A$2:$I$300,7,FALSE) -> Calidad | AQ68: =VLOOKUP(AL68,Personal!$A$2:$I$300,8,FALSE) -> Cocina
B69: 64 | G69: PC | H69: Usuario | I69: Dell | J69: Optiplex 3020 | K69: 353YN22 | L69: 0WMJ54 | S69: B0-83-FE-52-3F-C6 | U69: 10.72.10.70 | V69: LIMH1GMPC02 | W69: LIMH1GMPC02 | X69: Intel Core i5 | Y69: 4ta Gen. | Z69: Intel Integrado | AA69: 8 GB DDR3 | AC69: 250 GB SSD | AE69: Windows 10 Pro | AG69: MS Office 2007 HB | AJ69: HOTELERA COSTA DEL PACIFICO | AK69: Operativo | AL69: ACTSYS | AM69: =VLOOKUP(AL69,Personal!$A$2:$I$300,2,FALSE) -> 0 | AN69: =VLOOKUP(AL69,Personal!$A$2:$I$300,3,FALSE) -> SISTEMAS DE ACTIVOS FIJOS | AO69: =VLOOKUP(AL69,Personal!$A$2:$I$300,6,FALSE) -> Sistema de Activos Fijos | AP69: =VLOOKUP(AL69,Personal!$A$2:$I$300,7,FALSE) -> Contabilidad | AQ69: =VLOOKUP(AL69,Personal!$A$2:$I$300,8,FALSE) -> Contraloría
B70: 65 | G70: PC | H70: Usuario | I70: Dell | J70: Optiplex 3020 | K70: 35CXN22 | L70: 0WMJ54 | S70: B0-83-FE-52-AB-94 | U70: 10.72.10.51 | V70: LIMH1PUPC001 | W70: LIMCOMPGC | X70: Intel Core i5 | Y70: 4ta Gen. | Z70: Intel Integrado | AA70: 16 GB DDR3 | AC70: 480 GB SSD | AE70: Windows 11 Pro | AG70: MS Office 2007 HB | AJ70: HOTELERA COSTA DEL PACIFICO | AK70: Operativo | AL70: 09649733 | AM70: =VLOOKUP(AL70,Personal!$A$2:$I$300,2,FALSE) -> 0000000037 | AN70: =VLOOKUP(AL70,Personal!$A$2:$I$300,3,FALSE) -> OBARA AVI JUAN FERNANDO | AO70: =VLOOKUP(AL70,Personal!$A$2:$I$300,6,FALSE) -> Gerente de Compras | AP70: =VLOOKUP(AL70,Personal!$A$2:$I$300,7,FALSE) -> Compras | AQ70: =VLOOKUP(AL70,Personal!$A$2:$I$300,8,FALSE) -> Compras
B71: 66 | G71: PC | H71: Usuario | I71: Dell | J71: Precision 3660 | K71: 630Q7V3 | L71: 0PDTHJ | S71: C4-5A-B1-CE-05-5D | U71: 10.72.10.120 | V71: LIMH1SMPC012 | W71: LIMH1SMPC012 | X71: Intel Core i7 | Y71: 12va Gen. | Z71: NVIDEA | AA71: 32 GB DDR5 | AC71: 1000 GB SSD | AE71: Windows 11 Pro | AF71: Si | AG71: MS Office 2007 HB | AJ71: HOTELERA COSTA DEL PACIFICO | AK71: Operativo | AL71: 47840820 | AM71: =VLOOKUP(AL71,Personal!$A$2:$I$300,2,FALSE) -> 0000001708 | AN71: =VLOOKUP(AL71,Personal!$A$2:$I$300,3,FALSE) -> PALACIOS CULQUI THALIA YARIM | AO71: =VLOOKUP(AL71,Personal!$A$2:$I$300,6,FALSE) -> Jefe de Marketing | AP71: =VLOOKUP(AL71,Personal!$A$2:$I$300,7,FALSE) -> Marketing | AQ71: =VLOOKUP(AL71,Personal!$A$2:$I$300,8,FALSE) -> Ventas y Marketing
B72: 67 | G72: PC | H72: Usuario | I72: Dell | J72: Optiplex 3020 | K72: D0BFN22 | L72: 0WMJ54 | S72: B0-83-FE-5E-FF-1C | U72: 10.72.10.33 | V72: LIMH1SMPC018 | W72: LIMVMVEN01 | X72: Intel Core i5 | Y72: 4ta Gen. | Z72: Intel Integrado | AA72: 16 GB DDR3 | AC72: 480 GB SSD | AE72: Windows 11 Pro | AF72: Si | AG72: MS Office 2007 HB | AJ72: HOTELERA COSTA DEL PACIFICO | AK72: Operativo | AL72: 45809468 | AM72: =VLOOKUP(AL72,Personal!$A$2:$I$300,2,FALSE) -> 0000001510 | AN72: =VLOOKUP(AL72,Personal!$A$2:$I$300,3,FALSE) -> CHAVEZ CRUZ MARITZA DINA | AO72: =VLOOKUP(AL72,Personal!$A$2:$I$300,6,FALSE) -> Ejecutiva de Ventas | AP72: =VLOOKUP(AL72,Personal!$A$2:$I$300,7,FALSE) -> Ventas | AQ72: =VLOOKUP(AL72,Personal!$A$2:$I$300,8,FALSE) -> Ventas y Marketing
B73: 68 | G73: PC | H73: Usuario | I73: Dell | J73: Optiplex 3020 | K73: D05HN22 | L73: 0WMJ54 | S73: B0-83-FE-55-32-59 | U73: 10.72.10.133 | X73: Intel Core i5 | Y73: 4ta Gen. | Z73: Intel Integrado | AJ73: HOTELERA COSTA DEL PACIFICO | AK73: Custodia - Operativo | AL73: Sistemas | AM73: =VLOOKUP(AL73,Personal!$A$2:$I$300,2,FALSE) -> 0 | AN73: =VLOOKUP(AL73,Personal!$A$2:$I$300,3,FALSE) -> Tecnologias de Información | AO73: =VLOOKUP(AL73,Personal!$A$2:$I$300,6,FALSE) -> Tecnologias de Información | AP73: =VLOOKUP(AL73,Personal!$A$2:$I$300,7,FALSE) -> Tecnologias de Información | AQ73: =VLOOKUP(AL73,Personal!$A$2:$I$300,8,FALSE) -> Tecnologias de Información
B74: 69 | G74: PC | H74: Usuario | I74: Dell | J74: Optiplex 3020 | K74: 3540P22 | L74: 0WMJ54 | S74: B0-83-FE-52-AB-BB | U74: 10.72.10.161 | V74: LIMH1SMPC020 | W74: LIMVMRES01 | X74: Intel Core i5 | Y74: 4ta Gen. | Z74: Intel Integrado | AA74: 16 GB DDR3 | AC74: 480 GB SSD | AE74: Windows 11 Pro | AF74: Si | AG74: MS Office 2007 HB | AJ74: HOTELERA COSTA DEL PACIFICO | AK74: Operativo | AL74: 44247838 | AM74: =VLOOKUP(AL74,Personal!$A$2:$I$300,2,FALSE) -> 0000001516 | AN74: =VLOOKUP(AL74,Personal!$A$2:$I$300,3,FALSE) -> ROQUE SILVA TANIA MARYORI | AO74: =VLOOKUP(AL74,Personal!$A$2:$I$300,6,FALSE) -> Agente de Reservas | AP74: =VLOOKUP(AL74,Personal!$A$2:$I$300,7,FALSE) -> Reservas | AQ74: =VLOOKUP(AL74,Personal!$A$2:$I$300,8,FALSE) -> Ventas y Marketing
B75: 70 | G75: PC | H75: Usuario | I75: Dell | J75: Optiplex 3020 | K75: CZPSN22 | L75: 0WMJ54 | S75: B0-83-FE-5F-3F-57 | U75: 10.72.10.37 | V75: LIMH1SMPC022 | W75: LIMVMRES03 | X75: Intel Core i5 | Y75: 4ta Gen. | Z75: Intel Integrado | AA75: 16 GB DDR3 | AC75: 480 GB SSD | AE75: Windows 11 Pro | AF75: Si | AG75: MS Office 2007 HB | AJ75: HOTELERA COSTA DEL PACIFICO | AK75: Operativo | AL75: 46380959 | AM75: =VLOOKUP(AL75,Personal!$A$2:$I$300,2,FALSE) -> 0000001568 | AN75: =VLOOKUP(AL75,Personal!$A$2:$I$300,3,FALSE) -> BAGLIETTO ROJAS PIERO GIOVANI | AO75: =VLOOKUP(AL75,Personal!$A$2:$I$300,6,FALSE) -> Jefe de Revenue | AP75: =VLOOKUP(AL75,Personal!$A$2:$I$300,7,FALSE) -> Revenue | AQ75: =VLOOKUP(AL75,Personal!$A$2:$I$300,8,FALSE) -> Ventas y Marketing
B76: 71 | G76: PC | H76: Usuario | I76: Dell | J76: Optiplex 3020 | K76: D0HQN22 | L76: 0WMJ54 | S76: B0-83-FE-5E-FF-44 | U76: 10.72.10.149 | V76: LIMH1SMPC023 | W76: LIMVMGVC | X76: Intel Core i5 | Y76: 4ta Gen. | Z76: Intel Integrado | AA76: 16 GB DDR3 | AC76: 480 GB SSD | AE76: Windows 11 Pro | AF76: Si | AG76: MS Office 365 HB | AJ76: HOTELERA COSTA DEL PACIFICO | AK76: Operativo | AL76: 41994040 | AM76: =VLOOKUP(AL76,Personal!$A$2:$I$300,2,FALSE) -> 0000001121 | AN76: =VLOOKUP(AL76,Personal!$A$2:$I$300,3,FALSE) -> VASQUEZ MORALES MARIELA IRAIS | AO76: =VLOOKUP(AL76,Personal!$A$2:$I$300,6,FALSE) -> Gerente de Ventas Corporativas | AP76: =VLOOKUP(AL76,Personal!$A$2:$I$300,7,FALSE) -> Ventas | AQ76: =VLOOKUP(AL76,Personal!$A$2:$I$300,8,FALSE) -> Ventas y Marketing
B77: 72 | G77: PC | H77: Servidor | I77: Dell | J77: Optiplex 3020 | K77: D02RN22 | L77: 0WMJ54 | S77: B0-83-FE-5F-03-7D | U77: 10.72.10.95 | V77: LIMH1W7P07 | W77: LIMH1W7P07 | X77: Intel Core i5 | Y77: 4ta Gen. | Z77: Intel Integrado | AA77: 8 GB DDR3 | AC77: 500 GB HDD | AE77: Windows 10 Pro | AF77: Si | AG77: MS Office 2007 HB | AJ77: HOTELERA COSTA DEL PACIFICO | AK77: Operativo | AL77: Sistemas | AM77: =VLOOKUP(AL77,Personal!$A$2:$I$300,2,FALSE) -> 0 | AN77: =VLOOKUP(AL77,Personal!$A$2:$I$300,3,FALSE) -> Tecnologias de Información | AO77: =VLOOKUP(AL77,Personal!$A$2:$I$300,6,FALSE) -> Tecnologias de Información | AP77: =VLOOKUP(AL77,Personal!$A$2:$I$300,7,FALSE) -> Tecnologias de Información | AQ77: =VLOOKUP(AL77,Personal!$A$2:$I$300,8,FALSE) -> Tecnologias de Información | AR77: Conexión Remoto - ACDC - Frontdesk
B78: 73 | G78: PC | H78: Usuario | I78: Lenovo | J78: Thinkcentre Neo 50S | K78: YLT16FYF | L78: 12XG0015LS | S78: D0-F4-05-3F-CC-11 | U78: 10.72.10.165 | V78: LIMH1W7P34 | W78: LIMFD04 | X78: Intel Core i7 | Y78: 14va Gen. | Z78: Intel Integrado | AA78: 32 GB DDR5 | AC78: 1000 GB SSD | AE78: Windows 11 Pro | AF78: Si | AG78: MS Office 2007 HB | AJ78: HOTELERA COSTA DEL PACIFICO | AK78: Operativo | AL78: Front Desk 4 | AM78: =VLOOKUP(AL78,Personal!$A$2:$I$300,2,FALSE) -> Front Desk | AN78: =VLOOKUP(AL78,Personal!$A$2:$I$300,3,FALSE) -> Front Desk 4 | AO78: =VLOOKUP(AL78,Personal!$A$2:$I$300,6,FALSE) -> Recepcionista | AP78: =VLOOKUP(AL78,Personal!$A$2:$I$300,7,FALSE) -> Recepción | AQ78: =VLOOKUP(AL78,Personal!$A$2:$I$300,8,FALSE) -> División de Habitaciones (Operaciones) | AR78: Para Front Desk
B79: 74 | G79: PC | H79: Usuario | I79: Dell | J79: Optiplex 3020 | K79: GK0SN22 | L79: 0WMJ54 | S79: B0-83-FE-5E-9D-7B | V79: LIMH1W7P48 | X79: Intel Core i5 | Y79: 4ta Gen. | Z79: Intel Integrado | AA79: 8 GB DDR3 | AC79: 500 GB HDD | AE79: Windows 10 Pro | AG79: MS Office 2007 HB | AJ79: HOTELERA COSTA DEL PACIFICO | AK79: Custodia - Operativo | AL79: Sistemas | AM79: =VLOOKUP(AL79,Personal!$A$2:$I$300,2,FALSE) -> 0 | AN79: =VLOOKUP(AL79,Personal!$A$2:$I$300,3,FALSE) -> Tecnologias de Información | AO79: =VLOOKUP(AL79,Personal!$A$2:$I$300,6,FALSE) -> Tecnologias de Información | AP79: =VLOOKUP(AL79,Personal!$A$2:$I$300,7,FALSE) -> Tecnologias de Información | AQ79: =VLOOKUP(AL79,Personal!$A$2:$I$300,8,FALSE) -> Tecnologias de Información | AR79: Ex Front Desk - Se cambio por una Lenovo - tiene Información
B80: 75 | G80: PC | H80: Usuario | I80: Dell | J80: Optiplex 3020 | K80: D05FN22 | L80: 0WMJ54 | S80: B0-83-FE-5E-FF-7E | U80: 10.72.10.110 | V80: LIMH1W7P57 | W80: LIMCNTCONT6 | X80: Intel Core i5 | Y80: 4ta Gen. | Z80: Intel Integrado | AA80: 16 GB DDR3 | AC80: 480 GB SSD | AE80: Windows 11 Pro | AF80: Si | AG80: MS Office 2007 HB | AJ80: HOTELERA COSTA DEL PACIFICO | AK80: Operativo | AL80: 74915395 | AM80: =VLOOKUP(AL80,Personal!$A$2:$I$300,2,FALSE) -> 0000P00661 | AN80: =VLOOKUP(AL80,Personal!$A$2:$I$300,3,FALSE) -> ORELLANA CHIPANA MARTIN SANTIAGO | AO80: =VLOOKUP(AL80,Personal!$A$2:$I$300,6,FALSE) -> Practicante de Contabilidad | AP80: =VLOOKUP(AL80,Personal!$A$2:$I$300,7,FALSE) -> Contabilidad | AQ80: =VLOOKUP(AL80,Personal!$A$2:$I$300,8,FALSE) -> Contraloría
B81: 76 | G81: PC | H81: Usuario | I81: Dell | J81: Optiplex 3020 | K81: D09RN22 | L81: 0WMJ54 | S81: B0-83-FE-5E-FF-33 | U81: 10.72.10.138 | V81: LIMH1W7P65 | W81: LIMCNTAI | X81: Intel Core i5 | Y81: 4ta Gen. | Z81: Intel Integrado | AA81: 16 GB DDR3 | AC81: 480 GB SSD | AE81: Windows 11 Pro | AF81: Si | AG81: MS Office 2007 HB | AJ81: HOTELERA COSTA DEL PACIFICO | AK81: Operativo | AL81: 06111494 | AM81: =VLOOKUP(AL81,Personal!$A$2:$I$300,2,FALSE) -> 0000000086 | AN81: =VLOOKUP(AL81,Personal!$A$2:$I$300,3,FALSE) -> MOTA CASTRO JIM EDUARDO | AO81: =VLOOKUP(AL81,Personal!$A$2:$I$300,6,FALSE) -> Auditor de Ingresos | AP81: =VLOOKUP(AL81,Personal!$A$2:$I$300,7,FALSE) -> Auditoría de Ingresos | AQ81: =VLOOKUP(AL81,Personal!$A$2:$I$300,8,FALSE) -> Contraloría
B82: 77 | G82: PC | H82: Usuario | I82: Dell | J82: Optiplex 3020 | K82: D04FN22 | L82: 0WMJ54 | S82: B0-83-FE-54-C6-09 | U82: 10.72.10.83 | V82: LIMH1W7P85 | W82: LIMAYBBQ01 | X82: Intel Core i5 | Y82: 4ta Gen. | Z82: Intel Integrado | AA82: 16 GB DDR3 | AC82: 480 GB SSD | AE82: Windows 11 Pro | AF82: Si | AG82: MS Office 2007 HB | AJ82: HOTELERA COSTA DEL PACIFICO | AK82: Operativo | AL82: 10158051 | AM82: =VLOOKUP(AL82,Personal!$A$2:$I$300,2,FALSE) -> 0000000874 | AN82: =VLOOKUP(AL82,Personal!$A$2:$I$300,3,FALSE) -> FALCON PAZ JULIAN MIGUEL ANGEL | AO82: =VLOOKUP(AL82,Personal!$A$2:$I$300,6,FALSE) -> Supervisor Senior de A&B | AP82: =VLOOKUP(AL82,Personal!$A$2:$I$300,7,FALSE) -> Banquetes | AQ82: =VLOOKUP(AL82,Personal!$A$2:$I$300,8,FALSE) -> Alimentos y Bebidas
B83: 78 | G83: PC | H83: Usuario | I83: Dell | J83: Optiplex 3020 | K83: 352YN22 | L83: 0WMJ54 | S83: B0-83-FE-52-BB-9F | U83: 10.72.10.44 | V83: LIMH1W7P95 | W83: LIMAYBLB | X83: Intel Core i5 | Y83: 4ta Gen. | Z83: Intel Integrado | AA83: 16 GB DDR3 | AC83: 480 GB SSD | AE83: Windows 11 Pro | AF83: Si | AG83: MS Office 2007 HB | AJ83: HOTELERA COSTA DEL PACIFICO | AK83: Operativo | AL83: 10806822 | AM83: =VLOOKUP(AL83,Personal!$A$2:$I$300,2,FALSE) -> 0000000423 | AN83: =VLOOKUP(AL83,Personal!$A$2:$I$300,3,FALSE) -> UGAZ OLIVARES PALOMA | AO83: =VLOOKUP(AL83,Personal!$A$2:$I$300,6,FALSE) -> Supervisor Senior de A&B | AP83: =VLOOKUP(AL83,Personal!$A$2:$I$300,7,FALSE) -> Lobby | AQ83: =VLOOKUP(AL83,Personal!$A$2:$I$300,8,FALSE) -> Alimentos y Bebidas
B84: 79 | G84: PC | H84: Usuario | I84: Dell | J84: Optiplex 3020 | K84: GJVRN22 | L84: 0WMJ54 | S84: B0-83-FE-5E-87-E8 | V84: LIMSMVMEC | W84: LIMVMEC | X84: Intel Core i5 | Y84: 4ta Gen. | Z84: Intel Integrado | AA84: 12 GB DDR3 | AC84: 250 GB SSD | AE84: Windows 11 Pro | AF84: Si | AG84: MS Office 2007 HB | AJ84: HOTELERA COSTA DEL PACIFICO | AK84: Operativo | AL84: 44826856 | AM84: =VLOOKUP(AL84,Personal!$A$2:$I$300,2,FALSE) -> 0 | AN84: =VLOOKUP(AL84,Personal!$A$2:$I$300,3,FALSE) -> BOHORQUEZ LEMOR ROSSANA ARMIDA | AO84: =VLOOKUP(AL84,Personal!$A$2:$I$300,6,FALSE) -> Ejecutiva de Eventos | AP84: =VLOOKUP(AL84,Personal!$A$2:$I$300,7,FALSE) -> Ventas | AQ84: =VLOOKUP(AL84,Personal!$A$2:$I$300,8,FALSE) -> Ventas y Marketing
B85: 80 | G85: PC | H85: Usuario | I85: Dell | J85: Optiplex 3020 | K85: D0HRN22 | L85: 0WMJ54 | S85: B0-83-FE-5E-FC-30 | U85: 10.72.10.133 | V85: LIMH1W7P101 | W85: LIMCNTCONT3 | X85: Intel Core i5 | Y85: 4ta Gen. | Z85: Intel Integrado | AA85: 16 GB DDR3 | AC85: 480 GB SSD | AE85: Windows 11 Pro | AF85: Si | AG85: MS Office 2007 HB | AJ85: HOTELERA COSTA DEL PACIFICO | AK85: Operativo | AL85: 40856376 | AM85: =VLOOKUP(AL85,Personal!$A$2:$I$300,2,FALSE) -> 0000000772 | AN85: =VLOOKUP(AL85,Personal!$A$2:$I$300,3,FALSE) -> CARHUANCOTA CHAVEZ ANDRES ALBERTO | AO85: =VLOOKUP(AL85,Personal!$A$2:$I$300,6,FALSE) -> Asistente Senior de Contabilidad | AP85: =VLOOKUP(AL85,Personal!$A$2:$I$300,7,FALSE) -> Contabilidad | AQ85: =VLOOKUP(AL85,Personal!$A$2:$I$300,8,FALSE) -> Contraloría | AR85: La PC lo utiliza Alex Cardenas con usuario de Andres
B86: 81 | G86: PC | H86: Usuario | I86: Dell | J86: Optiplex 3020 | K86: D09HN22 | L86: 0WMJ54 | S86: B0-83-FE-5E-FE-05 | U86: 10.72.10.106 | V86: LIMH1W10FB010 | W86: LIMCHEF | X86: Intel Core i5 | Y86: 4ta Gen. | Z86: Intel Integrado | AA86: 16 GB DDR3 | AC86: 480 GB SSD | AE86: Windows 11 Pro | AF86: Si | AG86: MS Office 365 HB | AJ86: HOTELERA COSTA DEL PACIFICO | AK86: Operativo | AL86: 009109508 | AM86: =VLOOKUP(AL86,Personal!$A$2:$I$300,2,FALSE) -> 0000F00049 | AN86: =VLOOKUP(AL86,Personal!$A$2:$I$300,3,FALSE) -> LOPEZ PEREZ JUAN | AO86: =VLOOKUP(AL86,Personal!$A$2:$I$300,6,FALSE) -> Chef Ejecutivo | AP86: =VLOOKUP(AL86,Personal!$A$2:$I$300,7,FALSE) -> Cocina | AQ86: =VLOOKUP(AL86,Personal!$A$2:$I$300,8,FALSE) -> Cocina
B87: 82 | G87: PC | H87: Usuario | I87: Dell | J87: Optiplex 3020 | K87: GK5FN22 | L87: 0WMJ54 | S87: B0-83-FE-5E-9D-43 | U87: 10.9.10.38 | V87: LIMH1W10GYM02 | W87: LIMDHGYM01 | X87: Intel Core i5 | Y87: 4ta Gen. | Z87: Intel Integrado | AA87: 16 GB DDR3 | AC87: 480 GB SSD | AE87: Windows 11 Pro | AF87: Si | AG87: MS Office 365 HB | AJ87: HOTELERA COSTA DEL PACIFICO | AK87: Operativo | AL87: 45274548 | AM87: =VLOOKUP(AL87,Personal!$A$2:$I$300,2,FALSE) -> 0000001776 | AN87: =VLOOKUP(AL87,Personal!$A$2:$I$300,3,FALSE) -> MOGROVEJO BRACESCO ANDREA CAROLINA | AO87: =VLOOKUP(AL87,Personal!$A$2:$I$300,6,FALSE) -> Supervisor de Gimnasio | AP87: =VLOOKUP(AL87,Personal!$A$2:$I$300,7,FALSE) -> Gym & Spa | AQ87: =VLOOKUP(AL87,Personal!$A$2:$I$300,8,FALSE) -> División de Habitaciones (Operaciones)
B88: 83 | G88: PC | H88: Usuario | I88: Dell | J88: Optiplex 3020 | K88: GJVQN22 | L88: 0WMJ54 | S88: B0-83-FE-5E-89-1A | U88: 10.72.10.87 | V88: limh1w10p005 | W88: LIMAYBRS | X88: Intel Core i5 | Y88: 4ta Gen. | Z88: Intel Integrado | AA88: 16 GB DDR3 | AC88: 480 GB SSD | AE88: Windows 11 Pro | AF88: Si | AG88: MS Office 2007 HB | AJ88: HOTELERA COSTA DEL PACIFICO | AK88: Operativo | AL88: 46960867 | AM88: =VLOOKUP(AL88,Personal!$A$2:$I$300,2,FALSE) -> 0000001462 | AN88: =VLOOKUP(AL88,Personal!$A$2:$I$300,3,FALSE) -> HUAPAYA PEREZ LUIS ANGEL | AO88: =VLOOKUP(AL88,Personal!$A$2:$I$300,6,FALSE) -> Supervisor de A&B | AP88: =VLOOKUP(AL88,Personal!$A$2:$I$300,7,FALSE) -> Room Service | AQ88: =VLOOKUP(AL88,Personal!$A$2:$I$300,8,FALSE) -> Alimentos y Bebidas
B89: 84 | G89: PC | H89: Usuario | I89: Dell | J89: Optiplex 3020 | K89: D07QN22 | L89: 0WMJ54 | S89: B0-83-FE-5E-FE-79 | U89: 10.72.10.63 | V89: limh1w10p008 | W89: LIMAYBLC02 | X89: Intel Core i5 | Y89: 4ta Gen. | Z89: Intel Integrado | AA89: 16 GB DDR3 | AC89: 480 GB SSD | AE89: Windows 11 Pro | AF89: Si | AG89: MS Office 2007 HB | AJ89: HOTELERA COSTA DEL PACIFICO | AK89: Operativo | AL89: 71337245 | AM89: =VLOOKUP(AL89,Personal!$A$2:$I$300,2,FALSE) -> 0000001575 | AN89: =VLOOKUP(AL89,Personal!$A$2:$I$300,3,FALSE) -> ABANTO CARRANZA ANDREA SOFIA | AO89: =VLOOKUP(AL89,Personal!$A$2:$I$300,6,FALSE) -> Consejero Gastronómico | AP89: =VLOOKUP(AL89,Personal!$A$2:$I$300,7,FALSE) -> Le Café | AQ89: =VLOOKUP(AL89,Personal!$A$2:$I$300,8,FALSE) -> Alimentos y Bebidas
B90: 85 | G90: PC | H90: Usuario | I90: Dell | J90: Optiplex 3020 | K90: 35DWN22 | L90: 0WMJ54 | S90: B0-83-FE-52-AA-3A | U90: 10.72.10.135 | V90: limh1w10p009 | W90: LIMRD01 | X90: Intel Core i5 | Y90: 4ta Gen. | Z90: Intel Integrado | AA90: 16 GB DDR3 | AC90: 480 GB SSD | AE90: Windows 11 Pro | AF90: Si | AG90: MS Office 2007 HB | AJ90: HOTELERA COSTA DEL PACIFICO | AK90: Operativo | AL90: 70005695 | AM90: =VLOOKUP(AL90,Personal!$A$2:$I$300,2,FALSE) -> 0000001335 | AN90: =VLOOKUP(AL90,Personal!$A$2:$I$300,3,FALSE) -> CARBAJAL BRAVO ROMMEL MARTIN | AO90: =VLOOKUP(AL90,Personal!$A$2:$I$300,6,FALSE) -> Gerente de Turno | AP90: =VLOOKUP(AL90,Personal!$A$2:$I$300,7,FALSE) -> Recepción | AQ90: =VLOOKUP(AL90,Personal!$A$2:$I$300,8,FALSE) -> División de Habitaciones (Operaciones)
B91: 86 | G91: PC | H91: Usuario | I91: Dell | J91: Optiplex 3020 | K91: GK2HN22 | L91: 0WMJ54 | S91: B0-83-FE-5E-9D-8E | U91: 10.72.10.72 | V91: limh1w10p011 | W91: LIMAYBLL | X91: Intel Core i5 | Y91: 4ta Gen. | Z91: Intel Integrado | AA91: 16 GB DDR3 | AC91: 480 GB SSD | AE91: Windows 11 Pro | AF91: Si | AG91: MS Office 2007 HB | AJ91: HOTELERA COSTA DEL PACIFICO | AK91: Operativo | AL91: 76211885 | AM91: =VLOOKUP(AL91,Personal!$A$2:$I$300,2,FALSE) -> 0000001539 | AN91: =VLOOKUP(AL91,Personal!$A$2:$I$300,3,FALSE) -> HERRERA SOLIS CLAUDIA DANIELA FELICITA | AO91: =VLOOKUP(AL91,Personal!$A$2:$I$300,6,FALSE) -> Restaurant Manager | AP91: =VLOOKUP(AL91,Personal!$A$2:$I$300,7,FALSE) -> La Locanda | AQ91: =VLOOKUP(AL91,Personal!$A$2:$I$300,8,FALSE) -> Alimentos y Bebidas
B92: 87 | G92: PC | H92: Usuario | I92: Dell | J92: Optiplex 3020 | K92: D1LDN22 | L92: 0WMJ54 | S92: B0-83-FE-5F-4B-CF | U92: 10.72.10.136 | V92: limh1w10p013 | W92: LIMDHHK01 | X92: Intel Core i5 | Y92: 4ta Gen. | Z92: Intel Integrado | AA92: 16 GB DDR3 | AC92: 480 GB SSD | AE92: Windows 11 Pro | AF92: Si | AG92: MS Office 2007 HB | AJ92: HOTELERA COSTA DEL PACIFICO | AK92: Operativo | AL92: 43329158 | AM92: =VLOOKUP(AL92,Personal!$A$2:$I$300,2,FALSE) -> 0000001417 | AN92: =VLOOKUP(AL92,Personal!$A$2:$I$300,3,FALSE) -> CARDENAS ALCAZABA PAOLA RAQUEL | AO92: =VLOOKUP(AL92,Personal!$A$2:$I$300,6,FALSE) -> Supervisor Jr. De Housekeeping | AP92: =VLOOKUP(AL92,Personal!$A$2:$I$300,7,FALSE) -> Housekeeping | AQ92: =VLOOKUP(AL92,Personal!$A$2:$I$300,8,FALSE) -> División de Habitaciones (Operaciones)
B93: 88 | G93: PC | H93: Usuario | I93: Dell | J93: Optiplex 3020 | K93: GJXSN22 | L93: 0WMJ54 | S93: B0-83-FE-5E-9D-8A | U93: 10.72.10.159 | V93: limh1w10p017 | W93: LIMDHLIM | X93: Intel Core i5 | Y93: 4ta Gen. | Z93: Intel Integrado | AA93: 16 GB DDR3 | AC93: 480 GB SSD | AE93: Windows 11 Pro | AF93: Si | AG93: MS Office 2007 HB | AJ93: HOTELERA COSTA DEL PACIFICO | AK93: Operativo | AL93: 09884050 | AM93: =VLOOKUP(AL93,Personal!$A$2:$I$300,2,FALSE) -> 0000000345 | AN93: =VLOOKUP(AL93,Personal!$A$2:$I$300,3,FALSE) -> MARTINEZ SOTELO LUIS ENRIQUE | AO93: =VLOOKUP(AL93,Personal!$A$2:$I$300,6,FALSE) -> Supervisor Senior de Limpieza | AP93: =VLOOKUP(AL93,Personal!$A$2:$I$300,7,FALSE) -> Limpieza | AQ93: =VLOOKUP(AL93,Personal!$A$2:$I$300,8,FALSE) -> División de Habitaciones (Operaciones) | AR93: Para 0000000345
B94: 89 | G94: PC | H94: Usuario | I94: Dell | J94: Optiplex 3020 | K94: D0KQN22 | L94: 0WMJ54 | S94: B0-83-FE-5E-FE-DB | V94: limh1w10p024 | X94: Intel Core i5 | Y94: 4ta Gen. | Z94: Intel Integrado | AA94: 8 GB DDR3 | AC94: 500 GB HDD | AE94: Windows 10 Pro | AG94: MS Office 2007 HB | AJ94: HOTELERA COSTA DEL PACIFICO | AK94: Custodia - Por Revisar | AL94: 10479259 | AM94: =VLOOKUP(AL94,Personal!$A$2:$I$300,2,FALSE) -> 0000000031 | AN94: =VLOOKUP(AL94,Personal!$A$2:$I$300,3,FALSE) -> MEDINA CASTILLO ALVARO GERARDO | AO94: =VLOOKUP(AL94,Personal!$A$2:$I$300,6,FALSE) -> Sub Gerente de A&B | AP94: =VLOOKUP(AL94,Personal!$A$2:$I$300,7,FALSE) -> Gerencia A&B | AQ94: =VLOOKUP(AL94,Personal!$A$2:$I$300,8,FALSE) -> Alimentos y Bebidas | AR94: HDD no está operando, no es reconocido por la placa
B95: 90 | G95: PC | H95: Usuario | I95: Dell | J95: Optiplex 3020 | K95: CZYRN22 | L95: 0WMJ54 | S95: B0-83-FE-55-14-B7 | U95: 10.72.10.76 | V95: limh1w10p030 | W95: LIMPCGCD | X95: Intel Core i5 | Y95: 4ta Gen. | Z95: Intel Integrado | AA95: 16 GB DDR3 | AC95: 480 GB SSD | AE95: Windows 11 Pro | AF95: Si | AG95: MS Office 365 HB | AJ95: HOTELERA COSTA DEL PACIFICO | AK95: Operativo | AL95: 10710564 | AM95: =VLOOKUP(AL95,Personal!$A$2:$I$300,2,FALSE) -> 0000000875 | AN95: =VLOOKUP(AL95,Personal!$A$2:$I$300,3,FALSE) -> COBOS GRANDA GLADYS EDITH | AO95: =VLOOKUP(AL95,Personal!$A$2:$I$300,6,FALSE) -> Gerente de Capacitación y Desarrollo | AP95: =VLOOKUP(AL95,Personal!$A$2:$I$300,7,FALSE) -> Personas y Cultura | AQ95: =VLOOKUP(AL95,Personal!$A$2:$I$300,8,FALSE) -> Personas y Cultura | AR95: Tiene casi toda su información llena en el disco, se recomienda guardar su info en el server
B96: 91 | G96: PC | H96: Usuario | I96: Dell | J96: Optiplex 3020 | K96: D0DDN22 | L96: 0WMJ54 | S96: B0-83-FE-5F-03-FD | U96: 10.72.10.77 | V96: limh1w10p047 | W96: LIMDHSLV | X96: Intel Core i5 | Y96: 4ta Gen. | Z96: Intel Integrado | AA96: 16 GB DDR3 | AC96: 480 GB SSD | AE96: Windows 11 Pro | AF96: Si | AG96: MS Office 2007 HB | AJ96: HOTELERA COSTA DEL PACIFICO | AK96: Operativo | AL96: 42354767 | AM96: =VLOOKUP(AL96,Personal!$A$2:$I$300,2,FALSE) -> 0000000809 | AN96: =VLOOKUP(AL96,Personal!$A$2:$I$300,3,FALSE) -> VALDERRAMA ALVAREZ PABLO CESAR | AO96: =VLOOKUP(AL96,Personal!$A$2:$I$300,6,FALSE) -> Supervisor Senior de Lavanderia | AP96: =VLOOKUP(AL96,Personal!$A$2:$I$300,7,FALSE) -> Lavandería | AQ96: =VLOOKUP(AL96,Personal!$A$2:$I$300,8,FALSE) -> División de Habitaciones (Operaciones)
B97: 92 | G97: PC | H97: Usuario | I97: Dell | J97: Optiplex 3020 | K97: D05SN22 | L97: 0WMJ54 | S97: B0-83-FE-55-27-FF | U97: 10.72.10.86 | V97: limh1w10p054 | W97: LIMDHJHK | X97: Intel Core i5 | Y97: 4ta Gen. | Z97: Intel Integrado | AA97: 16 GB DDR3 | AC97: 480 GB SSD | AE97: Windows 11 Pro | AF97: Si | AG97: MS Office 365 HB | AJ97: HOTELERA COSTA DEL PACIFICO | AK97: Operativo | AL97: 41302115 | AM97: =VLOOKUP(AL97,Personal!$A$2:$I$300,2,FALSE) -> 0000001663 | AN97: =VLOOKUP(AL97,Personal!$A$2:$I$300,3,FALSE) -> LLACSAHUANGA VALENCIA EDITH | AO97: =VLOOKUP(AL97,Personal!$A$2:$I$300,6,FALSE) -> Jefe de Housekeeping | AP97: =VLOOKUP(AL97,Personal!$A$2:$I$300,7,FALSE) -> Housekeeping | AQ97: =VLOOKUP(AL97,Personal!$A$2:$I$300,8,FALSE) -> División de Habitaciones (Operaciones)
B98: 93 | G98: PC | H98: Usuario | I98: Dell | J98: Optiplex 3020 | K98: CZVGN22 | L98: 0WMJ54 | S98: B0-83-FE-5F-8F-4F | U98: 10.72.10.92 | W98: LIMCMP5 | X98: Intel Core i5 | Y98: 4ta Gen. | Z98: Intel Integrado | AA98: 8 GB DDR3 | AC98: 250 GB SSD | AE98: Windows 11 Pro | AF98: Si | AG98: MS Office 2007 HB | AJ98: HOTELERA COSTA DEL PACIFICO | AK98: Operativo | AL98: Puerta 5 | AM98: =VLOOKUP(AL98,Personal!$A$2:$I$300,2,FALSE) -> Puerta 5 | AN98: =VLOOKUP(AL98,Personal!$A$2:$I$300,3,FALSE) -> Puerta 5 | AO98: =VLOOKUP(AL98,Personal!$A$2:$I$300,6,FALSE) -> Empleado Puesto de Control | AP98: =VLOOKUP(AL98,Personal!$A$2:$I$300,7,FALSE) -> Control y Monitoreo | AQ98: =VLOOKUP(AL98,Personal!$A$2:$I$300,8,FALSE) -> Control y Monitoreo
B99: 94 | G99: PC | H99: Usuario | I99: Dell | J99: Optiplex 3020 | K99: 359ZN22 | L99: 0WMJ54 | S99: B0-83-FE-52-AA-84 | U99: 10.72.10.100 | V99: LIMH1W10P061 | W99: LIMAYBBQ02 | X99: Intel Core i5 | Y99: 4ta Gen. | Z99: Intel Integrado | AA99: 16 GB DDR3 | AC99: 480 GB SSD | AE99: Windows 11 Pro | AF99: Si | AG99: MS Office 2007 HB | AJ99: HOTELERA COSTA DEL PACIFICO | AK99: Operativo | AL99: 75623367 | AM99: =VLOOKUP(AL99,Personal!$A$2:$I$300,2,FALSE) -> 0000001439 | AN99: =VLOOKUP(AL99,Personal!$A$2:$I$300,3,FALSE) -> GOMEZ COBEÑA PERCY BOLIVAR | AO99: =VLOOKUP(AL99,Personal!$A$2:$I$300,6,FALSE) -> Capitán de Banquetes | AP99: =VLOOKUP(AL99,Personal!$A$2:$I$300,7,FALSE) -> Banquetes | AQ99: =VLOOKUP(AL99,Personal!$A$2:$I$300,8,FALSE) -> Alimentos y Bebidas
B100: 95 | G100: PC | H100: Usuario | I100: Dell | J100: Optiplex 3020 | K100: 355YN22 | L100: 0WMJ54 | S100: B0-83-FE-52-C5-64 | U100: 10.72.10.17 | V100: LIMH1W10P062 | X100: Intel Core i5 | Y100: 4ta Gen. | Z100: Intel Integrado | AA100: 8 GB DDR3 | AC100: 480 GB SSD | AE100: Windows 10 Pro | AG100: MS Office 2007 HB | AJ100: HOTELERA COSTA DEL PACIFICO | AK100: Operativo | AL100: 02856974 | AM100: =VLOOKUP(AL100,Personal!$A$2:$I$300,2,FALSE) -> 0000001501 | AN100: =VLOOKUP(AL100,Personal!$A$2:$I$300,3,FALSE) -> YAMUNAQUE CASTILLO HECTOR ARTURO | AO100: =VLOOKUP(AL100,Personal!$A$2:$I$300,6,FALSE) -> Gerente de Sistemas | AP100: =VLOOKUP(AL100,Personal!$A$2:$I$300,7,FALSE) -> Tecnologias de Información | AQ100: =VLOOKUP(AL100,Personal!$A$2:$I$300,8,FALSE) -> Tecnologias de Información
B101: 96 | G101: PC | H101: Usuario | I101: Dell | J101: Optiplex 3020 | K101: D0KRN22 | L101: 0WMJ54 | S101: B0-83-FE-5F-01-A4 | V101: LIMH1W10P066 | X101: Intel Core i5 | Y101: 4ta Gen. | Z101: Intel Integrado | AA101: 8 GB DDR3 | AC101: 500 GB HDD | AE101: Windows 10 Pro | AG101: MS Office 2007 HB | AJ101: HOTELERA COSTA DEL PACIFICO | AK101: Custodia - Inoperativo | AL101: 40856376 | AM101: =VLOOKUP(AL101,Personal!$A$2:$I$300,2,FALSE) -> 0000000772 | AN101: =VLOOKUP(AL101,Personal!$A$2:$I$300,3,FALSE) -> CARHUANCOTA CHAVEZ ANDRES ALBERTO | AO101: =VLOOKUP(AL101,Personal!$A$2:$I$300,6,FALSE) -> Asistente Senior de Contabilidad | AP101: =VLOOKUP(AL101,Personal!$A$2:$I$300,7,FALSE) -> Contabilidad | AQ101: =VLOOKUP(AL101,Personal!$A$2:$I$300,8,FALSE) -> Contraloría | AR101: Ex Andres Carhuanconta
B102: 97 | G102: PC | H102: Usuario | I102: HP | J102: Prodesk 600 G1 | K102: MXL3460T3Y | L102: E1Z56LT#ABM | S102: D4-C9-EF-F3-A7-A2 | U102: 10.72.10.71 | V102: LIMH1W10P081 | W102: LIMPCAPC | X102: Intel Core i7 | Y102: 4ta Gen. | Z102: Intel Integrado | AA102: 20 GB DDR3 | AC102: 480 GB SSD | AE102: Windows 11 Pro | AG102: MS Office 365 HB | AJ102: HOTELERA COSTA DEL PACIFICO | AK102: Operativo | AL102: 76204111 | AM102: =VLOOKUP(AL102,Personal!$A$2:$I$300,2,FALSE) -> 0000001670 | AN102: =VLOOKUP(AL102,Personal!$A$2:$I$300,3,FALSE) -> CARRERA PALACIOS ROSALIA RENE | AO102: =VLOOKUP(AL102,Personal!$A$2:$I$300,6,FALSE) -> Asistente de Personas y Cultura | AP102: =VLOOKUP(AL102,Personal!$A$2:$I$300,7,FALSE) -> Personas y Cultura | AQ102: =VLOOKUP(AL102,Personal!$A$2:$I$300,8,FALSE) -> Personas y Cultura
...

Sheet Dinamica
A3: Propiedad | B3: Unidad | C3: Centro de Costo | D3: Usuario | E3: Cargo | F3: Equipo | G3: Host | H3: Nombre Host | I3: IP | J3: Tipo | K3: Marca | L3: S/N | M3: Estado | N3: Ram | O3: Almacenamiento | P3: Sistema Operativo | Q3: Office | R3: Cuenta Equipos
A4: HOTELERA COSTA DEL PACIFICO | B4: Alimentos y Bebidas | C4: Banquetes | D4: FALCON PAZ JULIAN MIGUEL ANGEL | E4: Supervisor Senior de A&B | F4: PC | G4: LIMAYBBQ01 | H4: LIMH1W7P85 | I4: 10.72.10.83 | J4: Usuario | K4: Dell | L4: D04FN22 | M4: Operativo | N4: 16 GB DDR3 | O4: 480 GB SSD | P4: Windows 11 Pro | Q4: MS Office 2007 HB | R4: 1
D5: GOMEZ COBEÑA PERCY BOLIVAR | E5: Capitán de Banquetes | F5: PC | G5: LIMAYBBQ02 | H5: LIMH1W10P061 | I5: 10.72.10.100 | J5: Usuario | K5: Dell | L5: 359ZN22 | M5: Operativo | N5: 16 GB DDR3 | O5: 480 GB SSD | P5: Windows 11 Pro | Q5: MS Office 2007 HB | R5: 1
C6: Gerencia A&B | D6: JARA RISCO GINO | E6: Director de Alimentos y Bebidas | F6: PC | G6: (en blanco) | H6: LIMH1W11P071 | I6: 10.72.10.41 | J6: Usuario | K6: Dell | L6: CZPRN22 | M6: Operativo | N6: 16 GB DDR3 | O6: 480 GB SSD | P6: Windows 11 Pro | Q6: MS Office 2007 HB | R6: 1
D7: MEDINA CASTILLO ALVARO GERARDO | E7: Sub Gerente de A&B | F7: PC | G7: LIMAYBSGER | H7: (en blanco) | I7: 10.72.10.103 | J7: Usuario | K7: Dell | L7: D00RN22 | M7: Operativo | N7: 16 GB DDR3 | O7: 480 GB SSD | P7: Windows 11 Pro | Q7: MS Office 365 HB | R7: 1
D8: RAMOS MAGAN HANNA GRACE | E8: Asistente Administrativa Jr. | F8: PC | G8: LIMFB02 | H8: (en blanco) | I8: 10.72.10.93 | J8: Usuario | K8: Dell | L8: GK6DN22 | M8: Operativo | N8: 16 GB DDR3 | O8: 480 GB SSD | P8: Windows 11 Pro | Q8: MS Office 2007 HB | R8: 1
D9: ROMAN ZUÑIGA ANNIE PAOLA | E9: Gerente de Alimentos y Bebidas | F9: PC | G9: LIMAYBGER | H9: (en blanco) | I9: 10.72.10.161 | J9: Usuario | K9: Dell | L9: 356YN22 | M9: Operativo | N9: 16 GB DDR3 | O9: 480 GB SSD | P9: Windows 11 Pro | Q9: MS Office 365 HB | R9: 1
C10: La Locanda | D10: HERRERA SOLIS CLAUDIA DANIELA FELICITA | E10: Restaurant Manager | F10: PC | G10: LIMAYBLL | H10: limh1w10p011 | I10: 10.72.10.72 | J10: Usuario | K10: Dell | L10: GK2HN22 | M10: Operativo | N10: 16 GB DDR3 | O10: 480 GB SSD | P10: Windows 11 Pro | Q10: MS Office 2007 HB | R10: 1
C11: Le Café | D11: ABANTO CARRANZA ANDREA SOFIA | E11: Consejero Gastronómico | F11: PC | G11: LIMAYBLC02 | H11: limh1w10p008 | I11: 10.72.10.63 | J11: Usuario | K11: Dell | L11: D07QN22 | M11: Operativo | N11: 16 GB DDR3 | O11: 480 GB SSD | P11: Windows 11 Pro | Q11: MS Office 2007 HB | R11: 1
D12: GUTIERREZ OYARDO ANGELA GEORGINA | E12: Consejero Gastronómico | F12: PC | G12: LIMAYBLC01 | H12: (en blanco) | I12: 10.72.10.118 | J12: Usuario | K12: Dell | L12: D1FDN22 | M12: Operativo | N12: 16 GB DDR3 | O12: 480 GB SSD | P12: Windows 11 Pro | Q12: MS Office 365 HB | R12: 1
C13: Lobby | D13: UGAZ OLIVARES PALOMA | E13: Supervisor Senior de A&B | F13: PC | G13: LIMAYBLB | H13: LIMH1W7P95 | I13: 10.72.10.44 | J13: Usuario | K13: Dell | L13: 352YN22 | M13: Operativo | N13: 16 GB DDR3 | O13: 480 GB SSD | P13: Windows 11 Pro | Q13: MS Office 2007 HB | R13: 1
C14: Room Service | D14: HUAPAYA PEREZ LUIS ANGEL | E14: Supervisor de A&B | F14: PC | G14: LIMAYBRS | H14: limh1w10p005 | I14: 10.72.10.87 | J14: Usuario | K14: Dell | L14: GJVQN22 | M14: Operativo | N14: 16 GB DDR3 | O14: 480 GB SSD | P14: Windows 11 Pro | Q14: MS Office 2007 HB | R14: 1
C15: Steward | D15: VEGA ARRATEA JAVIER VICTOR | E15: Supervisor Jr. de Steward | F15: PC | G15: LIMFBSW | H15: (en blanco) | I15: 10.72.10.84 | J15: Usuario | K15: Dell | L15: GK2QN22 | M15: Operativo | N15: 16 GB DDR3 | O15: 480 GB SSD | P15: Windows 11 Pro | Q15: MS Office 2007 HB | R15: 1
C16: Piso Ejecutivo | D16: RODRIGUEZ ESPINOZA CYANE MILAGROS | E16: Consejero Gastronómico | F16: PC | G16: (en blanco) | H16: LIMH1W7P05 | I16: 10.72.10.164 | J16: Usuario | K16: HP | L16: MXL4321BFX | M16: Operativo | N16: 12 GB DDR3 | O16: 250 GB SSD | P16: Windows 11 Pro | Q16: MS Office 2007 HB | R16: 1
B17: Total Alimentos y Bebidas | R17: 13
B18: Cocina | C18: Calidad | D18: ALEGRE ANGELES FERNANDA LUCIA | E18: Jefa de Aseguramiento de Calidad | F18: PC | G18: LIMCOC06 | H18: (en blanco) | I18: (en blanco) | J18: Usuario | K18: HP | L18: 9CG6262196 | M18: Operativo | N18: 8 GB DDR4 | O18: 250 GB SSD | P18: Windows 11 Pro | Q18: MS Office 365 HB | R18: 1
D19: CONDORI MORENO ELIZABETH CINTHIA | E19: Asistente de Calidad | F19: PC | G19: LIMCOC05 | H19: (en blanco) | I19: 10.72.10.138 | J19: Usuario | K19: Dell | L19: D01GN22 | M19: Operativo | N19: 16 GB DDR3 | O19: 480 GB SSD | P19: Windows 11 Pro | Q19: MS Office 365 HB | R19: 1
C20: Cocina | D20: LOPEZ PEREZ JUAN | E20: Chef Ejecutivo | F20: PC | G20: LIMCHEF | H20: LIMH1W10FB010 | I20: 10.72.10.106 | J20: Usuario | K20: Dell | L20: D09HN22 | M20: Operativo | N20: 16 GB DDR3 | O20: 480 GB SSD | P20: Windows 11 Pro | Q20: MS Office 365 HB | R20: 1
D21: TRONCOS REQUEJO MELANIE ALICIA | E21: Practicante Administrativo de Cocina | F21: PC | G21: LIMCOC02 | H21: (en blanco) | I21: 10.72.10.49 | J21: Usuario | K21: Dell | L21: D1HFN22 | M21: Operativo | N21: 16 GB DDR3 | O21: 480 GB SSD | P21: Windows 11 Pro | Q21: MS Office 365 HB | R21: 1
C22: Cocina La Locanda | D22: BAUTISTA CARDENAS MIGUEL ALEJANDRO | E22: Sub Chef | F22: PC | G22: LIMCOC03 | H22: LIMH1W11FB12 | I22: 10.72.10.144 | J22: Usuario | K22: Dell | L22: CZNQN22 | M22: Operativo | N22: 16 GB DDR3 | O22: 250 GB SSD | P22: Windows 11 Pro | Q22: MS Office 2007 HB | R22: 1
G23: LIMCOC04 | H23: LIMH1FBPC06 | I23: 10.72.10.157 | J23: Usuario | K23: Dell | L23: CZYQN22 | M23: Operativo | N23: 16 GB DDR3 | O23: 480 GB SSD | P23: Windows 11 Pro | Q23: MS Office 2007 HB | R23: 1
C24: Pastelería | D24: CHAVEZ LING SUSANA BETSABE | E24: Supervisor Pasteleria / Panadería | F24: PC | G24: LIMCOC01 | H24: LIMH1W11FB12 | I24: 10.72.10.99 | J24: Usuario | K24: Dell | L24: 3510P22 | M24: Operativo | N24: 12 GB DDR3 | O24: 480 GB SSD | P24: Windows 11 Pro | Q24: MS Office 365 HB | R24: 1
B25: Total Cocina | R25: 7
B26: Compras | C26: Compras | D26: CASTRO MORA NELLY YOLANDA | E26: Gerente de Compras Regional | F26: Laptop | G26: LIMPU01 | H26: (en blanco) | I26: 10.72.10.101 | J26: Usuario | K26: Lenovo | L26: PF3KWH96 | M26: Operativo | N26: 16 GB DDR4 | O26: 1000 GB SSD | P26: Windows 11 Pro | Q26: MS Office 365 HB | R26: 1
D27: OBARA AVI JUAN FERNANDO | E27: Gerente de Compras | F27: PC | G27: LIMCOMPGC | H27: LIMH1PUPC001 | I27: 10.72.10.51 | J27: Usuario | K27: Dell | L27: 35CXN22 | M27: Operativo | N27: 16 GB DDR3 | O27: 480 GB SSD | P27: Windows 11 Pro | Q27: MS Office 2007 HB | R27: 1
B28: Total Compras | R28: 2
B29: Contraloría | C29: Auditoría de Ingresos | D29: MOTA CASTRO JIM EDUARDO | E29: Auditor de Ingresos | F29: PC | G29: LIMCNTAI | H29: LIMH1W7P65 | I29: 10.72.10.138 | J29: Usuario | K29: Dell | L29: D09RN22 | M29: Operativo | N29: 16 GB DDR3 | O29: 480 GB SSD | P29: Windows 11 Pro | Q29: MS Office 2007 HB | R29: 1
G30: LIMCNTAI02 | H30: (en blanco) | I30: 10.72.10.139 | J30: Usuario | K30: Dell | L30: 3550P22 | M30: Operativo | N30: 16 GB DDR3 | O30: 480 GB SSD | P30: Windows 11 Pro | Q30: MS Office 2007 HB | R30: 1
C31: Bodegas | D31: CARPIO PONCE GARY ANDRES | E31: Bodeguero | F31: PC | G31: LIMCNTBG01 | H31: LIMH1W10P100 | I31: 10.72.10.81 | J31: Usuario | K31: Dell | L31: 351YN22 | M31: Operativo | N31: 16 GB DDR3 | O31: 480 GB SSD | P31: Windows 11 Pro | Q31: MS Office 2007 HB | R31: 1
C32: Contabilidad | D32: ALVARADO CHAVARRY JIMMY GERARDO | E32: Sub Contralor | F32: PC | G32: LIMCNTSC | H32: (en blanco) | I32: 10.72.10.177 | J32: Usuario | K32: Lenovo | L32: YLT1642S | M32: Operativo | N32: 16 GB DDR5 | O32: 480 GB SSD | P32: Windows 11 Pro | Q32: MS Office 365 HB | R32: 1
D33: CARHUANCOTA CHAVEZ ANDRES ALBERTO | E33: Asistente Senior de Contabilidad | F33: PC | G33: LIMCNTCONT3 | H33: LIMH1W7P101 | I33: 10.72.10.133 | J33: Usuario | K33: Dell | L33: D0HRN22 | M33: Operativo | N33: 16 GB DDR3 | O33: 480 GB SSD | P33: Windows 11 Pro | Q33: MS Office 2007 HB | R33: 1
G34: LIMCNTCONT4 | H34: (en blanco) | I34: (en blanco) | J34: Usuario | K34: HP | L34: MXL5283YYX | M34: Operativo | N34: 16 GB DDR5 | O34: 1000 GB SSD | P34: Windows 11 Pro | Q34: MS Office 365 HB | R34: 1
D35: FLORES RAMIREZ PERCY FERNANDO | E35: Asistente de Cuentas por Cobrar | F35: PC | G35: LIMH1W11AC02 | H35: (en blanco) | I35: 10.72.10.94 | J35: Usuario | K35: Lenovo | L35: (en blanco) | M35: Operativo | N35: 16 GB DDR5 | O35: 1000 GB SSD | P35: Windows 11 Pro | Q35: MS Office 365 HB | R35: 1
D36: HUAYAMA INGAROCA MERCEDES GRACIELA | E36: Practicante de Contabilidad | F36: PC | G36: LIMCNTCONT7 | H36: (en blanco) | I36: 10.72.10.125 | J36: Usuario | K36: Dell | L36: GJWSN22 | M36: Operativo | N36: 16 GB DDR3 | O36: 480 GB SSD | P36: Windows 11 Pro | Q36: MS Office 2007 HB | R36: 1
D37: MILLA GOMEZ ANJALI ABIGAIL | E37: Practicante de Contabilidad | F37: PC | G37: LIMCNTCONT8 | H37: (en blanco) | I37: 10.72.10.129 | J37: Usuario | K37: Dell | L37: CZZFN22 | M37: Operativo | N37: 16 GB DDR3 | O37: 480 GB SSD | P37: Windows 11 Pro | Q37: (en blanco) | R37: 1
D38: ORELLANA CHIPANA MARTIN SANTIAGO | E38: Practicante de Contabilidad | F38: PC | G38: LIMCNTCONT6 | H38: LIMH1W7P57 | I38: 10.72.10.110 | J38: Usuario | K38: Dell | L38: D05FN22 | M38: Operativo | N38: 16 GB DDR3 | O38: 480 GB SSD | P38: Windows 11 Pro | Q38: MS Office 2007 HB | R38: 1
D39: ORELLANA GODOY MELCHORA OLINDA | E39: Contador | F39: PC | G39: (en blanco) | H39: LIMH1W10PC0011 | I39: 10.72.10.73 | J39: Usuario | K39: Dell | L39: 8RLT5X3 | M39: Operativo | N39: 32 GB DDR5 | O39: 500 GB SSD | P39: Windows 11 Pro | Q39: MS Office 2007 HB | R39: 1
D40: SEGOVIA CRISPIN XAVIER ALONSO | E40: Asistente de Contabilidad | F40: PC | G40: (en blanco) | H40: LIMH1W10PC005 | I40: 10.72.10.90 | J40: Usuario | K40: Dell | L40: 7HHT5X3 | M40: Operativo | N40: 32 GB DDR5 | O40: 500 GB SSD | P40: Windows 11 Pro | Q40: MS Office 2007 HB | R40: 1
D41: SISTEMAS DE ACTIVOS FIJOS | E41: Sistema de Activos Fijos | F41: PC | G41: LIMH1GMPC02 | H41: LIMH1GMPC02 | I41: 10.72.10.70 | J41: Usuario | K41: Dell | L41: 353YN22 | M41: Operativo | N41: 8 GB DDR3 | O41: 250 GB SSD | P41: Windows 10 Pro | Q41: MS Office 2007 HB | R41: 1
D42: TISNADO MEGO LEIDER ALFONZO | E42: Encargado de Costos | F42: PC | G42: LIMCNTCONT5 | H42: LIMH1ACPC003 | I42: 10.72.10.53 | J42: Usuario | K42: Dell | L42: D0HFN22 | M42: Operativo | N42: 16 GB DDR3 | O42: 480 GB SSD | P42: Windows 11 Pro | Q42: MS Office 365 HB | R42: 1
C43: Contraloría | D43: PINEDA LOPEZ GLADYS DIANA | E43: Contralora Regional | F43: Laptop | G43: (en blanco) | H43: (en blanco) | I43: (en blanco) | J43: Usuario | K43: Lenovo | L43: (en blanco) | M43: Operativo | N43: 8 GB DDR4 | O43: 250 GB SSD | P43: Windows 11 Pro | Q43: MS Office 365 HB | R43: 1
B44: Total Contraloría | R44: 15
B45: Control y Monitoreo | C45: Control y Monitoreo | D45: Control y Monitoreo | E45: Empleado Puesto de Control | F45: PC | G45: LIMCMSCM01 | H45: (en blanco) | I45: 10.72.10.109 | J45: Usuario | K45: Dell | L45: D1BSN22 | M45: Operativo | N45: 16 GB DDR3 | O45: 480 GB SSD | P45: Windows 11 Pro | Q45: (en blanco) | R45: 1
D46: MENDIETA SOLANO WILLIAM JESUS | E46: Gerente de Control y Monitero | F46: PC | G46: (en blanco) | H46: LIMH1W11P036 | I46: (en blanco) | J46: Usuario | K46: Dell | L46: D02QN22 | M46: Operativo | N46: 16 GB DDR3 | O46: 480 GB SSD | P46: Windows 11 Pro | Q46: MS Office 2007 HB | R46: 1
D47: Puerta 5 | E47: Empleado Puesto de Control | F47: PC | G47: LIMCMP5 | H47: (en blanco) | I47: 10.72.10.92 | J47: Usuario | K47: Dell | L47: CZVGN22 | M47: Operativo | N47: 8 GB DDR3 | O47: 250 GB SSD | P47: Windows 11 Pro | Q47: MS Office 2007 HB | R47: 1
C48: Seguridad y Salud en el Trabajo | D48: MARQUEZ GODOY LUIS ANGEL | E48: Analista de Seguridad y Salud en el Trabajo | F48: PC | G48: LIMCMASST | H48: LIMH1W10CM02 | I48: 10.72.10.93 | J48: Usuario | K48: Dell | L48: D00TN22 | M48: Operativo | N48: 12 GB DDR3 | O48: 480 GB SSD | P48: Windows 11 Pro | Q48: MS Office 365 HB | R48: 1
B49: Total Control y Monitoreo | R49: 4
B50: División de Habitaciones (Operaciones) | C50: Gym & Spa | D50: MOGROVEJO BRACESCO ANDREA CAROLINA | E50: Supervisor de Gimnasio | F50: PC | G50: LIMDHGYM01 | H50: LIMH1W10GYM02 | I50: 10.9.10.38 | J50: Usuario | K50: Dell | L50: GK5FN22 | M50: Operativo | N50: 16 GB DDR3 | O50: 480 GB SSD | P50: Windows 11 Pro | Q50: MS Office 365 HB | R50: 1
G51: (en blanco) | H51: LIMH1W11PMS100 | I51: 10.72.10.108 | J51: Usuario | K51: Dell | L51: 351XN22 | M51: Operativo | N51: 16 GB DDR3 | O51: 480 GB SSD | P51: Windows 11 Pro | Q51: MS Office 365 HB | R51: 1
C52: Housekeeping | D52: CARDENAS ALCAZABA PAOLA RAQUEL | E52: Supervisor Jr. De Housekeeping | F52: PC | G52: LIMDHHK01 | H52: limh1w10p013 | I52: 10.72.10.136 | J52: Usuario | K52: Dell | L52: D1LDN22 | M52: Operativo | N52: 16 GB DDR3 | O52: 480 GB SSD | P52: Windows 11 Pro | Q52: MS Office 2007 HB | R52: 1
D53: LLACSAHUANGA VALENCIA EDITH | E53: Jefe de Housekeeping | F53: PC | G53: LIMDHJHK | H53: limh1w10p054 | I53: 10.72.10.86 | J53: Usuario | K53: Dell | L53: D05SN22 | M53: Operativo | N53: 16 GB DDR3 | O53: 480 GB SSD | P53: Windows 11 Pro | Q53: MS Office 365 HB | R53: 1
D54: SICHA PEREZ IRIS GIOVANNA | E54: Supervisor Jr. De Housekeeping | F54: PC | G54: LIMH1W11HK01 | H54: LIMH1W11HK01 | I54: 10.72.10.148 | J54: Usuario | K54: Dell | L54: GJZRN22 | M54: Operativo | N54: 16 GB DDR3 | O54: 250 GB SSD | P54: Windows 11 Pro | Q54: MS Office 2007 HB | R54: 1
C55: Lavandería | D55: CERRON ACUÑA JUAN MIGUEL | E55: Supervisor Jr. De Lavanderia | F55: PC | G55: LIMH1W11HK02 | H55: LIMH1W11HK02 | I55: 10.72.10. | J55: Usuario | K55: Dell | L55: GJHGN22 | M55: Operativo | N55: 16 GB DDR3 | O55: 250 GB SSD | P55: Windows 11 Pro | Q55: MS Office 2007 HB | R55: 1
D56: VALDERRAMA ALVAREZ PABLO CESAR | E56: Supervisor Senior de Lavanderia | F56: PC | G56: LIMDHSLV | H56: limh1w10p047 | I56: 10.72.10.77 | J56: Usuario | K56: Dell | L56: D0DDN22 | M56: Operativo | N56: 16 GB DDR3 | O56: 480 GB SSD | P56: Windows 11 Pro | Q56: MS Office 2007 HB | R56: 1
C57: Limpieza | D57: MARTINEZ SOTELO LUIS ENRIQUE | E57: Supervisor Senior de Limpieza | F57: PC | G57: LIMDHLIM | H57: limh1w10p017 | I57: 10.72.10.159 | J57: Usuario | K57: Dell | L57: GJXSN22 | M57: Operativo | N57: 16 GB DDR3 | O57: 480 GB SSD | P57: Windows 11 Pro | Q57: MS Office 2007 HB | R57: 1
C58: Recepción | D58: CARBAJAL BRAVO ROMMEL MARTIN | E58: Gerente de Turno | F58: PC | G58: LIMRD01 | H58: limh1w10p009 | I58: 10.72.10.135 | J58: Usuario | K58: Dell | L58: 35DWN22 | M58: Operativo | N58: 16 GB DDR3 | O58: 480 GB SSD | P58: Windows 11 Pro | Q58: MS Office 2007 HB | R58: 1
D59: CARRILLO SILVA ENRIQUE RAFAEL | E59: Botones | F59: PC | G59: LIMDHBOT | H59: LIMH1W10PC0010 | I59: 10.72.10.67 | J59: Usuario | K59: Dell | L59: 34ZZN22 | M59: Operativo | N59: 16 GB DDR3 | O59: 480 GB SSD | P59: Windows 11 Pro | Q59: MS Office 2007 HB | R59: 1
D60: Front Desk 1 | E60: Recepcionista | F60: PC | G60: LIMFD01 | H60: (en blanco) | I60: 10.72.10.34 | J60: Usuario | K60: Lenovo | L60: YLT1643J | M60: Operativo | N60: 32 GB DDR5 | O60: 1000 GB SSD | P60: Windows 11 Pro | Q60: MS Office 2007 HB | R60: 1
D61: Front Desk 2 | E61: Recepcionista | F61: PC | G61: LIMFD02 | H61: (en blanco) | I61: 10.72.10.146 | J61: Usuario | K61: Lenovo | L61: YLT16443 | M61: Operativo | N61: 32 GB DDR5 | O61: 1000 GB SSD | P61: Windows 11 Pro | Q61: MS Office 2007 HB | R61: 1
D62: Front Desk 3 | E62: Recepcionista | F62: PC | G62: (en blanco) | H62: LIMH1W10P101 | I62: 10.72.10.50 | J62: Usuario | K62: Dell | L62: B8WS5X3 | M62: Operativo | N62: 32 GB DDR5 | O62: 500 GB SSD | P62: Windows 11 Pro | Q62: MS Office 2007 HB | R62: 1
D63: Front Desk 4 | E63: Recepcionista | F63: PC | G63: LIMFD04 | H63: LIMH1W7P34 | I63: 10.72.10.165 | J63: Usuario | K63: Lenovo | L63: YLT16FYF | M63: Operativo | N63: 32 GB DDR5 | O63: 1000 GB SSD | P63: Windows 11 Pro | Q63: MS Office 2007 HB | R63: 1
D64: HUAMAN NUÑUBERO ROSARIO NICOLE | E64: Recepcionista Back Office | F64: PC | G64: LIMDHREC | H64: (en blanco) | I64: 10.72.10.141 | J64: Usuario | K64: HP | L64: MXL3460T6K | M64: Operativo | N64: 16 GB DDR3 | O64: 480 GB SSD | P64: Windows 11 Pro | Q64: MS Office 2007 HB | R64: 1
D65: LUNA MARIÑO FANNY ISABEL | E65: Jefe de Recepción | F65: PC | G65: (en blanco) | H65: LIMH1W11FO03 | I65: 10.72.10.82 | J65: Usuario | K65: Dell | L65: D02FN22 | M65: Operativo | N65: 16 GB DDR3 | O65: 480 GB SSD | P65: Windows 11 Pro | Q65: MS Office 2007 HB | R65: 1
D66: NOVOA ZACIGA MEY-LIN | E66: Recepcionista | F66: PC | G66: LIMRD02 | H66: (en blanco) | I66: 10.72.10.112 | J66: Usuario | K66: Dell | L66: GK0GN22 | M66: Operativo | N66: 16 GB DDR3 | O66: 480 GB SSD | P66: Windows 11 Pro | Q66: MS Office 2007 HB | R66: 1
B67: Total División de Habitaciones (Operaciones) | R67: 17
B68: Gerencia General | C68: Gerencia General | D68: GAMBONI KOIFMAN DE TENORIO SANCHO DAVI C | E68: Asistente de Gerencia General | F68: PC | G68: LIMH1W10PC004 | H68: LIMH1W10PC004 | I68: 10.72.10.145 | J68: Usuario | K68: HP | L68: MXL4321BFP | M68: Operativo | N68: 32 GB DDR3 | O68: 500 GB SSD | P68: Windows 11 Pro | Q68: MS Office 2007 HB | R68: 1
B69: Total Gerencia General | R69: 1
B70: Personas y Cultura | C70: Personas y Cultura | D70: BRENDA STEFANY VILLAREAL MACHADO | E70: Trabajadora Social | F70: PC | G70: LIMPCAS | H70: (en blanco) | I70: 10.72.10.77 | J70: Usuario | K70: Dell | L70: 60YY282 | M70: Operativo | N70: 16 GB DDR3 | O70: 480 GB SSD | P70: Windows 11 Pro | Q70: MS Office 365 HB | R70: 1
D71: CARBAJAL SANDOVAL KARIN GEORGHET | E71: Enfermera | F71: PC | G71: LIMHR6 | H71: (en blanco) | I71: 10.72.10.91 | J71: Usuario | K71: Dell | L71: CZPQN22 | M71: Operativo | N71: 16 GB DDR3 | O71: 480 GB SSD | P71: Windows 11 Pro | Q71: MS Office 365 HB | R71: 1
D72: CARRERA PALACIOS ROSALIA RENE | E72: Asistente de Personas y Cultura | F72: PC | G72: LIMPCAPC | H72: LIMH1W10P081 | I72: 10.72.10.71 | J72: Usuario | K72: HP | L72: MXL3460T3Y | M72: Operativo | N72: 20 GB DDR3 | O72: 480 GB SSD | P72: Windows 11 Pro | Q72: MS Office 365 HB | R72: 1
D73: COBOS GRANDA GLADYS EDITH | E73: Gerente de Capacitación y Desarrollo | F73: PC | G73: LIMPCGCD | H73: limh1w10p030 | I73: 10.72.10.76 | J73: Usuario | K73: Dell | L73: CZYRN22 | M73: Operativo | N73: 16 GB DDR3 | O73: 480 GB SSD | P73: Windows 11 Pro | Q73: MS Office 365 HB | R73: 1
D74: TEJADA RIVEROS DIEGO JOEL | E74: Gerente de Personas y Cultura | F74: PC | G74: LIMH1W10P102 | H74: LIMH1W10P102 | I74: 10.72.10.25 | J74: Usuario | K74: Dell | L74: H4WS5X3 | M74: Operativo | N74: 32 GB DDR5 | O74: 500 GB SSD + 500 GB HDD | P74: Windows 11 Pro | Q74: MS Office 365 HB | R74: 1
B75: Total Personas y Cultura | R75: 5
B76: Tecnologias de Información | C76: Tecnologias de Información | D76: SALINAS TORRES NOE | E76: Analista de Sistemas | F76: Laptop | G76: (en blanco) | H76: LIMIT01 | I76: 10.72.10.168 | J76: Usuario | K76: HP | L76: CND8322H3N | M76: Operativo | N76: 32 GB DDR4 | O76: 480 GB SSD | P76: Windows 11 Pro | Q76: MS Office 2007 HB | R76: 1
D77: Tecnologias de Información | E77: Tecnologias de Información | F77: PC | G77: LIMSWCAP1 | H77: LIMSWCAP1 | I77: (en blanco) | J77: Usuario | K77: Lenovo | L77: MZ00212Y | M77: Operativo | N77: 16 GB DDR4 | O77: 1000 GB SSD | P77: Windows 11 Pro | Q77: MS Office 365 HB | R77: 1
G78: LIMSWCAP3 | H78: LIMSWCAP3 | I78: (en blanco) | J78: Usuario | K78: Lenovo | L78: MZ00213H | M78: Operativo | N78: 16 GB DDR4 | O78: 1000 GB SSD | P78: Windows 11 Pro | Q78: MS Office 365 HB | R78: 1
G79: LIMH1SVRQR | H79: (en blanco) | I79: 174.16.0.228 | J79: Servidor | K79: Dell | L79: CZNDN22 | M79: Operativo | N79: 8 GB DDR3 | O79: 480 GB SSD | P79: Windows 11 Pro | Q79: (en blanco) | R79: 1
G80: LIMH1SVRCONAC | H80: (en blanco) | I80: 10.72.8.115 | J80: Servidor | K80: Dell | L80: D0DHN22 | M80: Operativo | N80: 12 GB DDR3 | O80: 480 GB SSD | P80: Windows 11 Pro | Q80: MS Office 2007 HB | R80: 1
G81: LIMH1SVRVI01 | H81: (en blanco) | I81: 10.72.8.212 | J81: Servidor | K81: Dell | L81: D0CSN22 | M81: Operativo | N81: 8 GB DDR3 | O81: 500 HDD | P81: Windows 10 Pro | Q81: (en blanco) | R81: 1
G82: LIMH1SVRINT | H82: (en blanco) | I82: 10.72.9.10 | J82: Servidor | K82: HP | L82: 1CZ53601JG | M82: Operativo | N82: 16 GB DDR5 | O82: 1 TB | P82: Windows 11 Pro | Q82: (en blanco) | R82: 1
G83: LIMH1SVRCAPS | H83: (en blanco) | I83: 10.72.8.56 | J83: Servidor | K83: Dell | L83: D0DRN22 | M83: Operativo | N83: 8 GB DDR3 | O83: 500 HDD | P83: Windows Server 2012 | Q83: (en blanco) | R83: 1
G84: limh1w10p003 | H84: limh1w10p003 | I84: 10.72.8.113 | J84: Servidor | K84: Dell | L84: D09QN22 | M84: Operativo | N84: 8 GB DDR3 | O84: 500 HDD | P84: Windows 10 Pro | Q84: MS Office 2007 HB | R84: 1
G85: LIMH1W7P07 | H85: LIMH1W7P07 | I85: 10.72.10.95 | J85: Servidor | K85: Dell | L85: D02RN22 | M85: Operativo | N85: 8 GB DDR3 | O85: 500 HDD | P85: Windows 10 Pro | Q85: MS Office 2007 HB | R85: 1
G86: LIMH1W7P89 | H86: (en blanco) | I86: 10.72.8.79 | J86: Servidor | K86: Dell | L86: D06RN22 | M86: Operativo | N86: 8 GB DDR3 | O86: 500 HDD | P86: Windows 7 Pro | Q86: (en blanco) | R86: 1
D87: YAMUNAQUE CASTILLO HECTOR ARTURO | E87: Gerente de Sistemas | F87: PC | G87: (en blanco) | H87: LIMH1W10P062 | I87: 10.72.10.17 | J87: Usuario | K87: Dell | L87: 355YN22 | M87: Operativo | N87: 8 GB DDR3 | O87: 480 GB SSD | P87: Windows 10 Pro | Q87: MS Office 2007 HB | R87: 1
H88: LIMH1W11IT01 | I88: (en blanco) | J88: Usuario | K88: HP | L88: MXL4321BFN | M88: Operativo | N88: 32 GB DDR3 | O88: 480 GB SSD + 500 GB HDD | P88: Windows 11 Pro | Q88: MS Office 2007 HB | R88: 1
B89: Total Tecnologias de Información | R89: 13
B90: Ventas y Marketing | C90: Marketing | D90: PALACIOS CULQUI THALIA YARIM | E90: Jefe de Marketing | F90: PC | G90: LIMH1SMPC012 | H90: LIMH1SMPC012 | I90: 10.72.10.120 | J90: Usuario | K90: Dell | L90: 630Q7V3 | M90: Operativo | N90: 32 GB DDR5 | O90: 1000 GB SSD | P90: Windows 11 Pro | Q90: MS Office 2007 HB | R90: 1
G91: LIMH1W11SM14 | H91: LIMH1W11SM14 | I91: 10.72.10.65 | J91: Usuario | K91: Dell | L91: D07SN22 | M91: Operativo | N91: 16 GB DDR3 | O91: 480 GB SSD | P91: Windows 11 Pro | Q91: MS Office 2007 HB | R91: 1
C92: Reservas | D92: GUERRERO BOLAÑOS SONIBEL SOFIA | E92: Agente de Reservas | F92: PC | G92: LIMVMRES02 | H92: (en blanco) | I92: 10.72.10.73 | J92: Usuario | K92: Dell | L92: GK4RN22 | M92: Operativo | N92: 16 GB DDR3 | O92: 480 GB SSD | P92: Windows 11 Pro | Q92: MS Office 2007 HB | R92: 1
D93: PECHING CHIONG KARINA JANET | E93: Gerenta de Reservas | F93: PC | G93: LIMVMGRES | H93: LIMH1SMPC019 | I93: 10.72.10.138 | J93: Usuario | K93: Dell | L93: D03QN22 | M93: Operativo | N93: 16 GB DDR3 | O93: 480 GB SSD | P93: Windows 11 Pro | Q93: MS Office 2007 HB | R93: 1
D94: ROQUE SILVA TANIA MARYORI | E94: Agente de Reservas | F94: PC | G94: LIMVMRES01 | H94: LIMH1SMPC020 | I94: 10.72.10.161 | J94: Usuario | K94: Dell | L94: 3540P22 | M94: Operativo | N94: 16 GB DDR3 | O94: 480 GB SSD | P94: Windows 11 Pro | Q94: MS Office 2007 HB | R94: 1
C95: Revenue | D95: BAGLIETTO ROJAS PIERO GIOVANI | E95: Jefe de Revenue | F95: PC | G95: LIMVMRES03 | H95: LIMH1SMPC022 | I95: 10.72.10.37 | J95: Usuario | K95: Dell | L95: CZPSN22 | M95: Operativo | N95: 16 GB DDR3 | O95: 480 GB SSD | P95: Windows 11 Pro | Q95: MS Office 2007 HB | R95: 1
D96: VILLACIS PAREDES MARIA DE LOS ANGELES | E96: Directora Regional de Revenue | F96: Laptop | G96: (en blanco) | H96: (en blanco) | I96: (en blanco) | J96: Usuario | K96: Lenovo | L96: (en blanco) | M96: Operativo | N96: 8 GB DDR4 | O96: 250 GB SSD | P96: Windows 11 Pro | Q96: MS Office 365 HB | R96: 1
C97: Ventas | D97: BAZAN CRUZ MARCIA ANGELA | E97: Gerente de Grupos y Eventos | F97: PC | G97: LIMVMGGE | H97: (en blanco) | I97: 10.72.10.123 | J97: Usuario | K97: Dell | L97: 357ZN22 | M97: Operativo | N97: 16 GB DDR3 | O97: 480 GB SSD | P97: Windows 11 Pro | Q97: MS Office 2007 HB | R97: 1
D98: BOHORQUEZ LEMOR ROSSANA ARMIDA | E98: Ejecutiva de Eventos | F98: PC | G98: LIMVMEC | H98: LIMSMVMEC | I98: (en blanco) | J98: Usuario | K98: Dell | L98: GJVRN22 | M98: Operativo | N98: 12 GB DDR3 | O98: 250 GB SSD | P98: Windows 11 Pro | Q98: MS Office 2007 HB | R98: 1
D99: CHAVEZ CRUZ MARITZA DINA | E99: Ejecutiva de Ventas | F99: PC | G99: LIMVMVEN01 | H99: LIMH1SMPC018 | I99: 10.72.10.33 | J99: Usuario | K99: Dell | L99: D0BFN22 | M99: Operativo | N99: 16 GB DDR3 | O99: 480 GB SSD | P99: Windows 11 Pro | Q99: MS Office 2007 HB | R99: 1
D100: CHUYES MENDOZA CLAUDIA ELIZABETH | E100: Ejecutiva de Eventos | F100: PC | G100: LIMSMVEN1 | H100: (en blanco) | I100: 10.72.10.111 | J100: Usuario | K100: Dell | L100: D0GQN22 | M100: Operativo | N100: 16 GB DDR3 | O100: 480 GB SSD | P100: Windows 11 Pro | Q100: MS Office 2007 HB | R100: 1
D101: DAVILA GUERRERO DIANA MARIELLA | E101: Ejecutiva de Ventas Senior | F101: PC | G101: (en blanco) | H101: LIMH1W11SM12 | I101: 10.72.10.74 | J101: Usuario | K101: Dell | L101: D0KDN22 | M101: Operativo | N101: 16 GB DDR3 | O101: 480 GB SSD | P101: Windows 11 Pro | Q101: MS Office 2007 HB | R101: 1
D102: HOZMA DIAZ NORMA CONSTANZA | E102: Directora de Ventas y Marketing | F102: Laptop | G102: LIMSMDVM | H102: (en blanco) | I102: (en blanco) | J102: Usuario | K102: Lenovo | L102: PW0MTPAJ | M102: Operativo | N102: 16 GB DDR5 | O102: 1000 GB SSD | P102: Windows 11 Pro | Q102: MS Office 365 HB | R102: 1
...

Sheet PC-Laptop
A3: Propiedad | B3: Unidad | C3: Centro de Costo | D3: Usuario | E3: Cargo | F3: Equipo | G3: Host | H3: Nuevo Nombre Host | I3: IP | J3: Tipo | K3: Marca | L3: S/N | M3: Estado | N3: Ram | O3: Almacenamiento | P3: Sistema Operativo | Q3: Office | R3: Cuenta Equipo
A4: HOTELERA COSTA DEL PACIFICO | B4: Alimentos y Bebidas | C4: Banquetes | D4: FALCON PAZ JULIAN MIGUEL ANGEL | E4: Supervisor Senior de A&B | F4: PC | G4: LIMH1W7P85 | H4: LIMAYBBQ01 | I4: 10.72.10.83 | J4: Usuario | K4: Dell | L4: D04FN22 | M4: Operativo | N4: 16 GB DDR3 | O4: 480 GB SSD | P4: Windows 11 Pro | Q4: MS Office 2007 HB | R4: 1
D5: GOMEZ COBEÑA PERCY BOLIVAR | E5: Capitán de Banquetes | F5: PC | G5: LIMH1W10P061 | H5: LIMAYBBQ02 | I5: 10.72.10.100 | J5: Usuario | K5: Dell | L5: 359ZN22 | M5: Operativo | N5: 16 GB DDR3 | O5: 480 GB SSD | P5: Windows 11 Pro | Q5: MS Office 2007 HB | R5: 1
C6: Gerencia A&B | D6: JARA RISCO GINO | E6: Director de Alimentos y Bebidas | F6: PC | G6: LIMH1W11P071 | H6: (en blanco) | I6: 10.72.10.41 | J6: Usuario | K6: Dell | L6: CZPRN22 | M6: Operativo | N6: 16 GB DDR3 | O6: 480 GB SSD | P6: Windows 11 Pro | Q6: MS Office 2007 HB | R6: 1
D7: MEDINA CASTILLO ALVARO GERARDO | E7: Sub Gerente de A&B | F7: PC | G7: (en blanco) | H7: LIMAYBSGER | I7: 10.72.10.103 | J7: Usuario | K7: Dell | L7: D00RN22 | M7: Operativo | N7: 16 GB DDR3 | O7: 480 GB SSD | P7: Windows 11 Pro | Q7: MS Office 365 HB | R7: 1
D8: RAMOS MAGAN HANNA GRACE | E8: Asistente Administrativa Jr. | F8: PC | G8: (en blanco) | H8: LIMFB02 | I8: 10.72.10.93 | J8: Usuario | K8: Dell | L8: GK6DN22 | M8: Operativo | N8: 16 GB DDR3 | O8: 480 GB SSD | P8: Windows 11 Pro | Q8: MS Office 2007 HB | R8: 1
D9: ROMAN ZUÑIGA ANNIE PAOLA | E9: Gerente de Alimentos y Bebidas | F9: PC | G9: (en blanco) | H9: LIMAYBGER | I9: 10.72.10.161 | J9: Usuario | K9: Dell | L9: 356YN22 | M9: Operativo | N9: 16 GB DDR3 | O9: 480 GB SSD | P9: Windows 11 Pro | Q9: MS Office 365 HB | R9: 1
C10: La Locanda | D10: HERRERA SOLIS CLAUDIA DANIELA FELICITA | E10: Restaurant Manager | F10: PC | G10: limh1w10p011 | H10: LIMAYBLL | I10: 10.72.10.72 | J10: Usuario | K10: Dell | L10: GK2HN22 | M10: Operativo | N10: 16 GB DDR3 | O10: 480 GB SSD | P10: Windows 11 Pro | Q10: MS Office 2007 HB | R10: 1
C11: Le Café | D11: ABANTO CARRANZA ANDREA SOFIA | E11: Consejero Gastronómico | F11: PC | G11: limh1w10p008 | H11: LIMAYBLC02 | I11: 10.72.10.63 | J11: Usuario | K11: Dell | L11: D07QN22 | M11: Operativo | N11: 16 GB DDR3 | O11: 480 GB SSD | P11: Windows 11 Pro | Q11: MS Office 2007 HB | R11: 1
D12: GUTIERREZ OYARDO ANGELA GEORGINA | E12: Consejero Gastronómico | F12: PC | G12: (en blanco) | H12: LIMAYBLC01 | I12: 10.72.10.118 | J12: Usuario | K12: Dell | L12: D1FDN22 | M12: Operativo | N12: 16 GB DDR3 | O12: 480 GB SSD | P12: Windows 11 Pro | Q12: MS Office 365 HB | R12: 1
C13: Lobby | D13: UGAZ OLIVARES PALOMA | E13: Supervisor Senior de A&B | F13: PC | G13: LIMH1W7P95 | H13: LIMAYBLB | I13: 10.72.10.44 | J13: Usuario | K13: Dell | L13: 352YN22 | M13: Operativo | N13: 16 GB DDR3 | O13: 480 GB SSD | P13: Windows 11 Pro | Q13: MS Office 2007 HB | R13: 1
C14: Piso Ejecutivo | D14: RODRIGUEZ ESPINOZA CYANE MILAGROS | E14: Consejero Gastronómico | F14: PC | G14: LIMH1W7P05 | H14: (en blanco) | I14: 10.72.10.164 | J14: Usuario | K14: HP | L14: MXL4321BFX | M14: Operativo | N14: 12 GB DDR3 | O14: 250 GB SSD | P14: Windows 11 Pro | Q14: MS Office 2007 HB | R14: 1
C15: Room Service | D15: HUAPAYA PEREZ LUIS ANGEL | E15: Supervisor de A&B | F15: PC | G15: limh1w10p005 | H15: LIMAYBRS | I15: 10.72.10.87 | J15: Usuario | K15: Dell | L15: GJVQN22 | M15: Operativo | N15: 16 GB DDR3 | O15: 480 GB SSD | P15: Windows 11 Pro | Q15: MS Office 2007 HB | R15: 1
C16: Steward | D16: VEGA ARRATEA JAVIER VICTOR | E16: Supervisor Jr. de Steward | F16: PC | G16: (en blanco) | H16: LIMFBSW | I16: 10.72.10.84 | J16: Usuario | K16: Dell | L16: GK2QN22 | M16: Operativo | N16: 16 GB DDR3 | O16: 480 GB SSD | P16: Windows 11 Pro | Q16: MS Office 2007 HB | R16: 1
B17: Total Alimentos y Bebidas | R17: 13
B18: Cocina | C18: Calidad | D18: ALEGRE ANGELES FERNANDA LUCIA | E18: Jefa de Aseguramiento de Calidad | F18: PC | G18: (en blanco) | H18: LIMCOC06 | I18: (en blanco) | J18: Usuario | K18: HP | L18: 9CG6262196 | M18: Operativo | N18: 8 GB DDR4 | O18: 250 GB SSD | P18: Windows 11 Pro | Q18: MS Office 365 HB | R18: 1
D19: CONDORI MORENO ELIZABETH CINTHIA | E19: Asistente de Calidad | F19: PC | G19: (en blanco) | H19: LIMCOC05 | I19: 10.72.10.138 | J19: Usuario | K19: Dell | L19: D01GN22 | M19: Operativo | N19: 16 GB DDR3 | O19: 480 GB SSD | P19: Windows 11 Pro | Q19: MS Office 365 HB | R19: 1
C20: Cocina | D20: LOPEZ PEREZ JUAN | E20: Chef Ejecutivo | F20: PC | G20: LIMH1W10FB010 | H20: LIMCHEF | I20: 10.72.10.106 | J20: Usuario | K20: Dell | L20: D09HN22 | M20: Operativo | N20: 16 GB DDR3 | O20: 480 GB SSD | P20: Windows 11 Pro | Q20: MS Office 365 HB | R20: 1
D21: TRONCOS REQUEJO MELANIE ALICIA | E21: Practicante Administrativo de Cocina | F21: PC | G21: (en blanco) | H21: LIMCOC02 | I21: 10.72.10.49 | J21: Usuario | K21: Dell | L21: D1HFN22 | M21: Operativo | N21: 16 GB DDR3 | O21: 480 GB SSD | P21: Windows 11 Pro | Q21: MS Office 365 HB | R21: 1
C22: Cocina La Locanda | D22: BAUTISTA CARDENAS MIGUEL ALEJANDRO | E22: Sub Chef | F22: PC | G22: LIMH1FBPC06 | H22: LIMCOC04 | I22: 10.72.10.157 | J22: Usuario | K22: Dell | L22: CZYQN22 | M22: Operativo | N22: 16 GB DDR3 | O22: 480 GB SSD | P22: Windows 11 Pro | Q22: MS Office 2007 HB | R22: 1
G23: LIMH1W11FB12 | H23: LIMCOC03 | I23: 10.72.10.144 | J23: Usuario | K23: Dell | L23: CZNQN22 | M23: Operativo | N23: 16 GB DDR3 | O23: 250 GB SSD | P23: Windows 11 Pro | Q23: MS Office 2007 HB | R23: 1
C24: Pastelería | D24: CHAVEZ LING SUSANA BETSABE | E24: Supervisor Pasteleria / Panadería | F24: PC | G24: LIMH1W11FB12 | H24: LIMCOC01 | I24: 10.72.10.99 | J24: Usuario | K24: Dell | L24: 3510P22 | M24: Operativo | N24: 12 GB DDR3 | O24: 480 GB SSD | P24: Windows 11 Pro | Q24: MS Office 365 HB | R24: 1
B25: Total Cocina | R25: 7
B26: Compras | C26: Compras | D26: CASTRO MORA NELLY YOLANDA | E26: Gerente de Compras Regional | F26: Laptop | G26: (en blanco) | H26: LIMPU01 | I26: 10.72.10.101 | J26: Usuario | K26: Lenovo | L26: PF3KWH96 | M26: Operativo | N26: 16 GB DDR4 | O26: 1000 GB SSD | P26: Windows 11 Pro | Q26: MS Office 365 HB | R26: 1
D27: OBARA AVI JUAN FERNANDO | E27: Gerente de Compras | F27: PC | G27: LIMH1PUPC001 | H27: LIMCOMPGC | I27: 10.72.10.51 | J27: Usuario | K27: Dell | L27: 35CXN22 | M27: Operativo | N27: 16 GB DDR3 | O27: 480 GB SSD | P27: Windows 11 Pro | Q27: MS Office 2007 HB | R27: 1
B28: Total Compras | R28: 2
B29: Contraloría | C29: Auditoría de Ingresos | D29: MOTA CASTRO JIM EDUARDO | E29: Auditor de Ingresos | F29: PC | G29: LIMH1W7P65 | H29: LIMCNTAI | I29: 10.72.10.138 | J29: Usuario | K29: Dell | L29: D09RN22 | M29: Operativo | N29: 16 GB DDR3 | O29: 480 GB SSD | P29: Windows 11 Pro | Q29: MS Office 2007 HB | R29: 1
G30: (en blanco) | H30: LIMCNTAI02 | I30: 10.72.10.139 | J30: Usuario | K30: Dell | L30: 3550P22 | M30: Operativo | N30: 16 GB DDR3 | O30: 480 GB SSD | P30: Windows 11 Pro | Q30: MS Office 2007 HB | R30: 1
C31: Bodegas | D31: CARPIO PONCE GARY ANDRES | E31: Bodeguero | F31: PC | G31: LIMH1W10P100 | H31: LIMCNTBG01 | I31: 10.72.10.81 | J31: Usuario | K31: Dell | L31: 351YN22 | M31: Operativo | N31: 16 GB DDR3 | O31: 480 GB SSD | P31: Windows 11 Pro | Q31: MS Office 2007 HB | R31: 1
C32: Contabilidad | D32: CARHUANCOTA CHAVEZ ANDRES ALBERTO | E32: Asistente Senior de Contabilidad | F32: PC | G32: LIMH1W7P101 | H32: LIMCNTCONT3 | I32: 10.72.10.133 | J32: Usuario | K32: Dell | L32: D0HRN22 | M32: Operativo | N32: 16 GB DDR3 | O32: 480 GB SSD | P32: Windows 11 Pro | Q32: MS Office 2007 HB | R32: 1
G33: (en blanco) | H33: LIMCNTCONT4 | I33: (en blanco) | J33: Usuario | K33: HP | L33: MXL5283YYX | M33: Operativo | N33: 16 GB DDR5 | O33: 1000 GB SSD | P33: Windows 11 Pro | Q33: MS Office 365 HB | R33: 1
D34: FLORES RAMIREZ PERCY FERNANDO | E34: Asistente de Cuentas por Cobrar | F34: PC | G34: (en blanco) | H34: LIMH1W11AC02 | I34: 10.72.10.94 | J34: Usuario | K34: Lenovo | L34: (en blanco) | M34: Operativo | N34: 16 GB DDR5 | O34: 1000 GB SSD | P34: Windows 11 Pro | Q34: MS Office 365 HB | R34: 1
D35: HUAYAMA INGAROCA MERCEDES GRACIELA | E35: Practicante de Contabilidad | F35: PC | G35: (en blanco) | H35: LIMCNTCONT7 | I35: 10.72.10.125 | J35: Usuario | K35: Dell | L35: GJWSN22 | M35: Operativo | N35: 16 GB DDR3 | O35: 480 GB SSD | P35: Windows 11 Pro | Q35: MS Office 2007 HB | R35: 1
D36: MILLA GOMEZ ANJALI ABIGAIL | E36: Practicante de Contabilidad | F36: PC | G36: (en blanco) | H36: LIMCNTCONT8 | I36: 10.72.10.129 | J36: Usuario | K36: Dell | L36: CZZFN22 | M36: Operativo | N36: 16 GB DDR3 | O36: 480 GB SSD | P36: Windows 11 Pro | Q36: (en blanco) | R36: 1
D37: ORELLANA CHIPANA MARTIN SANTIAGO | E37: Practicante de Contabilidad | F37: PC | G37: LIMH1W7P57 | H37: LIMCNTCONT6 | I37: 10.72.10.110 | J37: Usuario | K37: Dell | L37: D05FN22 | M37: Operativo | N37: 16 GB DDR3 | O37: 480 GB SSD | P37: Windows 11 Pro | Q37: MS Office 2007 HB | R37: 1
D38: ORELLANA GODOY MELCHORA OLINDA | E38: Contador | F38: PC | G38: LIMH1W10PC0011 | H38: (en blanco) | I38: 10.72.10.73 | J38: Usuario | K38: Dell | L38: 8RLT5X3 | M38: Operativo | N38: 32 GB DDR5 | O38: 500 GB SSD | P38: Windows 11 Pro | Q38: MS Office 2007 HB | R38: 1
D39: SEGOVIA CRISPIN XAVIER ALONSO | E39: Asistente de Contabilidad | F39: PC | G39: LIMH1W10PC005 | H39: (en blanco) | I39: 10.72.10.90 | J39: Usuario | K39: Dell | L39: 7HHT5X3 | M39: Operativo | N39: 32 GB DDR5 | O39: 500 GB SSD | P39: Windows 11 Pro | Q39: MS Office 2007 HB | R39: 1
D40: SISTEMAS DE ACTIVOS FIJOS | E40: Sistema de Activos Fijos | F40: PC | G40: LIMH1GMPC02 | H40: LIMH1GMPC02 | I40: 10.72.10.70 | J40: Usuario | K40: Dell | L40: 353YN22 | M40: Operativo | N40: 8 GB DDR3 | O40: 250 GB SSD | P40: Windows 10 Pro | Q40: MS Office 2007 HB | R40: 1
D41: ALVARADO CHAVARRY JIMMY GERARDO | E41: Sub Contralor | F41: PC | G41: (en blanco) | H41: LIMCNTSC | I41: 10.72.10.177 | J41: Usuario | K41: Lenovo | L41: YLT1642S | M41: Operativo | N41: 16 GB DDR5 | O41: 480 GB SSD | P41: Windows 11 Pro | Q41: MS Office 365 HB | R41: 1
D42: TISNADO MEGO LEIDER ALFONZO | E42: Encargado de Costos | F42: PC | G42: LIMH1ACPC003 | H42: LIMCNTCONT5 | I42: 10.72.10.53 | J42: Usuario | K42: Dell | L42: D0HFN22 | M42: Operativo | N42: 16 GB DDR3 | O42: 480 GB SSD | P42: Windows 11 Pro | Q42: MS Office 365 HB | R42: 1
C43: Contraloría | D43: PINEDA LOPEZ GLADYS DIANA | E43: Contralora Regional | F43: Laptop | G43: (en blanco) | H43: (en blanco) | I43: (en blanco) | J43: Usuario | K43: Lenovo | L43: (en blanco) | M43: Operativo | N43: 8 GB DDR4 | O43: 250 GB SSD | P43: Windows 11 Pro | Q43: MS Office 365 HB | R43: 1
B44: Total Contraloría | R44: 15
B45: Control y Monitoreo | C45: Control y Monitoreo | D45: MENDIETA SOLANO WILLIAM JESUS | E45: Gerente de Control y Monitero | F45: PC | G45: LIMH1W11P036 | H45: (en blanco) | I45: (en blanco) | J45: Usuario | K45: Dell | L45: D02QN22 | M45: Operativo | N45: 16 GB DDR3 | O45: 480 GB SSD | P45: Windows 11 Pro | Q45: MS Office 2007 HB | R45: 1
D46: Puerta 5 | E46: Empleado Puesto de Control | F46: PC | G46: (en blanco) | H46: LIMCMP5 | I46: 10.72.10.92 | J46: Usuario | K46: Dell | L46: CZVGN22 | M46: Operativo | N46: 8 GB DDR3 | O46: 250 GB SSD | P46: Windows 11 Pro | Q46: MS Office 2007 HB | R46: 1
D47: Control y Monitoreo | E47: Empleado Puesto de Control | F47: PC | G47: (en blanco) | H47: LIMCMSCM01 | I47: 10.72.10.109 | J47: Usuario | K47: Dell | L47: D1BSN22 | M47: Operativo | N47: 16 GB DDR3 | O47: 480 GB SSD | P47: Windows 11 Pro | Q47: (en blanco) | R47: 1
C48: Seguridad y Salud en el Trabajo | D48: MARQUEZ GODOY LUIS ANGEL | E48: Analista de Seguridad y Salud en el Trabajo | F48: PC | G48: LIMH1W10CM02 | H48: LIMCMASST | I48: 10.72.10.93 | J48: Usuario | K48: Dell | L48: D00TN22 | M48: Operativo | N48: 12 GB DDR3 | O48: 480 GB SSD | P48: Windows 11 Pro | Q48: MS Office 365 HB | R48: 1
B49: Total Control y Monitoreo | R49: 4
B50: División de Habitaciones (Operaciones) | C50: Gym & Spa | D50: MOGROVEJO BRACESCO ANDREA CAROLINA | E50: Supervisor de Gimnasio | F50: PC | G50: LIMH1W10GYM02 | H50: LIMDHGYM01 | I50: 10.9.10.38 | J50: Usuario | K50: Dell | L50: GK5FN22 | M50: Operativo | N50: 16 GB DDR3 | O50: 480 GB SSD | P50: Windows 11 Pro | Q50: MS Office 365 HB | R50: 1
G51: LIMH1W11PMS100 | H51: (en blanco) | I51: 10.72.10.108 | J51: Usuario | K51: Dell | L51: 351XN22 | M51: Operativo | N51: 16 GB DDR3 | O51: 480 GB SSD | P51: Windows 11 Pro | Q51: MS Office 365 HB | R51: 1
C52: Housekeeping | D52: CARDENAS ALCAZABA PAOLA RAQUEL | E52: Supervisor Jr. De Housekeeping | F52: PC | G52: limh1w10p013 | H52: LIMDHHK01 | I52: 10.72.10.136 | J52: Usuario | K52: Dell | L52: D1LDN22 | M52: Operativo | N52: 16 GB DDR3 | O52: 480 GB SSD | P52: Windows 11 Pro | Q52: MS Office 2007 HB | R52: 1
D53: LLACSAHUANGA VALENCIA EDITH | E53: Jefe de Housekeeping | F53: PC | G53: limh1w10p054 | H53: LIMDHJHK | I53: 10.72.10.86 | J53: Usuario | K53: Dell | L53: D05SN22 | M53: Operativo | N53: 16 GB DDR3 | O53: 480 GB SSD | P53: Windows 11 Pro | Q53: MS Office 365 HB | R53: 1
D54: SICHA PEREZ IRIS GIOVANNA | E54: Supervisor Jr. De Housekeeping | F54: PC | G54: LIMH1W11HK01 | H54: LIMH1W11HK01 | I54: 10.72.10.148 | J54: Usuario | K54: Dell | L54: GJZRN22 | M54: Operativo | N54: 16 GB DDR3 | O54: 250 GB SSD | P54: Windows 11 Pro | Q54: MS Office 2007 HB | R54: 1
C55: Lavandería | D55: CERRON ACUÑA JUAN MIGUEL | E55: Supervisor Jr. De Lavanderia | F55: PC | G55: LIMH1W11HK02 | H55: LIMH1W11HK02 | I55: 10.72.10.121 | J55: Usuario | K55: Dell | L55: GJHGN22 | M55: Operativo | N55: 16 GB DDR3 | O55: 250 GB SSD | P55: Windows 11 Pro | Q55: MS Office 2007 HB | R55: 1
D56: VALDERRAMA ALVAREZ PABLO CESAR | E56: Supervisor Senior de Lavanderia | F56: PC | G56: limh1w10p047 | H56: LIMDHSLV | I56: 10.72.10.77 | J56: Usuario | K56: Dell | L56: D0DDN22 | M56: Operativo | N56: 16 GB DDR3 | O56: 480 GB SSD | P56: Windows 11 Pro | Q56: MS Office 2007 HB | R56: 1
C57: Limpieza | D57: MARTINEZ SOTELO LUIS ENRIQUE | E57: Supervisor Senior de Limpieza | F57: PC | G57: limh1w10p017 | H57: LIMDHLIM | I57: 10.72.10.159 | J57: Usuario | K57: Dell | L57: GJXSN22 | M57: Operativo | N57: 16 GB DDR3 | O57: 480 GB SSD | P57: Windows 11 Pro | Q57: MS Office 2007 HB | R57: 1
C58: Recepción | D58: CARBAJAL BRAVO ROMMEL MARTIN | E58: Gerente de Turno | F58: PC | G58: limh1w10p009 | H58: LIMRD01 | I58: 10.72.10.135 | J58: Usuario | K58: Dell | L58: 35DWN22 | M58: Operativo | N58: 16 GB DDR3 | O58: 480 GB SSD | P58: Windows 11 Pro | Q58: MS Office 2007 HB | R58: 1
D59: CARRILLO SILVA ENRIQUE RAFAEL | E59: Botones | F59: PC | G59: LIMH1W10PC0010 | H59: LIMDHBOT | I59: 10.72.10.67 | J59: Usuario | K59: Dell | L59: 34ZZN22 | M59: Operativo | N59: 16 GB DDR3 | O59: 480 GB SSD | P59: Windows 11 Pro | Q59: MS Office 2007 HB | R59: 1
D60: Front Desk 1 | E60: Recepcionista | F60: PC | G60: (en blanco) | H60: LIMFD01 | I60: 10.72.10.34 | J60: Usuario | K60: Lenovo | L60: YLT1643J | M60: Operativo | N60: 32 GB DDR5 | O60: 1000 GB SSD | P60: Windows 11 Pro | Q60: MS Office 2007 HB | R60: 1
D61: Front Desk 2 | E61: Recepcionista | F61: PC | G61: (en blanco) | H61: LIMFD02 | I61: 10.72.10.146 | J61: Usuario | K61: Lenovo | L61: YLT16443 | M61: Operativo | N61: 32 GB DDR5 | O61: 1000 GB SSD | P61: Windows 11 Pro | Q61: MS Office 2007 HB | R61: 1
D62: Front Desk 3 | E62: Recepcionista | F62: PC | G62: LIMH1W10P101 | H62: (en blanco) | I62: 10.72.10.50 | J62: Usuario | K62: Dell | L62: B8WS5X3 | M62: Operativo | N62: 32 GB DDR5 | O62: 500 GB SSD | P62: Windows 11 Pro | Q62: MS Office 2007 HB | R62: 1
D63: Front Desk 4 | E63: Recepcionista | F63: PC | G63: LIMH1W7P34 | H63: LIMFD04 | I63: 10.72.10.165 | J63: Usuario | K63: Lenovo | L63: YLT16FYF | M63: Operativo | N63: 32 GB DDR5 | O63: 1000 GB SSD | P63: Windows 11 Pro | Q63: MS Office 2007 HB | R63: 1
D64: HUAMAN NUÑUBERO ROSARIO NICOLE | E64: Recepcionista Back Office | F64: PC | G64: (en blanco) | H64: LIMDHREC | I64: 10.72.10.141 | J64: Usuario | K64: HP | L64: MXL3460T6K | M64: Operativo | N64: 16 GB DDR3 | O64: 480 GB SSD | P64: Windows 11 Pro | Q64: MS Office 2007 HB | R64: 1
D65: LUNA MARIÑO FANNY ISABEL | E65: Jefe de Recepción | F65: PC | G65: LIMH1W11FO03 | H65: (en blanco) | I65: 10.72.10.82 | J65: Usuario | K65: Dell | L65: D02FN22 | M65: Operativo | N65: 16 GB DDR3 | O65: 480 GB SSD | P65: Windows 11 Pro | Q65: MS Office 2007 HB | R65: 1
D66: NOVOA ZACIGA MEY-LIN | E66: Recepcionista | F66: PC | G66: (en blanco) | H66: LIMRD02 | I66: 10.72.10.112 | J66: Usuario | K66: Dell | L66: GK0GN22 | M66: Operativo | N66: 16 GB DDR3 | O66: 480 GB SSD | P66: Windows 11 Pro | Q66: MS Office 2007 HB | R66: 1
B67: Total División de Habitaciones (Operaciones) | R67: 17
B68: Gerencia General | C68: Gerencia General | D68: GAMBONI KOIFMAN DE TENORIO SANCHO DAVI C | E68: Asistente de Gerencia General | F68: PC | G68: LIMH1W10PC004 | H68: LIMH1W10PC004 | I68: 10.72.10.145 | J68: Usuario | K68: HP | L68: MXL4321BFP | M68: Operativo | N68: 32 GB DDR3 | O68: 500 GB SSD | P68: Windows 11 Pro | Q68: MS Office 2007 HB | R68: 1
B69: Total Gerencia General | R69: 1
B70: Mantenimiento | C70: Mantenimiento | D70: GAMARRA MARCELO TONY EISNTEIN | E70: Técnico Electricista | F70: PC | G70: (en blanco) | H70: (en blanco) | I70: (en blanco) | J70: Usuario | K70: HP | L70: MXL446116X | M70: Operativo | N70: 8 GB DDR3 | O70: 500 GB HDD | P70: Windows 7 Pro | Q70: MS Office 2007 HB | R70: 1
D71: LLANCA ZUÑIGA JIMMY WIELER | E71: Técnico de Mantenimiento | F71: PC | G71: (en blanco) | H71: (en blanco) | I71: 10.72.10.80 | J71: Usuario | K71: Dell | L71: D1DDN22 | M71: Operativo | N71: 16 GB DDR3 | O71: 480 GB SSD | P71: Windows 11 Pro | Q71: MS Office 2007 HB | R71: 1
D72: NOLASCO CUNYARACHE GABRIELA FLOR | E72: Practicante de Mantenimiento | F72: PC | G72: (en blanco) | H72: LIMMANT01 | I72: 10.72.10.130 | J72: Usuario | K72: Dell | L72: GJWQN22 | M72: Operativo | N72: 12 GB DDR3 | O72: 480 GB SSD | P72: Windows 11 Pro | Q72: MS Office 365 HB | R72: 1
D73: VARGAS CACHIQUE ORLANDO FLORENCIO | E73: Gerente de Mantenimiento | F73: PC | G73: (en blanco) | H73: LIMMANTGER | I73: 10.72.10.131 | J73: Usuario | K73: Dell | L73: GJPFN22 | M73: Operativo | N73: 16 GB DDR3 | O73: 480 GB SSD | P73: Windows 11 Pro | Q73: MS Office 2007 HB | R73: 1
D74: MAMANI SEVILLANO ANGIE | E74: Asistente de Mantenimiento | F74: PC | G74: LIMMANT02 | H74: LIMMANT02 | I74: 10.72.10.152 | J74: Usuario | K74: Dell | L74: GJQGN22 | M74: Operativo | N74: 12 GB DDR3 | O74: 480 GB SSD | P74: Windows 11 Pro | Q74: MS Office 365 HB | R74: 1
B75: Total Mantenimiento | R75: 5
B76: Personas y Cultura | C76: Personas y Cultura | D76: BRENDA STEFANY VILLAREAL MACHADO | E76: Trabajadora Social | F76: PC | G76: (en blanco) | H76: LIMPCAS | I76: 10.72.10.77 | J76: Usuario | K76: Dell | L76: 60YY282 | M76: Operativo | N76: 16 GB DDR3 | O76: 480 GB SSD | P76: Windows 11 Pro | Q76: MS Office 365 HB | R76: 1
D77: CARBAJAL SANDOVAL KARIN GEORGHET | E77: Enfermera | F77: PC | G77: (en blanco) | H77: LIMHR6 | I77: 10.72.10.91 | J77: Usuario | K77: Dell | L77: CZPQN22 | M77: Operativo | N77: 16 GB DDR3 | O77: 480 GB SSD | P77: Windows 11 Pro | Q77: MS Office 365 HB | R77: 1
D78: CARRERA PALACIOS ROSALIA RENE | E78: Asistente de Personas y Cultura | F78: PC | G78: LIMH1W10P081 | H78: LIMPCAPC | I78: 10.72.10.71 | J78: Usuario | K78: HP | L78: MXL3460T3Y | M78: Operativo | N78: 20 GB DDR3 | O78: 480 GB SSD | P78: Windows 11 Pro | Q78: MS Office 365 HB | R78: 1
D79: COBOS GRANDA GLADYS EDITH | E79: Gerente de Capacitación y Desarrollo | F79: PC | G79: limh1w10p030 | H79: LIMPCGCD | I79: 10.72.10.76 | J79: Usuario | K79: Dell | L79: CZYRN22 | M79: Operativo | N79: 16 GB DDR3 | O79: 480 GB SSD | P79: Windows 11 Pro | Q79: MS Office 365 HB | R79: 1
D80: TEJADA RIVEROS DIEGO JOEL | E80: Gerente de Personas y Cultura | F80: PC | G80: LIMH1W10P102 | H80: LIMH1W10P102 | I80: 10.72.10.25 | J80: Usuario | K80: Dell | L80: H4WS5X3 | M80: Operativo | N80: 32 GB DDR5 | O80: 500 GB SSD + 500 GB HDD | P80: Windows 11 Pro | Q80: MS Office 365 HB | R80: 1
B81: Total Personas y Cultura | R81: 5
B82: Tecnologias de Información | C82: Tecnologias de Información | D82: SALINAS TORRES NOE | E82: Analista de Sistemas | F82: Laptop | G82: LIMIT01 | H82: (en blanco) | I82: 10.72.10.168 | J82: Usuario | K82: HP | L82: CND8322H3N | M82: Operativo | N82: 32 GB DDR4 | O82: 480 GB SSD | P82: Windows 11 Pro | Q82: MS Office 2007 HB | R82: 1
D83: Tecnologias de Información | E83: Tecnologias de Información | F83: PC | G83: limh1w10p003 | H83: limh1w10p003 | I83: 10.72.8.113 | J83: Servidor | K83: Dell | L83: D09QN22 | M83: Operativo | N83: 8 GB DDR3 | O83: 500 GB HDD | P83: Windows 10 Pro | Q83: MS Office 2007 HB | R83: 1
G84: LIMH1W7P07 | H84: LIMH1W7P07 | I84: 10.72.10.95 | J84: Servidor | K84: Dell | L84: D02RN22 | M84: Operativo | N84: 8 GB DDR3 | O84: 500 GB HDD | P84: Windows 10 Pro | Q84: MS Office 2007 HB | R84: 1
G85: (en blanco) | H85: LIMH1SVRQR | I85: 174.16.0.228 | J85: Servidor | K85: Dell | L85: CZNDN22 | M85: Operativo | N85: 8 GB DDR3 | O85: 480 GB SSD | P85: Windows 11 Pro | Q85: (en blanco) | R85: 1
H86: LIMH1SVRCONAC | I86: 10.72.8.115 | J86: Servidor | K86: Dell | L86: D0DHN22 | M86: Operativo | N86: 12 GB DDR3 | O86: 480 GB SSD | P86: Windows 11 Pro | Q86: MS Office 2007 HB | R86: 1
H87: LIMH1SVRVI01 | I87: 10.72.8.212 | J87: Servidor | K87: Dell | L87: D0CSN22 | M87: Operativo | N87: 8 GB DDR3 | O87: 500 GB HDD | P87: Windows 10 Pro | Q87: (en blanco) | R87: 1
H88: LIMH1SVRINT | I88: 10.72.9.10 | J88: Servidor | K88: HP | L88: 1CZ53601JG | M88: Operativo | N88: 16 GB DDR5 | O88: 1 TB | P88: Windows 11 Pro | Q88: (en blanco) | R88: 1
H89: LIMH1SVRCAPS | I89: 10.72.8.56 | J89: Servidor | K89: Dell | L89: D0DRN22 | M89: Operativo | N89: 8 GB DDR3 | O89: 500 GB HDD | P89: Windows Server 2012 | Q89: (en blanco) | R89: 1
H90: LIMH1W7P89 | I90: 10.72.8.79 | J90: Servidor | K90: Dell | L90: D06RN22 | M90: Operativo | N90: 8 GB DDR3 | O90: 500 GB HDD | P90: Windows 7 Pro | Q90: (en blanco) | R90: 1
G91: LIMSWCAP1 | H91: LIMSWCAP1 | I91: (en blanco) | J91: Usuario | K91: Lenovo | L91: MZ00212Y | M91: Operativo | N91: 16 GB DDR4 | O91: 1000 GB SSD | P91: Windows 11 Pro | Q91: MS Office 365 HB | R91: 1
G92: LIMSWCAP3 | H92: LIMSWCAP3 | I92: (en blanco) | J92: Usuario | K92: Lenovo | L92: MZ00213H | M92: Operativo | N92: 16 GB DDR4 | O92: 1000 GB SSD | P92: Windows 11 Pro | Q92: MS Office 365 HB | R92: 1
D93: YAMUNAQUE CASTILLO HECTOR ARTURO | E93: Gerente de Sistemas | F93: PC | G93: LIMH1W10P062 | H93: (en blanco) | I93: 10.72.10.17 | J93: Usuario | K93: Dell | L93: 355YN22 | M93: Operativo | N93: 8 GB DDR3 | O93: 480 GB SSD | P93: Windows 10 Pro | Q93: MS Office 2007 HB | R93: 1
G94: LIMH1W11IT01 | H94: (en blanco) | I94: (en blanco) | J94: Usuario | K94: HP | L94: MXL4321BFN | M94: Operativo | N94: 32 GB DDR3 | O94: 480 GB SSD + 500 GB HDD | P94: Windows 11 Pro | Q94: MS Office 2007 HB | R94: 1
B95: Total Tecnologias de Información | R95: 13
B96: Ventas y Marketing | C96: Marketing | D96: PALACIOS CULQUI THALIA YARIM | E96: Jefe de Marketing | F96: PC | G96: LIMH1SMPC012 | H96: LIMH1SMPC012 | I96: 10.72.10.120 | J96: Usuario | K96: Dell | L96: 630Q7V3 | M96: Operativo | N96: 32 GB DDR5 | O96: 1000 GB SSD | P96: Windows 11 Pro | Q96: MS Office 2007 HB | R96: 1
G97: LIMH1W11SM14 | H97: LIMH1W11SM14 | I97: 10.72.10.65 | J97: Usuario | K97: Dell | L97: D07SN22 | M97: Operativo | N97: 16 GB DDR3 | O97: 480 GB SSD | P97: Windows 11 Pro | Q97: MS Office 2007 HB | R97: 1
C98: Reservas | D98: GUERRERO BOLAÑOS SONIBEL SOFIA | E98: Agente de Reservas | F98: PC | G98: (en blanco) | H98: LIMVMRES02 | I98: 10.72.10.73 | J98: Usuario | K98: Dell | L98: GK4RN22 | M98: Operativo | N98: 16 GB DDR3 | O98: 480 GB SSD | P98: Windows 11 Pro | Q98: MS Office 2007 HB | R98: 1
D99: PECHING CHIONG KARINA JANET | E99: Gerenta de Reservas | F99: PC | G99: LIMH1SMPC019 | H99: LIMVMGRES | I99: 10.72.10.138 | J99: Usuario | K99: Dell | L99: D03QN22 | M99: Operativo | N99: 16 GB DDR3 | O99: 480 GB SSD | P99: Windows 11 Pro | Q99: MS Office 2007 HB | R99: 1
D100: ROQUE SILVA TANIA MARYORI | E100: Agente de Reservas | F100: PC | G100: LIMH1SMPC020 | H100: LIMVMRES01 | I100: 10.72.10.161 | J100: Usuario | K100: Dell | L100: 3540P22 | M100: Operativo | N100: 16 GB DDR3 | O100: 480 GB SSD | P100: Windows 11 Pro | Q100: MS Office 2007 HB | R100: 1
C101: Revenue | D101: BAGLIETTO ROJAS PIERO GIOVANI | E101: Jefe de Revenue | F101: PC | G101: LIMH1SMPC022 | H101: LIMVMRES03 | I101: 10.72.10.37 | J101: Usuario | K101: Dell | L101: CZPSN22 | M101: Operativo | N101: 16 GB DDR3 | O101: 480 GB SSD | P101: Windows 11 Pro | Q101: MS Office 2007 HB | R101: 1
D102: VILLACIS PAREDES MARIA DE LOS ANGELES | E102: Directora Regional de Revenue | F102: Laptop | G102: (en blanco) | H102: (en blanco) | I102: (en blanco) | J102: Usuario | K102: Lenovo | L102: (en blanco) | M102: Operativo | N102: 8 GB DDR4 | O102: 250 GB SSD | P102: Windows 11 Pro | Q102: MS Office 365 HB | R102: 1
...

Sheet ImpresoasDinamica
A3: Propiedad | B3: Equipo | C3: Marca | D3: Modelo | E3: S/N | F3: IP | G3: Observación | H3: Cantidad Impresoras
A4: Prov. DATACONT | B4: Impresora | C4: Canon | D4: iR1730i | E4: QFX06245 | F4: 10.72.8.215 | G4: 2do Piso - Oficina Auditor de Ingresos | H4: 1
D5: iR1643i II | E5: 35E33608 | F5: 10.72.8.211 | G5: 1er Piso - Front Desk - Recepción | H5: 1
E6: 35E33607 | F6: 10.72.8.153 | G6: 1er Piso - Front Desk - Recepción | H6: 1
C7: Epson | D7: WF-C5790 Series | E7: X3B7002433 | F7: 10.72.8.191 | G7: 2do Piso - Oficina Banquetes | H7: 1
E8: X3B7003659 | F8: 10.72.8.197 | G8: 3er Piso - Reservas | H8: 1
E9: X3B7003660 | F9: 10.72.8.204 | G9: 1er Piso - Room Service | H9: 1
E10: X3B7003661 | F10: 10.72.8.132 | G10: 1er Sotano - Steward - Limpieza | H10: 1
E11: X3B7003671 | F11: 10.72.8.208 | G11: 1er Piso - Caja Lobby Bar | H11: 1
E12: X3B7003703 | F12: 10.9.10.153 | G12: 1er Piso Gym | H12: 1
E13: X3B7003711 | F13: 10.72.8.205 | G13: 1er Piso - Recepción - Back Office | H13: 1
E14: X3B7003739 | F14: 10.72.10.43 | G14: 1er Piso Compras | H14: 1
E15: X3B7003876 | F15: 10.72.8.220 | G15: 1er Piso - Oficina AyB | H15: 1
D16: WF-C5890 Series | E16: XBJZ017266 | F16: 10.72.8.229 | G16: 1er Sotano - Housekeeping | H16: 1
E17: XBJZ017602 | F17: 10.72.8.206 | G17: 1er Piso - Bodega | H17: 1
E18: XBJZ017603 | F18: 10.72.8.196 | G18: 1er Piso - Conserge | H18: 1
E19: XBJZ021745 | F19: 10.72.8.219 | G19: 1er Piso - Oficina Chef | H19: 1
E20: XBJZ021772 | F20: 10.72.8.151 | G20: 3er Piso - Gerencia General | H20: 1
E21: XBJZ027512 | F21: 10.72.8.210 | G21: 3er Piso - Ventas | H21: 1
C22: Sharp | D22: MX-3070V | E22: 3500930400 | F22: 10.72.8.200 | G22: 1er Sotano - RRHH - Sistemas | H22: 1
D23: MX-M3070 | E23: 9502370Y00 | F23: 10.72.8.207 | G23: 3er Piso - Contabilidad | H23: 1
E24: 15064216 | F24: 10.72.8.203 | G24: 2do Piso - Seguridad | H24: 1
A25: Total general | H25: 21

Sheet Micros
A3: Propiedad | B3: Unidad | C3: Centro de Costo | D3: Cargo | E3: Usuario | F3: Equipo | G3: Marca | H3: Modelo | I3: S/N | J3: IP | K3: Estado | L3: Cuenta de Equipo
A4: HOTELERA COSTA DEL PACIFICO | B4: Alimentos y Bebidas | C4: Banquetes | D4: Banquetes | E4: Banquetes | F4: Micros | G4: Oracle | H4: Workstation 8 | I4: 5365ECB05002311 | J4: 10.72.8.246 | K4: Operativo | L4: 1
C5: La Fondue | D5: Caja La Fondue | E5: Caja La Fondue | F5: Micros | G5: Oracle | H5: Workstation 8 | I5: 5365ECB05002309 | J5: 10.72.8.247 | K5: Operativo | L5: 1
C6: Room Service | D6: Caja Room Service | E6: Caja Room Service | F6: Micros | G6: Oracle | H6: Workstation 8 | I6: 5365ECB05002312 | J6: 10.72.8.238 | K6: Operativo | L6: 1
C7: Le Café | D7: Caja Le Café | E7: Caja Le Café | F7: Micros | G7: Oracle | H7: Workstation 8 | I7: 5365ECB05002324 | J7: 10.72.8.245 | K7: Operativo | L7: 1
C8: Lobby Bar | D8: Caja Lobby Bar | E8: Caja Lobby Bar | F8: Micros | G8: Oracle | H8: Workstation 8 | I8: 5365ECB05002273 | J8: 10.72.8.237 | K8: Operativo | L8: 1
C9: La Locanda | D9: Caja La Locanda | E9: Caja La Locanda | F9: Micros | G9: Oracle | H9: Workstation 8 | I9: 5365ECB05002282 | J9: 10.72.8.236 | K9: Operativo | L9: 1
B10: Tecnologias de Información | C10: Tecnologias de Información | D10: Tecnologias de Información | E10: Tecnologias de Información | F10: Micros | G10: Oracle | H10: Workstation 8 | I10: 5365ECB05002274 | J10: (en blanco) | K10: Custodia - Operativo | L10: 1
I11: 5365ECB05002291 | J11: (en blanco) | K11: Custodia - Operativo | L11: 1
A12: Total general | L12: 8

Sheet Datos
B4: Equipo | C4: Tipo | D4: Marca | E4: Modelo | F4: S/N | G4: P/N | H4: Operador | I4: Linea | J4: IMEI1 | K4: IMEI2 | L4: Mac Address | M4: Nombre Host | N4: Nuevo Nombre Host | O4: Procesador | P4: Generación Procesador | Q4: Chip Video | R4: Ram | S4: Ram Actual | T4: Almacenamiento | U4: Pantalla | V4: IP | W4: Sistema Operativo | X4: Antivirus | Y4: Office | Z4: Cuenta Gmail | AA4: Clave Gmail | AB4: Fech. Ini Garantía | AC4: Fech. Fin Garantía | AD4: Propiedad | AE4: Estado | AF4: DNI | AG4: Código | AH4: Usuario | AI4: Cargo | AJ4: Centro Costo | AK4: Unidad
B5: PC | C5: Usuario | D5: Dell | H5: Movistar | O5: Intel Core i3 | P5: 1era Gen. | Q5: Intel Integrado | R5: 4 GB DDR3 | T5: 250 GB HHD | U5: 14" | W5: Windows 11 Pro | X5: Si | Y5: MS Office 2007 HB | AD5: HOTELERA COSTA DEL PACIFICO | AE5: Operativo
B6: Laptop | C6: Servidor | D6: Lenovo | H6: Claro | O6: Intel Core i5 | P6: 2da Gen. | Q6: NVIDEA | R6: 8 GB DDR3 | T6: 500 GB HDD | U6: 15" | W6: Windows 11 IoT Enterprise LTSC | X6: No | Y6: MS Office 365 HB | AD6: Prov. DATACONT | AE6: Inoperativo
B7: Monitor | D7: HP | H7: Entel | O7: Intel Core i7 | P7: 3era Gen. | Q7: AMD ATI | R7: 12 GB DDR3 | T7: 1000 GB HDD | U7: 17" | W7: Windows 10 Pro | X7: Pendiente | AE7: Por Revisar
B8: Celular | D8: Toshiba | O8: Intel Core i9 | P8: 4ta Gen. | R8: 16 GB DDR3 | T8: 250 GB SSD | U8: 19" | W8: Windows Server 2008 | X8: N/A | AE8: Por Reparar
B9: Impresora | D9: Samsung | O9: Intel Xeon | P9: 5ta Gen. | R9: 20 GB DDR3 | T9: 480 GB SSD | U9: 20" | W9: Windows Server 2012 | AE9: Por Repotenciar
B10: Servidor | D10: LG | O10: AMD Ryzen | P10: 6ta Gen. | R10: 32 GB DDR3 | T10: 500 GB SSD | U10: 22" | W10: Windows Server 2022 | AE10: Obsoleto
B11: Access Point | D11: ZTE | O11: Movil | P11: 7ma Gen. | R11: 8 GB DDR4 | T11: 1000 GB SSD | U11: 24" | W11: Windows Server 2025 | AE11: Custodia - Operativo
B12: Switch | D12: Apple | O12: Intel Atom | P12: 8va Gen. | R12: 12 GB DDR4 | T12: 16 GB | U12: 27" | W12: Android | AE12: Custodia - Inoperativo
B13: Router | D13: Xiaomi | O13: ARM | P13: 9va Gen. | R13: 16 GB DDR4 | T13: 32gb | U13: 32" | W13: iOS | AE13: Custodia - Por Revisar
B14: Anexos IP | D14: Oppo | O14: Intel Celeron | P14: 10ma Gen. | R14: 20 GB DDR4 | T14: 64 GB | U14: 42" | W14: Windows 7 Pro | AE14: Custodia - Por Reparar
B15: Anexo Analógico | D15: Gigabyte | P15: 11va Gen. | R15: 32 GB DDR4 | T15: 128 GB | U15: 49" | W15: Windows 10 Enterprise | AE15: Custodia - Por Repotenciar
B16: TV | D16: Epson | P16: 12va Gen. | R16: 64 GB DDR4 | T16: 250 GB | U16: 4.7" | W16: Linux | AE16: Custodia - Obsoleto
B17: Parlantes | D17: Canon | P17: 13va Gen. | R17: 128 GB DDR4 | T17: 480 GB SSD + 500 GB HDD | U17: 6.1" | W17: Windows Server 2016
B18: Tablet | D18: Oracle | P18: 14va Gen. | R18: 8 GB DDR5 | T18: 500 GB SSD + 500 GB HDD | U18: 6.6"
B19: Micros | D19: Sharp | P19: Ultra | R19: 12 GB DDR5 | T19: 16 TB RAID | U19: 6.75"
D20: Qnap | R20: 16 GB DDR5 | T20: 6 TB RAID | U20: 6.8"
D21: Honor | R21: 20 GB DDR5 | T21: 1 TB | U21: 8"
D22: Synology | R22: 32 GB DDR5 | T22: 2 TB | U22: 9"
R23: 64 GB DDR5 | T23: 4 TB | U23: 10"
R24: 128 GB DDR5 | U24: 11"
R25: 4GB + 8GB | U25: 12"
R26: 3GB | U26: 8.9"
R27: 2GB
R28: 4GB
R29: 6GB
R30: 8GB

Sheet Suministros Impresoras
B3: Impresora: Epson WF-C5890
B4: Tinta | C4: Código | D4: Cantidad
B5: Negro (BK) | C5: T11A1 | D5: 1
B6: Amarillo (Y) | C6: T11A4 | D6: 3
B7: Magenta (M) | C7: T11A3 | D7: 3
B8: Cian (C) | C8: T11A2 | D8: 2
B9: Caja de Mantenimiento | C9: C9382 | D9: 1
B12: Impresora: Epson WF-C5790
B13: Tinta | C13: Código | D13: Cantidad
B14: Negro (BK) | C14: R04X | D14: 6
B15: Amarillo (Y) | C15: R04L | D15: 8
B16: Magenta (M) | C16: R04L | D16: 3
B17: Cian (C) | C17: R04L | D17: 11
B18: Caja de Mantenimiento | C18: T6716 | D18: 5
B21: Impresora: Epson WF-C869R
B22: Tinta | C22: Código | D22: Cantidad
B23: Negro (BK) | C23: T9741 | D23: 0
B24: Amarillo (Y) | C24: T9744 | D24: 0
B25: Magenta (M) | C25: T9743 | D25: 0
B26: Cian (C) | C26: T9742 | D26: 0
B27: Caja de Mantenimiento | C27: T6714 | D27: 0
B28: Caja de Mantenimiento | C28: T6712 | D28: 1
B33: Impresora: Canon imageRUNNER iR1730i
B34: Cartucho Toner | C34: Código | D34: Cantidad
B35: Negro (BK) | C35: GPR-39 | D35: 5

Sheet Pendientes
B4: Item | C4: Tareas | D4: Observación
B5: 1 | C5: Preparar imagen con sistema operativo actualizado. | D5: Imágenes preparadas en PC Gigabyte - IP: 192.168.0.252
B6: 2 | C6: Preparar archivo inventario | D6: \\10.72.8.101\IT_Files\SWISSOTEL 2025\Inventario 2025 Final.xlsx
B7: 3 | C7: Preparar correlativo hostname | D7: En proceso
B8: 4 | C8: Realizar inventario | D8: En proceso
B9: 5 | C9: Coordinar cambio de equipos en las areas | D9: En proceso
B10: 6 | C10: Actualización de Gary Carpio
B11: 7
B12: 8
B13: 9
B14: 10

Sheet Borrador
B6: Propiedad | C6: Equipo | D6: Marca | E6: Modelo | F6: S/N | G6: IP | H6: Observación | I6: Cantidad Impresoras
B7: Prov. DATACONT | C7: Impresora | D7: Canon | E7: imageRUNNER1730i | F7: QFX05353 | G7: 10.72.8.211 | H7: 1er Piso - Front Desk - Recepción | I7: 1
B8: Prov. DATACONT | C8: Impresora | D8: Canon | E8: imageRUNNER1730i | F8: QFX06116 | G8: 10.72.8.153 | H8: 1er Piso - Front Desk - Recepción | I8: 1
B9: Prov. DATACONT | C9: Impresora | D9: Canon | E9: imageRUNNER1730i | F9: QFX06245 | G9: 10.72.8.215 | H9: 2do Piso - Oficina Auditor de Ingresos | I9: 1
B10: Prov. DATACONT | C10: Impresora | D10: Canon | E10: imageRUNNER1730i | F10: QFX06246 | G10: 10.72.8.207 | H10: 3er Piso - Contabilidad | I10: 1
B11: Prov. DATACONT | C11: Impresora | D11: Epson | E11: WF-C5790 Series | F11: X3B7002433 | G11: 10.72.8.191 | H11: 2do Piso - Oficina Banquetes | I11: 1
B12: Prov. DATACONT | C12: Impresora | D12: Epson | E12: WF-C5790 Series | F12: X3B7003659 | G12: 10.72.8.197 | H12: 3er Piso - Reservas | I12: 1
B13: Prov. DATACONT | C13: Impresora | D13: Epson | E13: WF-C5790 Series | F13: X3B7003660 | G13: 10.72.8.204 | H13: 1er Piso - Room Service | I13: 1
B14: Prov. DATACONT | C14: Impresora | D14: Epson | E14: WF-C5790 Series | F14: X3B7003661 | G14: 10.72.8.132 | H14: 1er Sotano - Steward - Limpieza | I14: 1
B15: Prov. DATACONT | C15: Impresora | D15: Epson | E15: WF-C5790 Series | F15: X3B7003671 | G15: 10.72.8.208 | H15: 1er Piso - Caja Lobby Bar | I15: 1
B16: Prov. DATACONT | C16: Impresora | D16: Epson | E16: WF-C5790 Series | F16: X3B7003703 | G16: 10.9.10.153 | H16: 1er Piso Gym | I16: 1
B17: Prov. DATACONT | C17: Impresora | D17: Epson | E17: WF-C5790 Series | F17: X3B7003711 | G17: 10.72.8.205 | H17: 1er Piso - Recepción - Back Office | I17: 1
B18: Prov. DATACONT | C18: Impresora | D18: Epson | E18: WF-C5790 Series | F18: X3B7003712 | G18: 10.72.8.206 | H18: 1er Piso - Bodega | I18: 1
... B27: Prov. DATACONT | C27: Impresora | D27: Epson | E27: WF-C869R Series | F27: X2SR002748 | G27: 10.72.8.203 | H27: 2do Piso - Seguridad | I27: 1
B28: Total general | I28: 21
B31: Propiedad | C31: Equipo | D31: Marca | E31: Modelo | F31: S/N | G31: IP | H31: Observación | I31: Cantidad Impresoras | J31: Observación
B32: Prov. DATACONT | C32: Impresora | D32: Canon | E32: iR-ADV C3330 | F32: RJQ00596 | G32: 10.72.8.203 | H32: 2do Piso - Seguridad | I32: 1
E33: iR1730i | F33: QFX06245 | G33: 10.72.8.215 | H33: 2do Piso - Oficina Auditor de Ingresos | I33: 1
E34: iR1643i II | F34: 35E33608 | G34: 10.72.8.211 | H34: 1er Piso - Front Desk - Recepción | I34: 1
F35: 35E33607 | G35: 10.72.8.153 | H35: 1er Piso - Front Desk - Recepción | I35: 1
D36: Epson | E36: WF-C5790 Series | F36: X3B7002433 | G36: 10.72.8.191 | H36: 2do Piso - Oficina Banquetes | I36: 1
F37: X3B7003659 | G37: 10.72.8.197 | H37: 3er Piso - Reservas | I37: 1
F38: X3B7003660 | G38: 10.72.8.204 | H38: 1er Piso - Room Service | I38: 1
F39: X3B7003661 | G39: 10.72.8.132 | H39: 1er Sotano - Steward - Limpieza | I39: 1
F40: X3B7003671 | G40: 10.72.8.208 | H40: 1er Piso - Caja Lobby Bar | I40: 1
F41: X3B7003703 | G41: 10.9.10.153 | H41: 1er Piso Gym | I41: 1
F42: X3B7003711 | G42: 10.72.8.205 | H42: 1er Piso - Recepción - Back Office | I42: 1
F43: X3B7003739 | G43: 10.72.10.43 | H43: 1er Piso Compras | I43: 1
B44: Prov. DATACONT | C44: Impresora | D44: Epson | E44: WF-C5790 Series | F44: X3B7003876 | G44: 10.72.8.220 | H44: 1er Piso - Oficina AyB | I44: 1 | J44: Negro
B45: Prov. DATACONT | C45: Impresora | D45: Epson | E45: WF-C5890 Series | F45: XBJZ017266 | G45: 10.72.8.229 | H45: 1er Sotano - Housekeeping | I45: 1 | J45: Negro - Magenta - Cyan
B46: Prov. DATACONT | C46: Impresora | D46: Epson | E46: WF-C5890 Series | F46: XBJZ017602 | G46: 10.72.8.206 | H46: 1er Piso - Bodega | I46: 1 | J46: Amarrillo - Magenta - Caja Mantenimiento
F47: XBJZ017603 | G47: 10.72.8.196 | H47: 1er Piso - Conserge | I47: 1
B48: Prov. DATACONT | C48: Impresora | D48: Epson | E48: WF-C5890 Series | F48: XBJZ021745 | G48: 10.72.8.219 | H48: 1er Piso - Oficina Chef | I48: 1 | J48: Cyan Magenta
F49: XBJZ021772 | G49: 10.72.8.151 | H49: 3er Piso - Gerencia General | I49: 1
F50: XBJZ027512 | G50: 10.72.8.210 | H50: 3er Piso - Ventas | I50: 1
D51: Sharp | E51: MX-3070V | F51: 3500930400 | G51: 10.72.8.200 | H51: 1er Sotano - RRHH - Sistemas | I51: 1
E52: MX-M3070 | F52: 9502370Y00 | G52: 10.72.8.207 | H52: 3er Piso - Contabilidad | I52: 1
B53: Total general | I53: 21
B56: Propiedad | C56: Equipo | D56: Marca | E56: Modelo | F56: S/N | G56: IP | H56: Observación | I56: Cantidad Impresoras | J56: Observación
B57: Prov. DATACONT | C57: Impresora | D57: Canon | E57: iR1730i | F57: QFX06245 | G57: 10.72.8.215 | H57: 2do Piso - Oficina Auditor de Ingresos | I57: 1
E58: iR1643i II | F58: 35E33608 | G58: 10.72.8.211 | H58: 1er Piso - Front Desk - Recepción | I58: 1
F59: 35E33607 | G59: 10.72.8.153 | H59: 1er Piso - Front Desk - Recepción | I59: 1 | J59: Toner Negro
D60: Epson | E60: WF-C5790 Series | F60: X3B7002433 | G60: 10.72.8.191 | H60: 2do Piso - Oficina Banquetes | I60: 1 | J60: Toner Negro
F61: X3B7003659 | G61: 10.72.8.197 | H61: 3er Piso - Reservas | I61: 1 | J61: Magenta
F62: X3B7003660 | G62: 10.72.8.204 | H62: 1er Piso - Room Service | I62: 1
F63: X3B7003661 | G63: 10.72.8.132 | H63: 1er Sotano - Steward - Limpieza | I63: 1 | J63: Negro y Cyan
F64: X3B7003671 | G64: 10.72.8.208 | H64: 1er Piso - Caja Lobby Bar | I64: 1 | J64: Negro y Magenta
F65: X3B7003703 | G65: 10.9.10.153 | H65: 1er Piso Gym | I65: 1
F66: X3B7003711 | G66: 10.72.8.205 | H66: 1er Piso - Recepción - Back Office | I66: 1
F67: X3B7003739 | G67: 10.72.10.43 | H67: 1er Piso Compras | I67: 1
F68: X3B7003876 | G68: 10.72.8.220 | H68: 1er Piso - Oficina AyB | I68: 1
E69: WF-C5890 Series | F69: XBJZ017266 | G69: 10.72.8.229 | H69: 1er Sotano - Housekeeping | I69: 1 | J69: Negro - Magenta - Amarillo - Cyan
F70: XBJZ017602 | G70: 10.72.8.206 | H70: 1er Piso - Bodega | I70: 1
F71: XBJZ017603 | G71: 10.72.8.196 | H71: 1er Piso - Conserge | I71: 1
F72: XBJZ021745 | G72: 10.72.8.219 | H72: 1er Piso - Oficina Chef | I72: 1
F73: XBJZ021772 | G73: 10.72.8.151 | H73: 3er Piso - Gerencia General | I73: 1
F74: XBJZ027512 | G74: 10.72.8.210 | H74: 3er Piso - Ventas | I74: 1
D75: Sharp | E75: MX-3070V | F75: 3500930400 | G75: 10.72.8.200 | H75: 1er Sotano - RRHH - Sistemas | I75: 1
E76: MX-M3070 | F76: 9502370Y00 | G76: 10.72.8.207 | H76: 3er Piso - Contabilidad | I76: 1
F77: 15064216 | G77: 10.72.8.203 | H77: 2do Piso - Seguridad | I77: 1
B78: Total general | I78: 21
B82: Propiedad | C82: Equipo | D82: Marca | E82: Modelo | F82: S/N | G82: IP | H82: Observación | I82: Cantidad Impresoras | J82: Observación
B83: Prov. DATACONT | C83: Impresora | D83: Canon | E83: iR1643i II | F83: 35E33608 | G83: 10.72.8.211 | H83: 1er Piso - Front Desk - Recepción | I83: 1 | J83: Toner Negro
B84: Prov. DATACONT | C84: Impresora | D84: Canon | E84: iR1643i II | F84: 35E33607 | G84: 10.72.8.153 | H84: 1er Piso - Front Desk - Recepción | I84: 1 | J84: Toner Negro
B85: Prov. DATACONT | C85: Impresora | D85: Epson | E85: WF-C5790 Series | F85: X3B7002433 | G85: 10.72.8.191 | H85: 2do Piso - Oficina Banquetes | I85: 1 | J85: Magenta
B86: Prov. DATACONT | C86: Impresora | D86: Epson | E86: WF-C5790 Series | F86: X3B7003660 | G86: 10.72.8.204 | H86: 1er Piso - Room Service | I86: 1 | J86: Negro y Cyan
B87: Prov. DATACONT | C87: Impresora | D87: Epson | E87: WF-C5790 Series | F87: X3B7003661 | G87: 10.72.8.132 | H87: 1er Sotano - Steward - Limpieza | I87: 1 | J87: Negro y Magenta
B88: Prov. DATACONT | C88: Impresora | D88: Epson | E88: WF-C5790 Series | F88: X3B7003876 | G88: 10.72.8.220 | H88: 1er Piso - Oficina AyB | I88: 1 | J88: Negro - Magenta - Amarillo - Cyan

Sheet Hostname
B3: Siglas Ciudad | C3: Siglas del Area | D3: Siglas Cargo # Equipo
B4: LIM | C4: IT | D4: GTI | E4: GTI | F4: Gerente IT
B5: LIM | C5: IT | D5: 1 | E5: IT | F5: Information Technology
B6: LIM | C6: FB | D6: 1 | E6: FB | F6: Food & Beverage
B7: LIM | C7: SM | D7: DR | E7: SM | F7: Sale Manager | G7: DR | H7: Directora Revenue
B8: LIM | C8: SM | D8: GV | E8: GV | F8: Gerente de Ventas
B9: LIM | C9: SM | D9: GE | E9: GE | F9: Gerente de Eventos
B10: LIM | C10: SM | D10: JM | E10: JM | F10: Jefe de Marketing
B11: LIM | C11: SM | D11: DS | E11: DS | F11: Diseñador
B12: LIM | C12: SM | D12: CE | E12: CE | F12: Coordinador de Eventos
B13: LIM | C13: SM | D13: EV | E13: EV | F13: Ejecutiva Ventas
B14: LIM | C14: SM | D14: RS | E14: RS | F14: Reservas
B15: LIM | C15: SM | D15: RV | E15: RV | F15: Revenue
B16: LIM | C16: ACC | D16: 1 | E16: ACC | F16: Accounting
B17: LIM | C17: GG | E17: GG | F17: Gerencia General
B18: LIM | C18: CM | D18: 1 | E18: CM | F18: Consola & Monitoreo
B19: LIM | C19: RD | D19: 1 | E19: RD | F19: Room Divisions
B20: LIM | C20: EN | D20: 1 | E20: EN | F20: Engineering
B21: LIM | C21: PU | D21: 1 | E21: PU | F21: Purchasing
B22: LIM | C22: HR | E22: HR | F22: Human Resources
B23: LIM | C23: SM | D23: GCC | F23: Gerente Congreso y Convenciones
B24: LIM | C24: FB | D24: SW | F24: Food & Beverage | G24: SW | H24: Steward
B25: LIM | C25: FIN | D25: 1 | F25: FINANZAS
B26: LIM | C26: SM | D26: VEN1 | E26: VEN | F26: VENTAS 1
B27: LIM | C27: FD | D27: 1 | F27: FrontDesk
B28: LIM
B29: LIM
B30: LIM
B31: LIM
B32: LIM
